hw4/p1/8to1mux.v
module mux81(out, D0, D1, D2, D3, D4, D5, D6, D7, Sel_Baud_Rate);
    input wire D0, D1, D2, D3, D4, D5, D6, D7;
    input wire[2:0] Sel_Baud_Rate;
    output reg out;
    always@(*) begin
        case(Sel_Baud_Rate)
            3'b000: out=D0;
            3'b001: out=D1;
            3'b010: out=D2;
            3'b011: out=D3;
            3'b100: out=D4;
            3'b101: out=D5;
            3'b110: out=D6;
            3'b111: out=D7;
            default: out=1'b0;
        endcase
    end
endmodule

hw4/p1/8to1mux_tb.v
module mux81_tb ();
    reg clk_read,
        clk_write, 
        rst,
        enable_read, 
        enable_write;

    reg D0, D1, D2, D3, D4, D5, D6, D7;
    reg[2:0] Sel_Baud_Rate;
    wire out;


    integer tb_cycle_number = 1;
    integer total_errors = 0;  // tracking total errors in assertions
    integer i; // loop variable

    //////////// EVENTS //////////////

    // Increment TB cycle number
    event tb_cycle_update;
    initial begin 
        forever @(tb_cycle_update) begin
            tb_cycle_number = tb_cycle_number + 1;
        end
    end

    // Increment error variable for error monitor
    event error;
    initial begin 
        forever @(error) begin
            total_errors = total_errors + 1;
        end
    end

    // Error Monitor
    initial  begin
        $display("\t\tTime, TB Cycle Number,\terror count"); 
        $monitor("\t%d,\t%d", $time, tb_cycle_number, total_errors); 
    end 

    // Watchdog - used for exiting and reports error monitor
    event watchdog;
    initial begin
        forever @(watchdog) begin
            #10 $display("Total Error Count: ", total_errors);
            $finish;
        end
    end

    // Create the 8:1 multiplexer
    mux81 mux_for_clocks(
            .out(out),
            .D0(D0), 
            .D1(D1), 
            .D2(D2), 
            .D3(D3), 
            .D4(D4), 
            .D5(D5), 
            .D6(D6), 
            .D7(D7),
            .Sel_Baud_Rate(Sel_Baud_Rate));


    event randomize_inputs;
    initial begin 
        forever @(randomize_inputs) begin
            D0 = {$random} % 2;
            D1 = {$random} % 2;
            D2 = {$random} % 2;
            D3 = {$random} % 2;
            D4 = {$random} % 2;
            D5 = {$random} % 2;
            D6 = {$random} % 2;
            D7 = {$random} % 2;
            -> tb_cycle_update;
        end
    end


    event cycle_select;
    initial begin 
        forever @(cycle_select) begin
            $display(out);
            Sel_Baud_Rate = 3'b0;
            if (out != D0) -> error;
            #5 Sel_Baud_Rate = Sel_Baud_Rate + 1;
            #5 if (out != D1) -> error;
            #5 Sel_Baud_Rate = Sel_Baud_Rate + 1;
            #5 if (out != D2) -> error;
            #5 Sel_Baud_Rate = Sel_Baud_Rate + 1;
            #5 if (out != D3) -> error;
            #5 Sel_Baud_Rate = Sel_Baud_Rate + 1;
            #5 if (out != D4) -> error;
            #5 Sel_Baud_Rate = Sel_Baud_Rate + 1;
            #5 if (out != D5) -> error;
            #5 Sel_Baud_Rate = Sel_Baud_Rate + 1;
            #5 if (out != D6) -> error;       
            #5 Sel_Baud_Rate = Sel_Baud_Rate + 1;
            #5 if (out != D7) -> error;
            -> tb_cycle_update;
        end
    end

    // Test Case Loop
    always @ (*) begin
        case(tb_cycle_number)
            1: -> randomize_inputs;
            2: -> cycle_select;
            default: -> watchdog;
        endcase
    end

    // Log *vcd file for vieweing in gtkWave
    initial begin
        $dumpfile("8to1mux.vcd");
        $dumpvars(0, mux81_tb);
    end

endmodule

hw4/p1/8to1mux.vcd
$date
	Sun Oct 02 00:30:48 2022
$end
$version
	Icarus Verilog
$end
$timescale
	1s
$end
$scope module mux81_tb $end
$var event 1 ! watchdog $end
$var event 1 " tb_cycle_update $end
$var event 1 # randomize_inputs $end
$var event 1 $ error $end
$var event 1 % cycle_select $end
$var wire 1 & out $end
$var reg 1 ' D0 $end
$var reg 1 ( D1 $end
$var reg 1 ) D2 $end
$var reg 1 * D3 $end
$var reg 1 + D4 $end
$var reg 1 , D5 $end
$var reg 1 - D6 $end
$var reg 1 . D7 $end
$var reg 3 / Sel_Baud_Rate [2:0] $end
$var integer 32 0 tb_cycle_number [31:0] $end
$var integer 32 1 total_errors [31:0] $end
$scope module mux_for_clocks $end
$var wire 1 ' D0 $end
$var wire 1 ( D1 $end
$var wire 1 ) D2 $end
$var wire 1 * D3 $end
$var wire 1 + D4 $end
$var wire 1 , D5 $end
$var wire 1 - D6 $end
$var wire 1 . D7 $end
$var wire 3 2 Sel_Baud_Rate [2:0] $end
$var reg 1 & out $end
$upscope $end
$upscope $end
$enddefinitions $end
$comment Show the parameter values. $end
$dumpall
$end
#0
$dumpvars
b0 2
b0 1
b10 0
b0 /
0.
1-
1,
1+
1*
1)
1(
0'
0&
1%
1$
1#
1"
1!
$end
#5
1&
b1 /
b1 2
#15
b10 /
b10 2
#25
b11 /
b11 2
#35
b100 /
b100 2
#45
b101 /
b101 2
#55
b110 /
b110 2
#65
0&
b111 /
b111 2
#70
1!
b11 0
1"
