hw4/p1/divideby8.v
module divideby8(output wire clock_by_8, 
                  input wire clock, reset);
    reg [3:0] counter;
    assign clock_by_8 = (counter == 7);
    always @ (posedge clock, negedge reset) begin
        if (reset == 0) counter <= 4'b0000;
        else if (counter == 4'd7) counter <= 4'd0;
        else counter <= counter + 1;
    end
endmodule

hw4/p1/divideby8_tb.v
module divideby8_tb();

    wire clock_by_8;
    reg clock, reset;

    integer tb_cycle_number = 1;
    integer total_errors = 0;  // tracking total errors in assertions
    integer i; // loop variable

    //////////// EVENTS //////////////

    // Increment TB cycle number
    event tb_cycle_update;
    initial begin 
        forever @(tb_cycle_update) begin
            tb_cycle_number = tb_cycle_number + 1;
        end
    end

    // Increment error variable for error monitor
    event error;
    initial begin 
        forever @(error) begin
            total_errors = total_errors + 1;
        end
    end

    // Error Monitor
    initial  begin
        $display("\t\tTime, TB Cycle Number,\terror count"); 
        $monitor("\t%d,\t%d", $time, tb_cycle_number, total_errors); 
    end 

    // Watchdog - used for exiting and reports error monitor
    event watchdog;
    initial begin
        forever @(watchdog) begin
            $display("Total Error Count: ", total_errors);
            $finish;
        end
    end
    // absolute timed watchdog
    initial #300 -> watchdog;

    // Create the div8 dvt
    divideby8 dvt(.clock_by_8(clock_by_8),
                   .clock(clock),
                   .reset(reset));
    
    // set clock frequencies, reader is independent of writer
    initial begin
        clock = 1'b0;
        forever #5 clock = ~clock;
    end

    event reset_divby8;
    initial begin 
        forever @(reset_divby8) begin
            reset = 1'b0;
            #10 reset = 1'b1;
            -> tb_cycle_update;
        end
    end


    event case_2;
    initial begin 
        forever @(case_2) begin
            -> tb_cycle_update;
        end
    end

    // Test Case Loop
    always @ (*) begin
        case(tb_cycle_number)
            1: -> reset_divby8;
            //default: -> watchdog;
        endcase
    end

    // Log *vcd file for vieweing in gtkWave
    initial begin
        $dumpfile("divideby8.vcd");
        $dumpvars(0, divideby8_tb);
    end

endmodule

hw4/p1/divideby8.vcd
$date
	Sun Oct 02 15:01:52 2022
$end
$version
	Icarus Verilog
$end
$timescale
	1s
$end
$scope module divideby8_tb $end
$var event 1 ! watchdog $end
$var event 1 " tb_cycle_update $end
$var event 1 # reset_divby8 $end
$var event 1 $ error $end
$var event 1 % case_2 $end
$var wire 1 & clock_by_8 $end
$var reg 1 ' clock $end
$var reg 1 ( reset $end
$var integer 32 ) tb_cycle_number [31:0] $end
$var integer 32 * total_errors [31:0] $end
$scope module dvt $end
$var wire 1 ' clock $end
$var wire 1 ( reset $end
$var wire 1 & clock_by_8 $end
$var reg 4 + counter [3:0] $end
$upscope $end
$upscope $end
$enddefinitions $end
$comment Show the parameter values. $end
$dumpall
$end
#0
$dumpvars
b0 +
b0 *
b1 )
0(
0'
0&
1%
1$
1#
1"
1!
$end
#5
1'
#10
b10 )
0'
1"
1(
#15
b1 +
1'
#20
0'
#25
b10 +
1'
#30
0'
#35
b11 +
1'
#40
0'
#45
b100 +
1'
#50
0'
#55
b101 +
1'
#60
0'
#65
b110 +
1'
#70
0'
#75
1&
b111 +
1'
#80
0'
#85
0&
b0 +
1'
#90
0'
#95
b1 +
1'
#100
0'
#105
b10 +
1'
#110
0'
#115
b11 +
1'
#120
0'
#125
b100 +
1'
#130
0'
#135
b101 +
1'
#140
0'
#145
b110 +
1'
#150
0'
#155
1&
b111 +
1'
#160
0'
#165
0&
b0 +
1'
#170
0'
#175
b1 +
1'
#180
0'
#185
b10 +
1'
#190
0'
#195
b11 +
1'
#200
0'
#205
b100 +
1'
#210
0'
#215
b101 +
1'
#220
0'
#225
b110 +
1'
#230
0'
#235
1&
b111 +
1'
#240
0'
#245
0&
b0 +
1'
#250
0'
#255
b1 +
1'
#260
0'
#265
b10 +
1'
#270
0'
#275
b11 +
1'
#280
0'
#285
b100 +
1'
#290
0'
#295
b101 +
1'
#300
0'
1!
