hw4/p1/divideby256.v
module divideby256(output wire clock_by_256,
                   output wire [7:0] counter256,
                   input wire clock, reset);
    reg [7:0] counter;
    assign counter256 = counter;
    assign clock_by_256 = (counter == 255);
    always @ (posedge clock, negedge reset) begin
        if (reset == 0) counter <= 8'd0;
        else if (counter == 8'd255) counter <= 8'd0;
        else counter <= counter + 1;
    end
endmodule

hw4/p1/divideby256_tb.v
module divideby256_tb();

    wire clock_by_256;
    wire [7:0] counter256;
    reg clock, reset;

    integer tb_cycle_number = 1;
    integer total_errors = 0;  // tracking total errors in assertions
    integer i; // loop variable

    //////////// EVENTS //////////////

    // Increment TB cycle number
    event tb_cycle_update;
    initial begin 
        forever @(tb_cycle_update) begin
            tb_cycle_number = tb_cycle_number + 1;
        end
    end

    // Increment error variable for error monitor
    event error;
    initial begin 
        forever @(error) begin
            total_errors = total_errors + 1;
        end
    end

    // Error Monitor
    initial  begin
        $display("\t\tTime, TB Cycle Number,\terror count"); 
        $monitor("\t%d,\t%d", $time, tb_cycle_number, total_errors); 
    end 

    // Watchdog - used for exiting and reports error monitor
    event watchdog;
    initial begin
        forever @(watchdog) begin
            $display("Total Error Count: ", total_errors);
            $finish;
        end
    end
    // absolute timed watchdog
    initial #5000 -> watchdog;

    // Create the div256 dvt
    divideby256 dvt(.clock_by_256(clock_by_256),
                    .counter256(counter256),
                   .clock(clock),
                   .reset(reset));
    
    // set clock frequencies, reader is independent of writer
    initial begin
        clock = 1'b0;
        forever #5 clock = ~clock;
    end

    event reset_divby256;
    initial begin 
        forever @(reset_divby256) begin
            reset = 1'b0;
            #10 reset = 1'b1;
            -> tb_cycle_update;
        end
    end

    // Test Case Loop
    always @ (*) begin
        case(tb_cycle_number)
            1: -> reset_divby256;
        endcase
    end

    // Log *vcd file for vieweing in gtkWave
    initial begin
        $dumpfile("divideby256.vcd");
        $dumpvars(0, divideby256_tb);
    end

endmodule

hw4/p1/divideby256.vcd
$date
	Sun Oct 02 16:12:07 2022
$end
$version
	Icarus Verilog
$end
$timescale
	1s
$end
$scope module divideby256_tb $end
$var event 1 ! watchdog $end
$var event 1 " tb_cycle_update $end
$var event 1 # reset_divby256 $end
$var event 1 $ error $end
$var wire 8 % counter256 [7:0] $end
$var wire 1 & clock_by_256 $end
$var reg 1 ' clock $end
$var reg 1 ( reset $end
$var integer 32 ) tb_cycle_number [31:0] $end
$var integer 32 * total_errors [31:0] $end
$scope module dvt $end
$var wire 1 ' clock $end
$var wire 8 + counter256 [7:0] $end
$var wire 1 ( reset $end
$var wire 1 & clock_by_256 $end
$var reg 8 , counter [7:0] $end
$upscope $end
$upscope $end
$enddefinitions $end
$comment Show the parameter values. $end
$dumpall
$end
#0
$dumpvars
b0 ,
b0 +
b0 *
b1 )
0(
0'
0&
b0 %
1$
1#
1"
1!
$end
#5
1'
#10
b10 )
0'
1"
1(
#15
b1 %
b1 +
b1 ,
1'
#20
0'
#25
b10 %
b10 +
b10 ,
1'
#30
0'
#35
b11 %
b11 +
b11 ,
1'
#40
0'
#45
b100 %
b100 +
b100 ,
1'
#50
0'
#55
b101 %
b101 +
b101 ,
1'
#60
0'
#65
b110 %
b110 +
b110 ,
1'
#70
0'
#75
b111 %
b111 +
b111 ,
1'
#80
0'
#85
b1000 %
b1000 +
b1000 ,
1'
#90
0'
#95
b1001 %
b1001 +
b1001 ,
1'
#100
0'
#105
b1010 %
b1010 +
b1010 ,
1'
#110
0'
#115
b1011 %
b1011 +
b1011 ,
1'
#120
0'
#125
b1100 %
b1100 +
b1100 ,
1'
#130
0'
#135
b1101 %
b1101 +
b1101 ,
1'
#140
0'
#145
b1110 %
b1110 +
b1110 ,
1'
#150
0'
#155
b1111 %
b1111 +
b1111 ,
1'
#160
0'
#165
b10000 %
b10000 +
b10000 ,
1'
#170
0'
#175
b10001 %
b10001 +
b10001 ,
1'
#180
0'
#185
b10010 %
b10010 +
b10010 ,
1'
#190
0'
#195
b10011 %
b10011 +
b10011 ,
1'
#200
0'
#205
b10100 %
b10100 +
b10100 ,
1'
#210
0'
#215
b10101 %
b10101 +
b10101 ,
1'
#220
0'
#225
b10110 %
b10110 +
b10110 ,
1'
#230
0'
#235
b10111 %
b10111 +
b10111 ,
1'
#240
0'
#245
b11000 %
b11000 +
b11000 ,
1'
#250
0'
#255
b11001 %
b11001 +
b11001 ,
1'
#260
0'
#265
b11010 %
b11010 +
b11010 ,
1'
#270
0'
#275
b11011 %
b11011 +
b11011 ,
1'
#280
0'
#285
b11100 %
b11100 +
b11100 ,
1'
#290
0'
#295
b11101 %
b11101 +
b11101 ,
1'
#300
0'
#305
b11110 %
b11110 +
b11110 ,
1'
#310
0'
#315
b11111 %
b11111 +
b11111 ,
1'
#320
0'
#325
b100000 %
b100000 +
b100000 ,
1'
#330
0'
#335
b100001 %
b100001 +
b100001 ,
1'
#340
0'
#345
b100010 %
b100010 +
b100010 ,
1'
#350
0'
#355
b100011 %
b100011 +
b100011 ,
1'
#360
0'
#365
b100100 %
b100100 +
b100100 ,
1'
#370
0'
#375
b100101 %
b100101 +
b100101 ,
1'
#380
0'
#385
b100110 %
b100110 +
b100110 ,
1'
#390
0'
#395
b100111 %
b100111 +
b100111 ,
1'
#400
0'
#405
b101000 %
b101000 +
b101000 ,
1'
#410
0'
#415
b101001 %
b101001 +
b101001 ,
1'
#420
0'
#425
b101010 %
b101010 +
b101010 ,
1'
#430
0'
#435
b101011 %
b101011 +
b101011 ,
1'
#440
0'
#445
b101100 %
b101100 +
b101100 ,
1'
#450
0'
#455
b101101 %
b101101 +
b101101 ,
1'
#460
0'
#465
b101110 %
b101110 +
b101110 ,
1'
#470
0'
#475
b101111 %
b101111 +
b101111 ,
1'
#480
0'
#485
b110000 %
b110000 +
b110000 ,
1'
#490
0'
#495
b110001 %
b110001 +
b110001 ,
1'
#500
0'
#505
b110010 %
b110010 +
b110010 ,
1'
#510
0'
#515
b110011 %
b110011 +
b110011 ,
1'
#520
0'
#525
b110100 %
b110100 +
b110100 ,
1'
#530
0'
#535
b110101 %
b110101 +
b110101 ,
1'
#540
0'
#545
b110110 %
b110110 +
b110110 ,
1'
#550
0'
#555
b110111 %
b110111 +
b110111 ,
1'
#560
0'
#565
b111000 %
b111000 +
b111000 ,
1'
#570
0'
#575
b111001 %
b111001 +
b111001 ,
1'
#580
0'
#585
b111010 %
b111010 +
b111010 ,
1'
#590
0'
#595
b111011 %
b111011 +
b111011 ,
1'
#600
0'
#605
b111100 %
b111100 +
b111100 ,
1'
#610
0'
#615
b111101 %
b111101 +
b111101 ,
1'
#620
0'
#625
b111110 %
b111110 +
b111110 ,
1'
#630
0'
#635
b111111 %
b111111 +
b111111 ,
1'
#640
0'
#645
b1000000 %
b1000000 +
b1000000 ,
1'
#650
0'
#655
b1000001 %
b1000001 +
b1000001 ,
1'
#660
0'
#665
b1000010 %
b1000010 +
b1000010 ,
1'
#670
0'
#675
b1000011 %
b1000011 +
b1000011 ,
1'
#680
0'
#685
b1000100 %
b1000100 +
b1000100 ,
1'
#690
0'
#695
b1000101 %
b1000101 +
b1000101 ,
1'
#700
0'
#705
b1000110 %
b1000110 +
b1000110 ,
1'
#710
0'
#715
b1000111 %
b1000111 +
b1000111 ,
1'
#720
0'
#725
b1001000 %
b1001000 +
b1001000 ,
1'
#730
0'
#735
b1001001 %
b1001001 +
b1001001 ,
1'
#740
0'
#745
b1001010 %
b1001010 +
b1001010 ,
1'
#750
0'
#755
b1001011 %
b1001011 +
b1001011 ,
1'
#760
0'
#765
b1001100 %
b1001100 +
b1001100 ,
1'
#770
0'
#775
b1001101 %
b1001101 +
b1001101 ,
1'
#780
0'
#785
b1001110 %
b1001110 +
b1001110 ,
1'
#790
0'
#795
b1001111 %
b1001111 +
b1001111 ,
1'
#800
0'
#805
b1010000 %
b1010000 +
b1010000 ,
1'
#810
0'
#815
b1010001 %
b1010001 +
b1010001 ,
1'
#820
0'
#825
b1010010 %
b1010010 +
b1010010 ,
1'
#830
0'
#835
b1010011 %
b1010011 +
b1010011 ,
1'
#840
0'
#845
b1010100 %
b1010100 +
b1010100 ,
1'
#850
0'
#855
b1010101 %
b1010101 +
b1010101 ,
1'
#860
0'
#865
b1010110 %
b1010110 +
b1010110 ,
1'
#870
0'
#875
b1010111 %
b1010111 +
b1010111 ,
1'
#880
0'
#885
b1011000 %
b1011000 +
b1011000 ,
1'
#890
0'
#895
b1011001 %
b1011001 +
b1011001 ,
1'
#900
0'
#905
b1011010 %
b1011010 +
b1011010 ,
1'
#910
0'
#915
b1011011 %
b1011011 +
b1011011 ,
1'
#920
0'
#925
b1011100 %
b1011100 +
b1011100 ,
1'
#930
0'
#935
b1011101 %
b1011101 +
b1011101 ,
1'
#940
0'
#945
b1011110 %
b1011110 +
b1011110 ,
1'
#950
0'
#955
b1011111 %
b1011111 +
b1011111 ,
1'
#960
0'
#965
b1100000 %
b1100000 +
b1100000 ,
1'
#970
0'
#975
b1100001 %
b1100001 +
b1100001 ,
1'
#980
0'
#985
b1100010 %
b1100010 +
b1100010 ,
1'
#990
0'
#995
b1100011 %
b1100011 +
b1100011 ,
1'
#1000
0'
#1005
b1100100 %
b1100100 +
b1100100 ,
1'
#1010
0'
#1015
b1100101 %
b1100101 +
b1100101 ,
1'
#1020
0'
#1025
b1100110 %
b1100110 +
b1100110 ,
1'
#1030
0'
#1035
b1100111 %
b1100111 +
b1100111 ,
1'
#1040
0'
#1045
b1101000 %
b1101000 +
b1101000 ,
1'
#1050
0'
#1055
b1101001 %
b1101001 +
b1101001 ,
1'
#1060
0'
#1065
b1101010 %
b1101010 +
b1101010 ,
1'
#1070
0'
#1075
b1101011 %
b1101011 +
b1101011 ,
1'
#1080
0'
#1085
b1101100 %
b1101100 +
b1101100 ,
1'
#1090
0'
#1095
b1101101 %
b1101101 +
b1101101 ,
1'
#1100
0'
#1105
b1101110 %
b1101110 +
b1101110 ,
1'
#1110
0'
#1115
b1101111 %
b1101111 +
b1101111 ,
1'
#1120
0'
#1125
b1110000 %
b1110000 +
b1110000 ,
1'
#1130
0'
#1135
b1110001 %
b1110001 +
b1110001 ,
1'
#1140
0'
#1145
b1110010 %
b1110010 +
b1110010 ,
1'
#1150
0'
#1155
b1110011 %
b1110011 +
b1110011 ,
1'
#1160
0'
#1165
b1110100 %
b1110100 +
b1110100 ,
1'
#1170
0'
#1175
b1110101 %
b1110101 +
b1110101 ,
1'
#1180
0'
#1185
b1110110 %
b1110110 +
b1110110 ,
1'
#1190
0'
#1195
b1110111 %
b1110111 +
b1110111 ,
1'
#1200
0'
#1205
b1111000 %
b1111000 +
b1111000 ,
1'
#1210
0'
#1215
b1111001 %
b1111001 +
b1111001 ,
1'
#1220
0'
#1225
b1111010 %
b1111010 +
b1111010 ,
1'
#1230
0'
#1235
b1111011 %
b1111011 +
b1111011 ,
1'
#1240
0'
#1245
b1111100 %
b1111100 +
b1111100 ,
1'
#1250
0'
#1255
b1111101 %
b1111101 +
b1111101 ,
1'
#1260
0'
#1265
b1111110 %
b1111110 +
b1111110 ,
1'
#1270
0'
#1275
b1111111 %
b1111111 +
b1111111 ,
1'
#1280
0'
#1285
b10000000 %
b10000000 +
b10000000 ,
1'
#1290
0'
#1295
b10000001 %
b10000001 +
b10000001 ,
1'
#1300
0'
#1305
b10000010 %
b10000010 +
b10000010 ,
1'
#1310
0'
#1315
b10000011 %
b10000011 +
b10000011 ,
1'
#1320
0'
#1325
b10000100 %
b10000100 +
b10000100 ,
1'
#1330
0'
#1335
b10000101 %
b10000101 +
b10000101 ,
1'
#1340
0'
#1345
b10000110 %
b10000110 +
b10000110 ,
1'
#1350
0'
#1355
b10000111 %
b10000111 +
b10000111 ,
1'
#1360
0'
#1365
b10001000 %
b10001000 +
b10001000 ,
1'
#1370
0'
#1375
b10001001 %
b10001001 +
b10001001 ,
1'
#1380
0'
#1385
b10001010 %
b10001010 +
b10001010 ,
1'
#1390
0'
#1395
b10001011 %
b10001011 +
b10001011 ,
1'
#1400
0'
#1405
b10001100 %
b10001100 +
b10001100 ,
1'
#1410
0'
#1415
b10001101 %
b10001101 +
b10001101 ,
1'
#1420
0'
#1425
b10001110 %
b10001110 +
b10001110 ,
1'
#1430
0'
#1435
b10001111 %
b10001111 +
b10001111 ,
1'
#1440
0'
#1445
b10010000 %
b10010000 +
b10010000 ,
1'
#1450
0'
#1455
b10010001 %
b10010001 +
b10010001 ,
1'
#1460
0'
#1465
b10010010 %
b10010010 +
b10010010 ,
1'
#1470
0'
#1475
b10010011 %
b10010011 +
b10010011 ,
1'
#1480
0'
#1485
b10010100 %
b10010100 +
b10010100 ,
1'
#1490
0'
#1495
b10010101 %
b10010101 +
b10010101 ,
1'
#1500
0'
#1505
b10010110 %
b10010110 +
b10010110 ,
1'
#1510
0'
#1515
b10010111 %
b10010111 +
b10010111 ,
1'
#1520
0'
#1525
b10011000 %
b10011000 +
b10011000 ,
1'
#1530
0'
#1535
b10011001 %
b10011001 +
b10011001 ,
1'
#1540
0'
#1545
b10011010 %
b10011010 +
b10011010 ,
1'
#1550
0'
#1555
b10011011 %
b10011011 +
b10011011 ,
1'
#1560
0'
#1565
b10011100 %
b10011100 +
b10011100 ,
1'
#1570
0'
#1575
b10011101 %
b10011101 +
b10011101 ,
1'
#1580
0'
#1585
b10011110 %
b10011110 +
b10011110 ,
1'
#1590
0'
#1595
b10011111 %
b10011111 +
b10011111 ,
1'
#1600
0'
#1605
b10100000 %
b10100000 +
b10100000 ,
1'
#1610
0'
#1615
b10100001 %
b10100001 +
b10100001 ,
1'
#1620
0'
#1625
b10100010 %
b10100010 +
b10100010 ,
1'
#1630
0'
#1635
b10100011 %
b10100011 +
b10100011 ,
1'
#1640
0'
#1645
b10100100 %
b10100100 +
b10100100 ,
1'
#1650
0'
#1655
b10100101 %
b10100101 +
b10100101 ,
1'
#1660
0'
#1665
b10100110 %
b10100110 +
b10100110 ,
1'
#1670
0'
#1675
b10100111 %
b10100111 +
b10100111 ,
1'
#1680
0'
#1685
b10101000 %
b10101000 +
b10101000 ,
1'
#1690
0'
#1695
b10101001 %
b10101001 +
b10101001 ,
1'
#1700
0'
#1705
b10101010 %
b10101010 +
b10101010 ,
1'
#1710
0'
#1715
b10101011 %
b10101011 +
b10101011 ,
1'
#1720
0'
#1725
b10101100 %
b10101100 +
b10101100 ,
1'
#1730
0'
#1735
b10101101 %
b10101101 +
b10101101 ,
1'
#1740
0'
#1745
b10101110 %
b10101110 +
b10101110 ,
1'
#1750
0'
#1755
b10101111 %
b10101111 +
b10101111 ,
1'
#1760
0'
#1765
b10110000 %
b10110000 +
b10110000 ,
1'
#1770
0'
#1775
b10110001 %
b10110001 +
b10110001 ,
1'
#1780
0'
#1785
b10110010 %
b10110010 +
b10110010 ,
1'
#1790
0'
#1795
b10110011 %
b10110011 +
b10110011 ,
1'
#1800
0'
#1805
b10110100 %
b10110100 +
b10110100 ,
1'
#1810
0'
#1815
b10110101 %
b10110101 +
b10110101 ,
1'
#1820
0'
#1825
b10110110 %
b10110110 +
b10110110 ,
1'
#1830
0'
#1835
b10110111 %
b10110111 +
b10110111 ,
1'
#1840
0'
#1845
b10111000 %
b10111000 +
b10111000 ,
1'
#1850
0'
#1855
b10111001 %
b10111001 +
b10111001 ,
1'
#1860
0'
#1865
b10111010 %
b10111010 +
b10111010 ,
1'
#1870
0'
#1875
b10111011 %
b10111011 +
b10111011 ,
1'
#1880
0'
#1885
b10111100 %
b10111100 +
b10111100 ,
1'
#1890
0'
#1895
b10111101 %
b10111101 +
b10111101 ,
1'
#1900
0'
#1905
b10111110 %
b10111110 +
b10111110 ,
1'
#1910
0'
#1915
b10111111 %
b10111111 +
b10111111 ,
1'
#1920
0'
#1925
b11000000 %
b11000000 +
b11000000 ,
1'
#1930
0'
#1935
b11000001 %
b11000001 +
b11000001 ,
1'
#1940
0'
#1945
b11000010 %
b11000010 +
b11000010 ,
1'
#1950
0'
#1955
b11000011 %
b11000011 +
b11000011 ,
1'
#1960
0'
#1965
b11000100 %
b11000100 +
b11000100 ,
1'
#1970
0'
#1975
b11000101 %
b11000101 +
b11000101 ,
1'
#1980
0'
#1985
b11000110 %
b11000110 +
b11000110 ,
1'
#1990
0'
#1995
b11000111 %
b11000111 +
b11000111 ,
1'
#2000
0'
#2005
b11001000 %
b11001000 +
b11001000 ,
1'
#2010
0'
#2015
b11001001 %
b11001001 +
b11001001 ,
1'
#2020
0'
#2025
b11001010 %
b11001010 +
b11001010 ,
1'
#2030
0'
#2035
b11001011 %
b11001011 +
b11001011 ,
1'
#2040
0'
#2045
b11001100 %
b11001100 +
b11001100 ,
1'
#2050
0'
#2055
b11001101 %
b11001101 +
b11001101 ,
1'
#2060
0'
#2065
b11001110 %
b11001110 +
b11001110 ,
1'
#2070
0'
#2075
b11001111 %
b11001111 +
b11001111 ,
1'
#2080
0'
#2085
b11010000 %
b11010000 +
b11010000 ,
1'
#2090
0'
#2095
b11010001 %
b11010001 +
b11010001 ,
1'
#2100
0'
#2105
b11010010 %
b11010010 +
b11010010 ,
1'
#2110
0'
#2115
b11010011 %
b11010011 +
b11010011 ,
1'
#2120
0'
#2125
b11010100 %
b11010100 +
b11010100 ,
1'
#2130
0'
#2135
b11010101 %
b11010101 +
b11010101 ,
1'
#2140
0'
#2145
b11010110 %
b11010110 +
b11010110 ,
1'
#2150
0'
#2155
b11010111 %
b11010111 +
b11010111 ,
1'
#2160
0'
#2165
b11011000 %
b11011000 +
b11011000 ,
1'
#2170
0'
#2175
b11011001 %
b11011001 +
b11011001 ,
1'
#2180
0'
#2185
b11011010 %
b11011010 +
b11011010 ,
1'
#2190
0'
#2195
b11011011 %
b11011011 +
b11011011 ,
1'
#2200
0'
#2205
b11011100 %
b11011100 +
b11011100 ,
1'
#2210
0'
#2215
b11011101 %
b11011101 +
b11011101 ,
1'
#2220
0'
#2225
b11011110 %
b11011110 +
b11011110 ,
1'
#2230
0'
#2235
b11011111 %
b11011111 +
b11011111 ,
1'
#2240
0'
#2245
b11100000 %
b11100000 +
b11100000 ,
1'
#2250
0'
#2255
b11100001 %
b11100001 +
b11100001 ,
1'
#2260
0'
#2265
b11100010 %
b11100010 +
b11100010 ,
1'
#2270
0'
#2275
b11100011 %
b11100011 +
b11100011 ,
1'
#2280
0'
#2285
b11100100 %
b11100100 +
b11100100 ,
1'
#2290
0'
#2295
b11100101 %
b11100101 +
b11100101 ,
1'
#2300
0'
#2305
b11100110 %
b11100110 +
b11100110 ,
1'
#2310
0'
#2315
b11100111 %
b11100111 +
b11100111 ,
1'
#2320
0'
#2325
b11101000 %
b11101000 +
b11101000 ,
1'
#2330
0'
#2335
b11101001 %
b11101001 +
b11101001 ,
1'
#2340
0'
#2345
b11101010 %
b11101010 +
b11101010 ,
1'
#2350
0'
#2355
b11101011 %
b11101011 +
b11101011 ,
1'
#2360
0'
#2365
b11101100 %
b11101100 +
b11101100 ,
1'
#2370
0'
#2375
b11101101 %
b11101101 +
b11101101 ,
1'
#2380
0'
#2385
b11101110 %
b11101110 +
b11101110 ,
1'
#2390
0'
#2395
b11101111 %
b11101111 +
b11101111 ,
1'
#2400
0'
#2405
b11110000 %
b11110000 +
b11110000 ,
1'
#2410
0'
#2415
b11110001 %
b11110001 +
b11110001 ,
1'
#2420
0'
#2425
b11110010 %
b11110010 +
b11110010 ,
1'
#2430
0'
#2435
b11110011 %
b11110011 +
b11110011 ,
1'
#2440
0'
#2445
b11110100 %
b11110100 +
b11110100 ,
1'
#2450
0'
#2455
b11110101 %
b11110101 +
b11110101 ,
1'
#2460
0'
#2465
b11110110 %
b11110110 +
b11110110 ,
1'
#2470
0'
#2475
b11110111 %
b11110111 +
b11110111 ,
1'
#2480
0'
#2485
b11111000 %
b11111000 +
b11111000 ,
1'
#2490
0'
#2495
b11111001 %
b11111001 +
b11111001 ,
1'
#2500
0'
#2505
b11111010 %
b11111010 +
b11111010 ,
1'
#2510
0'
#2515
b11111011 %
b11111011 +
b11111011 ,
1'
#2520
0'
#2525
b11111100 %
b11111100 +
b11111100 ,
1'
#2530
0'
#2535
b11111101 %
b11111101 +
b11111101 ,
1'
#2540
0'
#2545
b11111110 %
b11111110 +
b11111110 ,
1'
#2550
0'
#2555
1&
b11111111 %
b11111111 +
b11111111 ,
1'
#2560
0'
#2565
0&
b0 %
b0 +
b0 ,
1'
#2570
0'
#2575
b1 %
b1 +
b1 ,
1'
#2580
0'
#2585
b10 %
b10 +
b10 ,
1'
#2590
0'
#2595
b11 %
b11 +
b11 ,
1'
#2600
0'
#2605
b100 %
b100 +
b100 ,
1'
#2610
0'
#2615
b101 %
b101 +
b101 ,
1'
#2620
0'
#2625
b110 %
b110 +
b110 ,
1'
#2630
0'
#2635
b111 %
b111 +
b111 ,
1'
#2640
0'
#2645
b1000 %
b1000 +
b1000 ,
1'
#2650
0'
#2655
b1001 %
b1001 +
b1001 ,
1'
#2660
0'
#2665
b1010 %
b1010 +
b1010 ,
1'
#2670
0'
#2675
b1011 %
b1011 +
b1011 ,
1'
#2680
0'
#2685
b1100 %
b1100 +
b1100 ,
1'
#2690
0'
#2695
b1101 %
b1101 +
b1101 ,
1'
#2700
0'
#2705
b1110 %
b1110 +
b1110 ,
1'
#2710
0'
#2715
b1111 %
b1111 +
b1111 ,
1'
#2720
0'
#2725
b10000 %
b10000 +
b10000 ,
1'
#2730
0'
#2735
b10001 %
b10001 +
b10001 ,
1'
#2740
0'
#2745
b10010 %
b10010 +
b10010 ,
1'
#2750
0'
#2755
b10011 %
b10011 +
b10011 ,
1'
#2760
0'
#2765
b10100 %
b10100 +
b10100 ,
1'
#2770
0'
#2775
b10101 %
b10101 +
b10101 ,
1'
#2780
0'
#2785
b10110 %
b10110 +
b10110 ,
1'
#2790
0'
#2795
b10111 %
b10111 +
b10111 ,
1'
#2800
0'
#2805
b11000 %
b11000 +
b11000 ,
1'
#2810
0'
#2815
b11001 %
b11001 +
b11001 ,
1'
#2820
0'
#2825
b11010 %
b11010 +
b11010 ,
1'
#2830
0'
#2835
b11011 %
b11011 +
b11011 ,
1'
#2840
0'
#2845
b11100 %
b11100 +
b11100 ,
1'
#2850
0'
#2855
b11101 %
b11101 +
b11101 ,
1'
#2860
0'
#2865
b11110 %
b11110 +
b11110 ,
1'
#2870
0'
#2875
b11111 %
b11111 +
b11111 ,
1'
#2880
0'
#2885
b100000 %
b100000 +
b100000 ,
1'
#2890
0'
#2895
b100001 %
b100001 +
b100001 ,
1'
#2900
0'
#2905
b100010 %
b100010 +
b100010 ,
1'
#2910
0'
#2915
b100011 %
b100011 +
b100011 ,
1'
#2920
0'
#2925
b100100 %
b100100 +
b100100 ,
1'
#2930
0'
#2935
b100101 %
b100101 +
b100101 ,
1'
#2940
0'
#2945
b100110 %
b100110 +
b100110 ,
1'
#2950
0'
#2955
b100111 %
b100111 +
b100111 ,
1'
#2960
0'
#2965
b101000 %
b101000 +
b101000 ,
1'
#2970
0'
#2975
b101001 %
b101001 +
b101001 ,
1'
#2980
0'
#2985
b101010 %
b101010 +
b101010 ,
1'
#2990
0'
#2995
b101011 %
b101011 +
b101011 ,
1'
#3000
0'
#3005
b101100 %
b101100 +
b101100 ,
1'
#3010
0'
#3015
b101101 %
b101101 +
b101101 ,
1'
#3020
0'
#3025
b101110 %
b101110 +
b101110 ,
1'
#3030
0'
#3035
b101111 %
b101111 +
b101111 ,
1'
#3040
0'
#3045
b110000 %
b110000 +
b110000 ,
1'
#3050
0'
#3055
b110001 %
b110001 +
b110001 ,
1'
#3060
0'
#3065
b110010 %
b110010 +
b110010 ,
1'
#3070
0'
#3075
b110011 %
b110011 +
b110011 ,
1'
#3080
0'
#3085
b110100 %
b110100 +
b110100 ,
1'
#3090
0'
#3095
b110101 %
b110101 +
b110101 ,
1'
#3100
0'
#3105
b110110 %
b110110 +
b110110 ,
1'
#3110
0'
#3115
b110111 %
b110111 +
b110111 ,
1'
#3120
0'
#3125
b111000 %
b111000 +
b111000 ,
1'
#3130
0'
#3135
b111001 %
b111001 +
b111001 ,
1'
#3140
0'
#3145
b111010 %
b111010 +
b111010 ,
1'
#3150
0'
#3155
b111011 %
b111011 +
b111011 ,
1'
#3160
0'
#3165
b111100 %
b111100 +
b111100 ,
1'
#3170
0'
#3175
b111101 %
b111101 +
b111101 ,
1'
#3180
0'
#3185
b111110 %
b111110 +
b111110 ,
1'
#3190
0'
#3195
b111111 %
b111111 +
b111111 ,
1'
#3200
0'
#3205
b1000000 %
b1000000 +
b1000000 ,
1'
#3210
0'
#3215
b1000001 %
b1000001 +
b1000001 ,
1'
#3220
0'
#3225
b1000010 %
b1000010 +
b1000010 ,
1'
#3230
0'
#3235
b1000011 %
b1000011 +
b1000011 ,
1'
#3240
0'
#3245
b1000100 %
b1000100 +
b1000100 ,
1'
#3250
0'
#3255
b1000101 %
b1000101 +
b1000101 ,
1'
#3260
0'
#3265
b1000110 %
b1000110 +
b1000110 ,
1'
#3270
0'
#3275
b1000111 %
b1000111 +
b1000111 ,
1'
#3280
0'
#3285
b1001000 %
b1001000 +
b1001000 ,
1'
#3290
0'
#3295
b1001001 %
b1001001 +
b1001001 ,
1'
#3300
0'
#3305
b1001010 %
b1001010 +
b1001010 ,
1'
#3310
0'
#3315
b1001011 %
b1001011 +
b1001011 ,
1'
#3320
0'
#3325
b1001100 %
b1001100 +
b1001100 ,
1'
#3330
0'
#3335
b1001101 %
b1001101 +
b1001101 ,
1'
#3340
0'
#3345
b1001110 %
b1001110 +
b1001110 ,
1'
#3350
0'
#3355
b1001111 %
b1001111 +
b1001111 ,
1'
#3360
0'
#3365
b1010000 %
b1010000 +
b1010000 ,
1'
#3370
0'
#3375
b1010001 %
b1010001 +
b1010001 ,
1'
#3380
0'
#3385
b1010010 %
b1010010 +
b1010010 ,
1'
#3390
0'
#3395
b1010011 %
b1010011 +
b1010011 ,
1'
#3400
0'
#3405
b1010100 %
b1010100 +
b1010100 ,
1'
#3410
0'
#3415
b1010101 %
b1010101 +
b1010101 ,
1'
#3420
0'
#3425
b1010110 %
b1010110 +
b1010110 ,
1'
#3430
0'
#3435
b1010111 %
b1010111 +
b1010111 ,
1'
#3440
0'
#3445
b1011000 %
b1011000 +
b1011000 ,
1'
#3450
0'
#3455
b1011001 %
b1011001 +
b1011001 ,
1'
#3460
0'
#3465
b1011010 %
b1011010 +
b1011010 ,
1'
#3470
0'
#3475
b1011011 %
b1011011 +
b1011011 ,
1'
#3480
0'
#3485
b1011100 %
b1011100 +
b1011100 ,
1'
#3490
0'
#3495
b1011101 %
b1011101 +
b1011101 ,
1'
#3500
0'
#3505
b1011110 %
b1011110 +
b1011110 ,
1'
#3510
0'
#3515
b1011111 %
b1011111 +
b1011111 ,
1'
#3520
0'
#3525
b1100000 %
b1100000 +
b1100000 ,
1'
#3530
0'
#3535
b1100001 %
b1100001 +
b1100001 ,
1'
#3540
0'
#3545
b1100010 %
b1100010 +
b1100010 ,
1'
#3550
0'
#3555
b1100011 %
b1100011 +
b1100011 ,
1'
#3560
0'
#3565
b1100100 %
b1100100 +
b1100100 ,
1'
#3570
0'
#3575
b1100101 %
b1100101 +
b1100101 ,
1'
#3580
0'
#3585
b1100110 %
b1100110 +
b1100110 ,
1'
#3590
0'
#3595
b1100111 %
b1100111 +
b1100111 ,
1'
#3600
0'
#3605
b1101000 %
b1101000 +
b1101000 ,
1'
#3610
0'
#3615
b1101001 %
b1101001 +
b1101001 ,
1'
#3620
0'
#3625
b1101010 %
b1101010 +
b1101010 ,
1'
#3630
0'
#3635
b1101011 %
b1101011 +
b1101011 ,
1'
#3640
0'
#3645
b1101100 %
b1101100 +
b1101100 ,
1'
#3650
0'
#3655
b1101101 %
b1101101 +
b1101101 ,
1'
#3660
0'
#3665
b1101110 %
b1101110 +
b1101110 ,
1'
#3670
0'
#3675
b1101111 %
b1101111 +
b1101111 ,
1'
#3680
0'
#3685
b1110000 %
b1110000 +
b1110000 ,
1'
#3690
0'
#3695
b1110001 %
b1110001 +
b1110001 ,
1'
#3700
0'
#3705
b1110010 %
b1110010 +
b1110010 ,
1'
#3710
0'
#3715
b1110011 %
b1110011 +
b1110011 ,
1'
#3720
0'
#3725
b1110100 %
b1110100 +
b1110100 ,
1'
#3730
0'
#3735
b1110101 %
b1110101 +
b1110101 ,
1'
#3740
0'
#3745
b1110110 %
b1110110 +
b1110110 ,
1'
#3750
0'
#3755
b1110111 %
b1110111 +
b1110111 ,
1'
#3760
0'
#3765
b1111000 %
b1111000 +
b1111000 ,
1'
#3770
0'
#3775
b1111001 %
b1111001 +
b1111001 ,
1'
#3780
0'
#3785
b1111010 %
b1111010 +
b1111010 ,
1'
#3790
0'
#3795
b1111011 %
b1111011 +
b1111011 ,
1'
#3800
0'
#3805
b1111100 %
b1111100 +
b1111100 ,
1'
#3810
0'
#3815
b1111101 %
b1111101 +
b1111101 ,
1'
#3820
0'
#3825
b1111110 %
b1111110 +
b1111110 ,
1'
#3830
0'
#3835
b1111111 %
b1111111 +
b1111111 ,
1'
#3840
0'
#3845
b10000000 %
b10000000 +
b10000000 ,
1'
#3850
0'
#3855
b10000001 %
b10000001 +
b10000001 ,
1'
#3860
0'
#3865
b10000010 %
b10000010 +
b10000010 ,
1'
#3870
0'
#3875
b10000011 %
b10000011 +
b10000011 ,
1'
#3880
0'
#3885
b10000100 %
b10000100 +
b10000100 ,
1'
#3890
0'
#3895
b10000101 %
b10000101 +
b10000101 ,
1'
#3900
0'
#3905
b10000110 %
b10000110 +
b10000110 ,
1'
#3910
0'
#3915
b10000111 %
b10000111 +
b10000111 ,
1'
#3920
0'
#3925
b10001000 %
b10001000 +
b10001000 ,
1'
#3930
0'
#3935
b10001001 %
b10001001 +
b10001001 ,
1'
#3940
0'
