hw4/p1/divideby8.v
module divideby8(output wire clock_by_8, 
                  input wire clock, reset);
    reg [3:0] counter;
    assign clock_by_8 = (counter == 7);
    always @ (posedge clock, negedge reset) begin
        if (reset == 0) counter <= 4'b0000;
        else if (counter == 4'd7) counter <= 4'd0;
        else counter <= counter + 1;
    end
endmodule

hw4/p1/8to1mux.v
module mux81(out, D0, D1, D2, D3, D4, D5, D6, D7, Sel_Baud_Rate);
    input wire D0, D1, D2, D3, D4, D5, D6, D7;
    input wire[2:0] Sel_Baud_Rate;
    output reg out;
    always@(*) begin
        case(Sel_Baud_Rate)
            3'b000: out<=D0;
            3'b001: out<=D1;
            3'b010: out<=D2;
            3'b011: out<=D3;
            3'b100: out<=D4;
            3'b101: out<=D5;
            3'b110: out<=D6;
            3'b111: out<=D7;
            default: out<=1'b0;
        endcase
    end
endmodule

hw4/p1/divideby256.v
module divideby256(output wire clock_by_256,
                   output wire [7:0] counter256,
                   input wire clock, reset);
    reg [7:0] counter;
    assign counter256 = counter;
    assign clock_by_256 = (counter == 255);
    always @ (posedge clock, negedge reset) begin
        if (reset == 0) counter <= 8'd0;
        else if (counter == 8'd255) counter <= 8'd0;
        else counter <= counter + 1;
    end
endmodule

hw4/p1/divideby13.v
module divideby13(output wire sys_clock_by_13, 
                  input wire sys_clock, reset);
    reg [3:0] temp;
    assign sys_clock_by_13 = temp[3];
    wire clk_1 = (temp == 12);
    wire clk_2 = (temp > 6);
    always @ (posedge sys_clock, negedge reset) begin
        if (reset == 0) temp <= 4'b0000;
        else if (temp == 4'd12) temp <= 4'd0;
        else temp <= temp + 1;
    end
endmodule

hw4/p1/uart.v
module uart_clk_gen(output wire Clock, Sample_clock, 
                  input wire Sys_clock, reset,
                  input [2:0] Sel_Baud_Rate);
    
    wire sys_clock_by_13;
    wire clock_by_256;
    wire [7:0] counter256;

    // Divide_By_13
    divideby13 Divide_By_13(.sys_clock_by_13(sys_clock_by_13),
                   .sys_clock(Sys_clock),
                   .reset(reset));

    // Divide_By_256
    divideby256 Divide_By_256(.clock_by_256(clock_by_256),
                    .counter256(counter256),
                   .clock(sys_clock_by_13),
                   .reset(reset));

    // 8:1 multiplexer
    mux81 Mux_For_Clocks(
            .out(Clock),
            .D0(counter256[0]), 
            .D1(counter256[1]), 
            .D2(counter256[2]), 
            .D3(counter256[3]), 
            .D4(counter256[4]), 
            .D5(counter256[5]), 
            .D6(counter256[6]), 
            .D7(counter256[7]),
            .Sel_Baud_Rate(Sel_Baud_Rate));

    // Divide_By_8
    divideby8 Divide_By_8(.clock_by_8(Sample_clock),
                  .clock(Clock),
                  .reset(reset));

endmodule

hw4/p1/uart_tb.v
module uart_clk_gen_tb();

    integer tb_cycle_number = 1;
    integer total_errors = 0;  // tracking total errors in assertions
    integer i; // loop variable

    // Inputs
    reg Sys_clock, reset;
    reg [2:0] Sel_Baud_Rate;
    // Outputs
    wire Clock, Sample_clock;
    //////////// EVENTS //////////////

    // Increment TB cycle number
    event tb_cycle_update;
    initial begin 
        forever @(tb_cycle_update) begin
            tb_cycle_number = tb_cycle_number + 1;
        end
    end

    // Increment error variable for error monitor
    event error;
    initial begin 
        forever @(error) begin
            total_errors = total_errors + 1;
        end
    end

    // Error Monitor
    initial  begin
        $display("\t\tTime, TB Cycle Number,\terror count"); 
        $monitor("\t%d,\t%d", $time, tb_cycle_number, total_errors); 
    end 

    // Watchdog - used for exiting and reports error monitor
    event watchdog;
    initial begin
        forever @(watchdog) begin
            $display("Total Error Count: ", total_errors);
            $finish;
        end
    end
    // absolute timed watchdog
    initial #5000 -> watchdog;

    // Create the dvt

    uart_clk_gen dvt(// Outputs
                     .Clock(Clock),
                     .Sample_clock(Sample_clock),
                     // Inputs
                     .Sys_clock(Sys_clock),
                     .reset(reset),
                     .Sel_Baud_Rate(Sel_Baud_Rate));
    
    initial begin
        Sys_clock = 1'b0;
        forever #5 Sys_clock = ~Sys_clock;
    end

    event reset_uart;
    initial begin 
        forever @(reset_uart) begin
            reset = 1'b0;
            #10 reset = 1'b1;
            Sel_Baud_Rate = 3'b000;
            -> tb_cycle_update;
        end
    end

    event init_baud;
    initial begin 
        forever @(init_baud) begin

            -> tb_cycle_update;
        end
    end

    // Test Case Loop
    always @ (*) begin
        case(tb_cycle_number)
            1: -> reset_uart;
            2: -> init_baud;
        endcase
    end

    // Log *vcd file for vieweing in gtkWave
    initial begin
        $dumpfile("uart_clk_gen.vcd");
        $dumpvars(0, uart_clk_gen_tb);
    end

endmodule

hw4/p1/uart_clk_gen.vcd
$date
	Sun Oct 02 16:33:12 2022
$end
$version
	Icarus Verilog
$end
$timescale
	1s
$end
$scope module uart_clk_gen_tb $end
$var event 1 ! watchdog $end
$var event 1 " tb_cycle_update $end
$var event 1 # reset_uart $end
$var event 1 $ init_baud $end
$var event 1 % error $end
$var wire 1 & Sample_clock $end
$var wire 1 ' Clock $end
$var reg 3 ( Sel_Baud_Rate [2:0] $end
$var reg 1 ) Sys_clock $end
$var reg 1 * reset $end
$var integer 32 + tb_cycle_number [31:0] $end
$var integer 32 , total_errors [31:0] $end
$scope module dvt $end
$var wire 3 - Sel_Baud_Rate [2:0] $end
$var wire 1 ) Sys_clock $end
$var wire 1 * reset $end
$var wire 1 . sys_clock_by_13 $end
$var wire 8 / counter256 [7:0] $end
$var wire 1 0 clock_by_256 $end
$var wire 1 & Sample_clock $end
$var wire 1 ' Clock $end
$scope module Divide_By_13 $end
$var wire 1 * reset $end
$var wire 1 ) sys_clock $end
$var wire 1 . sys_clock_by_13 $end
$var wire 1 1 clk_2 $end
$var wire 1 2 clk_1 $end
$var reg 4 3 temp [3:0] $end
$upscope $end
$scope module Divide_By_256 $end
$var wire 1 . clock $end
$var wire 8 4 counter256 [7:0] $end
$var wire 1 * reset $end
$var wire 1 0 clock_by_256 $end
$var reg 8 5 counter [7:0] $end
$upscope $end
$scope module Divide_By_8 $end
$var wire 1 * reset $end
$var wire 1 & clock_by_8 $end
$var wire 1 ' clock $end
$var reg 4 6 counter [3:0] $end
$upscope $end
$scope module Mux_For_Clocks $end
$var wire 1 7 D0 $end
$var wire 1 8 D1 $end
$var wire 1 9 D2 $end
$var wire 1 : D3 $end
$var wire 1 ; D4 $end
$var wire 1 < D5 $end
$var wire 1 = D6 $end
$var wire 1 > D7 $end
$var wire 3 ? Sel_Baud_Rate [2:0] $end
$var reg 1 ' out $end
$upscope $end
$upscope $end
$upscope $end
$enddefinitions $end
$comment Show the parameter values. $end
$dumpall
$end
#0
$dumpvars
bx ?
0>
0=
0<
0;
0:
09
08
07
b0 6
b0 5
b0 4
b0 3
02
01
00
b0 /
0.
bx -
b0 ,
b1 +
0*
0)
bx (
0'
0&
1%
1$
1#
1"
1!
$end
#5
1)
#10
1$
b11 +
0)
1"
b0 (
b0 -
b0 ?
1*
#15
b1 3
1)
#20
0)
#25
b10 3
1)
#30
0)
#35
b11 3
1)
#40
0)
#45
b100 3
1)
#50
0)
#55
b101 3
1)
#60
0)
#65
b110 3
1)
#70
0)
#75
11
b111 3
1)
#80
0)
#85
b1 6
1'
17
b1 /
b1 4
b1 5
1.
b1000 3
1)
#90
0)
#95
b1001 3
1)
#100
0)
#105
b1010 3
1)
#110
0)
#115
b1011 3
1)
#120
0)
#125
12
b1100 3
1)
#130
0)
#135
0.
02
01
b0 3
1)
#140
0)
#145
b1 3
1)
#150
0)
#155
b10 3
1)
#160
0)
#165
b11 3
1)
#170
0)
#175
b100 3
1)
#180
0)
#185
b101 3
1)
#190
0)
#195
b110 3
1)
#200
0)
#205
11
b111 3
1)
#210
0)
#215
0'
18
07
b10 /
b10 4
b10 5
1.
b1000 3
1)
#220
0)
#225
b1001 3
1)
#230
0)
#235
b1010 3
1)
#240
0)
#245
b1011 3
1)
#250
0)
#255
12
b1100 3
1)
#260
0)
#265
0.
02
01
b0 3
1)
#270
0)
#275
b1 3
1)
#280
0)
#285
b10 3
1)
#290
0)
#295
b11 3
1)
#300
0)
#305
b100 3
1)
#310
0)
#315
b101 3
1)
#320
0)
#325
b110 3
1)
#330
0)
#335
11
b111 3
1)
#340
0)
#345
b10 6
1'
17
b11 /
b11 4
b11 5
1.
b1000 3
1)
#350
0)
#355
b1001 3
1)
#360
0)
#365
b1010 3
1)
#370
0)
#375
b1011 3
1)
#380
0)
#385
12
b1100 3
1)
#390
0)
#395
0.
02
01
b0 3
1)
#400
0)
#405
b1 3
1)
#410
0)
#415
b10 3
1)
#420
0)
#425
b11 3
1)
#430
0)
#435
b100 3
1)
#440
0)
#445
b101 3
1)
#450
0)
#455
b110 3
1)
#460
0)
#465
11
b111 3
1)
#470
0)
#475
0'
19
08
07
b100 /
b100 4
b100 5
1.
b1000 3
1)
#480
0)
#485
b1001 3
1)
#490
0)
#495
b1010 3
1)
#500
0)
#505
b1011 3
1)
#510
0)
#515
12
b1100 3
1)
#520
0)
#525
0.
02
01
b0 3
1)
#530
0)
#535
b1 3
1)
#540
0)
#545
b10 3
1)
#550
0)
#555
b11 3
1)
#560
0)
#565
b100 3
1)
#570
0)
#575
b101 3
1)
#580
0)
#585
b110 3
1)
#590
0)
#595
11
b111 3
1)
#600
0)
#605
b11 6
1'
17
b101 /
b101 4
b101 5
1.
b1000 3
1)
#610
0)
#615
b1001 3
1)
#620
0)
#625
b1010 3
1)
#630
0)
#635
b1011 3
1)
#640
0)
#645
12
b1100 3
1)
#650
0)
#655
0.
02
01
b0 3
1)
#660
0)
#665
b1 3
1)
#670
0)
#675
b10 3
1)
#680
0)
#685
b11 3
1)
#690
0)
#695
b100 3
1)
#700
0)
#705
b101 3
1)
#710
0)
#715
b110 3
1)
#720
0)
#725
11
b111 3
1)
#730
0)
#735
0'
18
07
b110 /
b110 4
b110 5
1.
b1000 3
1)
#740
0)
#745
b1001 3
1)
#750
0)
#755
b1010 3
1)
#760
0)
#765
b1011 3
1)
#770
0)
#775
12
b1100 3
1)
#780
0)
#785
0.
02
01
b0 3
1)
#790
0)
#795
b1 3
1)
#800
0)
#805
b10 3
1)
#810
0)
#815
b11 3
1)
#820
0)
#825
b100 3
1)
#830
0)
#835
b101 3
1)
#840
0)
#845
b110 3
1)
#850
0)
#855
11
b111 3
1)
#860
0)
#865
b100 6
1'
17
b111 /
b111 4
b111 5
1.
b1000 3
1)
#870
0)
#875
b1001 3
1)
#880
0)
#885
b1010 3
1)
#890
0)
#895
b1011 3
1)
#900
0)
#905
12
b1100 3
1)
#910
0)
#915
0.
02
01
b0 3
1)
#920
0)
#925
b1 3
1)
#930
0)
#935
b10 3
1)
#940
0)
#945
b11 3
1)
#950
0)
#955
b100 3
1)
#960
0)
#965
b101 3
1)
#970
0)
#975
b110 3
1)
#980
0)
#985
11
b111 3
1)
#990
0)
#995
0'
1:
09
08
07
b1000 /
b1000 4
b1000 5
1.
b1000 3
1)
#1000
0)
#1005
b1001 3
1)
#1010
0)
#1015
b1010 3
1)
#1020
0)
#1025
b1011 3
1)
#1030
0)
#1035
12
b1100 3
1)
#1040
0)
#1045
0.
02
01
b0 3
1)
#1050
0)
#1055
b1 3
1)
#1060
0)
#1065
b10 3
1)
#1070
0)
#1075
b11 3
1)
#1080
0)
#1085
b100 3
1)
#1090
0)
#1095
b101 3
1)
#1100
0)
#1105
b110 3
1)
#1110
0)
#1115
11
b111 3
1)
#1120
0)
#1125
b101 6
1'
17
b1001 /
b1001 4
b1001 5
1.
b1000 3
1)
#1130
0)
#1135
b1001 3
1)
#1140
0)
#1145
b1010 3
1)
#1150
0)
#1155
b1011 3
1)
#1160
0)
#1165
12
b1100 3
1)
#1170
0)
#1175
0.
02
01
b0 3
1)
#1180
0)
#1185
b1 3
1)
#1190
0)
#1195
b10 3
1)
#1200
0)
#1205
b11 3
1)
#1210
0)
#1215
b100 3
1)
#1220
0)
#1225
b101 3
1)
#1230
0)
#1235
b110 3
1)
#1240
0)
#1245
11
b111 3
1)
#1250
0)
#1255
0'
18
07
b1010 /
b1010 4
b1010 5
1.
b1000 3
1)
#1260
0)
#1265
b1001 3
1)
#1270
0)
#1275
b1010 3
1)
#1280
0)
#1285
b1011 3
1)
#1290
0)
#1295
12
b1100 3
1)
#1300
0)
#1305
0.
02
01
b0 3
1)
#1310
0)
#1315
b1 3
1)
#1320
0)
#1325
b10 3
1)
#1330
0)
#1335
b11 3
1)
#1340
0)
#1345
b100 3
1)
#1350
0)
#1355
b101 3
1)
#1360
0)
#1365
b110 3
1)
#1370
0)
#1375
11
b111 3
1)
#1380
0)
#1385
b110 6
1'
17
b1011 /
b1011 4
b1011 5
1.
b1000 3
1)
#1390
0)
#1395
b1001 3
1)
#1400
0)
#1405
b1010 3
1)
#1410
0)
#1415
b1011 3
1)
#1420
0)
#1425
12
b1100 3
1)
#1430
0)
#1435
0.
02
01
b0 3
1)
#1440
0)
#1445
b1 3
1)
#1450
0)
#1455
b10 3
1)
#1460
0)
#1465
b11 3
1)
#1470
0)
#1475
b100 3
1)
#1480
0)
#1485
b101 3
1)
#1490
0)
#1495
b110 3
1)
#1500
0)
#1505
11
b111 3
1)
#1510
0)
#1515
0'
19
08
07
b1100 /
b1100 4
b1100 5
1.
b1000 3
1)
#1520
0)
#1525
b1001 3
1)
#1530
0)
#1535
b1010 3
1)
#1540
0)
#1545
b1011 3
1)
#1550
0)
#1555
12
b1100 3
1)
#1560
0)
#1565
0.
02
01
b0 3
1)
#1570
0)
#1575
b1 3
1)
#1580
0)
#1585
b10 3
1)
#1590
0)
#1595
b11 3
1)
#1600
0)
#1605
b100 3
1)
#1610
0)
#1615
b101 3
1)
#1620
0)
#1625
b110 3
1)
#1630
0)
#1635
11
b111 3
1)
#1640
0)
#1645
1&
b111 6
1'
17
b1101 /
b1101 4
b1101 5
1.
b1000 3
1)
#1650
0)
#1655
b1001 3
1)
#1660
0)
#1665
b1010 3
1)
#1670
0)
#1675
b1011 3
1)
#1680
0)
#1685
12
b1100 3
1)
#1690
0)
#1695
0.
02
01
b0 3
1)
#1700
0)
#1705
b1 3
1)
#1710
0)
#1715
b10 3
1)
#1720
0)
#1725
b11 3
1)
#1730
0)
#1735
b100 3
1)
#1740
0)
#1745
b101 3
1)
#1750
0)
#1755
b110 3
1)
#1760
0)
#1765
11
b111 3
1)
#1770
0)
#1775
0'
18
07
b1110 /
b1110 4
b1110 5
1.
b1000 3
1)
#1780
0)
#1785
b1001 3
1)
#1790
0)
#1795
b1010 3
1)
#1800
0)
#1805
b1011 3
1)
#1810
0)
#1815
12
b1100 3
1)
#1820
0)
#1825
0.
02
01
b0 3
1)
#1830
0)
#1835
b1 3
1)
#1840
0)
#1845
b10 3
1)
#1850
0)
#1855
b11 3
1)
#1860
0)
#1865
b100 3
1)
#1870
0)
#1875
b101 3
1)
#1880
0)
#1885
b110 3
1)
#1890
0)
#1895
11
b111 3
1)
#1900
0)
#1905
0&
b0 6
1'
17
b1111 /
b1111 4
b1111 5
1.
b1000 3
1)
#1910
0)
#1915
b1001 3
1)
#1920
0)
#1925
b1010 3
1)
#1930
0)
#1935
b1011 3
1)
#1940
0)
#1945
12
b1100 3
1)
#1950
0)
#1955
0.
02
01
b0 3
1)
#1960
0)
#1965
b1 3
1)
#1970
0)
#1975
b10 3
1)
#1980
0)
#1985
b11 3
1)
#1990
0)
#1995
b100 3
1)
#2000
0)
#2005
b101 3
1)
#2010
0)
#2015
b110 3
1)
#2020
0)
#2025
11
b111 3
1)
#2030
0)
#2035
0'
1;
0:
09
08
07
b10000 /
b10000 4
b10000 5
1.
b1000 3
1)
#2040
0)
#2045
b1001 3
1)
#2050
0)
#2055
b1010 3
1)
#2060
0)
#2065
b1011 3
1)
#2070
0)
#2075
12
b1100 3
1)
#2080
0)
#2085
0.
02
01
b0 3
1)
#2090
0)
#2095
b1 3
1)
#2100
0)
#2105
b10 3
1)
#2110
0)
#2115
b11 3
1)
#2120
0)
#2125
b100 3
1)
#2130
0)
#2135
b101 3
1)
#2140
0)
#2145
b110 3
1)
#2150
0)
#2155
11
b111 3
1)
#2160
0)
#2165
b1 6
1'
17
b10001 /
b10001 4
b10001 5
1.
b1000 3
1)
#2170
0)
#2175
b1001 3
1)
#2180
0)
#2185
b1010 3
1)
#2190
0)
#2195
b1011 3
1)
#2200
0)
#2205
12
b1100 3
1)
#2210
0)
#2215
0.
02
01
b0 3
1)
#2220
0)
#2225
b1 3
1)
#2230
0)
#2235
b10 3
1)
#2240
0)
#2245
b11 3
1)
#2250
0)
#2255
b100 3
1)
#2260
0)
#2265
b101 3
1)
#2270
0)
#2275
b110 3
1)
#2280
0)
#2285
11
b111 3
1)
#2290
0)
#2295
0'
18
07
b10010 /
b10010 4
b10010 5
1.
b1000 3
1)
#2300
0)
#2305
b1001 3
1)
#2310
0)
#2315
b1010 3
1)
#2320
0)
#2325
b1011 3
1)
#2330
0)
#2335
12
b1100 3
1)
#2340
0)
#2345
0.
02
01
b0 3
1)
#2350
0)
#2355
b1 3
1)
#2360
0)
#2365
b10 3
1)
#2370
0)
#2375
b11 3
1)
#2380
0)
#2385
b100 3
1)
#2390
0)
#2395
b101 3
1)
#2400
0)
#2405
b110 3
1)
#2410
0)
#2415
11
b111 3
1)
#2420
0)
#2425
b10 6
1'
17
b10011 /
b10011 4
b10011 5
1.
b1000 3
1)
#2430
0)
#2435
b1001 3
1)
#2440
0)
#2445
b1010 3
1)
#2450
0)
#2455
b1011 3
1)
#2460
0)
#2465
12
b1100 3
1)
#2470
0)
#2475
0.
02
01
b0 3
1)
#2480
0)
#2485
b1 3
1)
#2490
0)
#2495
b10 3
1)
#2500
0)
#2505
b11 3
1)
#2510
0)
#2515
b100 3
1)
#2520
0)
#2525
b101 3
1)
#2530
0)
#2535
b110 3
1)
#2540
0)
#2545
11
b111 3
1)
#2550
0)
#2555
0'
19
08
07
b10100 /
b10100 4
b10100 5
1.
b1000 3
1)
#2560
0)
#2565
b1001 3
1)
#2570
0)
#2575
b1010 3
1)
#2580
0)
#2585
b1011 3
1)
#2590
0)
#2595
12
b1100 3
1)
#2600
0)
#2605
0.
02
01
b0 3
1)
#2610
0)
#2615
b1 3
1)
#2620
0)
#2625
b10 3
1)
#2630
0)
#2635
b11 3
1)
#2640
0)
#2645
b100 3
1)
#2650
0)
#2655
b101 3
1)
#2660
0)
#2665
b110 3
1)
#2670
0)
#2675
11
b111 3
1)
#2680
0)
#2685
b11 6
1'
17
b10101 /
b10101 4
b10101 5
1.
b1000 3
1)
#2690
0)
#2695
b1001 3
1)
#2700
0)
#2705
b1010 3
1)
#2710
0)
#2715
b1011 3
1)
#2720
0)
#2725
12
b1100 3
1)
#2730
0)
#2735
0.
02
01
b0 3
1)
#2740
0)
#2745
b1 3
1)
#2750
0)
#2755
b10 3
1)
#2760
0)
#2765
b11 3
1)
#2770
0)
#2775
b100 3
1)
#2780
0)
#2785
b101 3
1)
#2790
0)
#2795
b110 3
1)
#2800
0)
#2805
11
b111 3
1)
#2810
0)
#2815
0'
18
07
b10110 /
b10110 4
b10110 5
1.
b1000 3
1)
#2820
0)
#2825
b1001 3
1)
#2830
0)
#2835
b1010 3
1)
#2840
0)
#2845
b1011 3
1)
#2850
0)
#2855
12
b1100 3
1)
#2860
0)
#2865
0.
02
01
b0 3
1)
#2870
0)
#2875
b1 3
1)
#2880
0)
#2885
b10 3
1)
#2890
0)
#2895
b11 3
1)
#2900
0)
#2905
b100 3
1)
#2910
0)
#2915
b101 3
1)
#2920
0)
#2925
b110 3
1)
#2930
0)
#2935
11
b111 3
1)
#2940
0)
#2945
b100 6
1'
17
b10111 /
b10111 4
b10111 5
1.
b1000 3
1)
#2950
0)
#2955
b1001 3
1)
#2960
0)
#2965
b1010 3
1)
#2970
0)
#2975
b1011 3
1)
#2980
0)
#2985
12
b1100 3
1)
#2990
0)
#2995
0.
02
01
b0 3
1)
#3000
0)
#3005
b1 3
1)
#3010
0)
#3015
b10 3
1)
#3020
0)
#3025
b11 3
1)
#3030
0)
#3035
b100 3
1)
#3040
0)
#3045
b101 3
1)
#3050
0)
#3055
b110 3
1)
#3060
0)
#3065
11
b111 3
1)
#3070
0)
#3075
0'
1:
09
08
07
b11000 /
b11000 4
b11000 5
1.
b1000 3
1)
#3080
0)
#3085
b1001 3
1)
#3090
0)
#3095
b1010 3
1)
#3100
0)
#3105
b1011 3
1)
#3110
0)
#3115
12
b1100 3
1)
#3120
0)
#3125
0.
02
01
b0 3
1)
#3130
0)
#3135
b1 3
1)
#3140
0)
#3145
b10 3
1)
#3150
0)
#3155
b11 3
1)
#3160
0)
#3165
b100 3
1)
#3170
0)
#3175
b101 3
1)
#3180
0)
#3185
b110 3
1)
#3190
0)
#3195
11
b111 3
1)
#3200
0)
#3205
b101 6
1'
17
b11001 /
b11001 4
b11001 5
1.
b1000 3
1)
#3210
0)
#3215
b1001 3
1)
#3220
0)
#3225
b1010 3
1)
#3230
0)
#3235
b1011 3
1)
#3240
0)
#3245
12
b1100 3
1)
#3250
0)
#3255
0.
02
01
b0 3
1)
#3260
0)
#3265
b1 3
1)
#3270
0)
#3275
b10 3
1)
#3280
0)
#3285
b11 3
1)
#3290
0)
#3295
b100 3
1)
#3300
0)
#3305
b101 3
1)
#3310
0)
#3315
b110 3
1)
#3320
0)
#3325
11
b111 3
1)
#3330
0)
#3335
0'
18
07
b11010 /
b11010 4
b11010 5
1.
b1000 3
1)
#3340
0)
#3345
b1001 3
1)
#3350
0)
#3355
b1010 3
1)
#3360
0)
#3365
b1011 3
1)
#3370
0)
#3375
12
b1100 3
1)
#3380
0)
#3385
0.
02
01
b0 3
1)
#3390
0)
#3395
b1 3
1)
#3400
0)
#3405
b10 3
1)
#3410
0)
#3415
b11 3
1)
#3420
0)
#3425
b100 3
1)
#3430
0)
#3435
b101 3
1)
#3440
0)
#3445
b110 3
1)
#3450
0)
#3455
11
b111 3
1)
#3460
0)
#3465
b110 6
1'
17
b11011 /
b11011 4
b11011 5
1.
b1000 3
1)
#3470
0)
#3475
b1001 3
1)
#3480
0)
#3485
b1010 3
1)
#3490
0)
#3495
b1011 3
1)
#3500
0)
#3505
12
b1100 3
1)
#3510
0)
#3515
0.
02
01
b0 3
1)
#3520
0)
#3525
b1 3
1)
#3530
0)
#3535
b10 3
1)
#3540
0)
#3545
b11 3
1)
#3550
0)
#3555
b100 3
1)
#3560
0)
#3565
b101 3
1)
#3570
0)
#3575
b110 3
1)
#3580
0)
#3585
11
b111 3
1)
#3590
0)
#3595
0'
19
08
07
b11100 /
b11100 4
b11100 5
1.
b1000 3
1)
#3600
0)
#3605
b1001 3
1)
#3610
0)
#3615
b1010 3
1)
#3620
0)
#3625
b1011 3
1)
#3630
0)
#3635
12
b1100 3
1)
#3640
0)
#3645
0.
02
01
b0 3
1)
#3650
0)
#3655
b1 3
1)
#3660
0)
#3665
b10 3
1)
#3670
0)
#3675
b11 3
1)
#3680
0)
#3685
b100 3
1)
#3690
0)
#3695
b101 3
1)
#3700
0)
#3705
b110 3
1)
#3710
0)
#3715
11
b111 3
1)
#3720
0)
#3725
1&
b111 6
1'
17
b11101 /
b11101 4
b11101 5
1.
b1000 3
1)
#3730
0)
#3735
b1001 3
1)
#3740
0)
#3745
b1010 3
1)
#3750
0)
#3755
b1011 3
1)
#3760
0)
#3765
12
b1100 3
1)
#3770
0)
#3775
0.
02
01
b0 3
1)
#3780
0)
#3785
b1 3
1)
#3790
0)
#3795
b10 3
1)
#3800
0)
#3805
b11 3
1)
#3810
0)
#3815
b100 3
1)
#3820
0)
#3825
b101 3
1)
#3830
0)
#3835
b110 3
1)
#3840
0)
#3845
11
b111 3
1)
#3850
0)
#3855
0'
18
07
b11110 /
b11110 4
b11110 5
1.
b1000 3
1)
#3860
0)
#3865
b1001 3
1)
#3870
0)
#3875
b1010 3
1)
#3880
0)
#3885
b1011 3
1)
#3890
0)
#3895
12
b1100 3
1)
#3900
0)
#3905
0.
02
01
b0 3
1)
#3910
0)
#3915
b1 3
1)
#3920
0)
#3925
b10 3
1)
#3930
0)
#3935
b11 3
1)
#3940
0)
#3945
b100 3
1)
#3950
0)
#3955
b101 3
1)
#3960
0)
#3965
b110 3
1)
#3970
0)
#3975
11
b111 3
1)
#3980
0)
#3985
0&
b0 6
1'
17
b11111 /
b11111 4
b11111 5
1.
b1000 3
1)
#3990
0)
#3995
b1001 3
1)
#4000
0)
#4005
b1010 3
1)
#4010
0)
#4015
b1011 3
1)
#4020
0)
#4025
12
b1100 3
1)
#4030
0)
#4035
0.
02
01
b0 3
1)
#4040
0)
#4045
b1 3
1)
#4050
0)
#4055
b10 3
1)
#4060
0)
#4065
b11 3
1)
#4070
0)
#4075
b100 3
1)
#4080
0)
#4085
b101 3
1)
#4090
0)
#4095
b110 3
1)
#4100
0)
#4105
11
b111 3
1)
#4110
0)
#4115
0'
1<
0;
0:
09
08
07
b100000 /
b100000 4
b100000 5
1.
b1000 3
1)
#4120
0)
#4125
b1001 3
1)
#4130
0)
#4135
b1010 3
1)
#4140
0)
#4145
b1011 3
1)
#4150
0)
#4155
12
b1100 3
1)
#4160
0)
#4165
0.
02
01
b0 3
1)
#4170
0)
#4175
b1 3
1)
#4180
0)
#4185
b10 3
1)
#4190
0)
#4195
b11 3
1)
#4200
0)
#4205
b100 3
1)
#4210
0)
#4215
b101 3
1)
#4220
0)
#4225
b110 3
1)
#4230
0)
#4235
11
b111 3
1)
#4240
0)
#4245
b1 6
1'
17
b100001 /
b100001 4
b100001 5
1.
b1000 3
1)
#4250
0)
#4255
b1001 3
1)
#4260
0)
#4265
b1010 3
1)
#4270
0)
#4275
b1011 3
1)
#4280
0)
#4285
12
b1100 3
1)
#4290
0)
#4295
0.
02
01
b0 3
1)
#4300
0)
#4305
b1 3
1)
#4310
0)
#4315
b10 3
1)
#4320
0)
#4325
b11 3
1)
#4330
0)
#4335
b100 3
1)
#4340
0)
#4345
b101 3
1)
#4350
0)
#4355
b110 3
1)
#4360
0)
#4365
11
b111 3
1)
#4370
0)
#4375
0'
18
07
b100010 /
b100010 4
b100010 5
1.
b1000 3
1)
#4380
0)
#4385
b1001 3
1)
#4390
0)
#4395
b1010 3
1)
#4400
0)
#4405
b1011 3
1)
#4410
0)
#4415
12
b1100 3
1)
#4420
0)
#4425
0.
02
01
b0 3
1)
#4430
0)
#4435
b1 3
1)
#4440
0)
#4445
b10 3
1)
#4450
0)
#4455
b11 3
1)
#4460
0)
#4465
b100 3
1)
#4470
0)
#4475
b101 3
1)
#4480
0)
#4485
b110 3
1)
#4490
0)
#4495
11
b111 3
1)
#4500
0)
#4505
b10 6
1'
17
b100011 /
b100011 4
b100011 5
1.
b1000 3
1)
#4510
0)
#4515
b1001 3
1)
#4520
0)
#4525
b1010 3
1)
#4530
0)
#4535
b1011 3
1)
#4540
0)
#4545
12
b1100 3
1)
#4550
0)
#4555
0.
02
01
b0 3
1)
#4560
0)
#4565
b1 3
1)
#4570
0)
#4575
b10 3
1)
#4580
0)
#4585
b11 3
1)
#4590
0)
#4595
b100 3
1)
#4600
0)
#4605
b101 3
1)
#4610
0)
#4615
b110 3
1)
#4620
0)
#4625
11
b111 3
1)
#4630
0)
#4635
0'
19
08
07
b100100 /
b100100 4
b100100 5
1.
b1000 3
1)
#4640
0)
#4645
b1001 3
1)
#4650
0)
#4655
b1010 3
1)
#4660
0)
#4665
b1011 3
1)
#4670
0)
#4675
12
b1100 3
1)
#4680
0)
#4685
0.
02
01
b0 3
1)
#4690
0)
#4695
b1 3
1)
#4700
0)
#4705
b10 3
1)
#4710
0)
#4715
b11 3
1)
#4720
0)
#4725
b100 3
1)
#4730
0)
#4735
b101 3
1)
#4740
0)
#4745
b110 3
1)
#4750
0)
#4755
11
b111 3
1)
#4760
0)
#4765
b11 6
1'
17
b100101 /
b100101 4
b100101 5
1.
b1000 3
1)
#4770
0)
#4775
b1001 3
1)
#4780
0)
#4785
b1010 3
1)
#4790
0)
#4795
b1011 3
1)
#4800
0)
#4805
12
b1100 3
1)
#4810
0)
#4815
0.
02
01
b0 3
1)
#4820
0)
#4825
b1 3
1)
#4830
0)
#4835
b10 3
1)
#4840
0)
#4845
b11 3
1)
#4850
0)
#4855
b100 3
1)
#4860
0)
#4865
b101 3
1)
#4870
0)
#4875
b110 3
1)
#4880
0)
#4885
11
b111 3
1)
#4890
0)
#4895
0'
18
07
b100110 /
b100110 4
b100110 5
1.
b1000 3
1)
#4900
0)
#4905
b1001 3
1)
#4910
0)
#4915
b1010 3
1)
#4920
0)
#4925
b1011 3
1)
#4930
0)
#4935
12
b1100 3
1)
#4940
0)
#4945
0.
02
01
b0 3
1)
#4950
0)
#4955
b1 3
1)
#4960
0)
#4965
b10 3
1)
#4970
0)
#4975
b11 3
1)
#4980
0)
#4985
b100 3
1)
#4990
0)
#4995
b101 3
1)
#5000
0)
1!
