hw3/p2/counter_4bit.v
/* 
A 4bit up_counter with:

- negative edge-triggered synchronization
- synchronous load and reset
- parallel load of data
- active-low enabled counting.

*/

module counter_4bit (
    output reg[3:0] out,
    input clk, rst, load, enable,
    input wire[3:0] D
);


always @(negedge clk)

    if (rst) out <= 4'b0000; // if reset, output 0

    else if (~enable & ~load) out <= out + 1; // low-enabled, load is 0, up-count

    // low-enabled, with data to load
    else if (~enable & load)  out <= D; // parallel-load of data

endmodule

hw3/p2/counter_4bit_tb.v
module counter_4bit_tb ();
    // note to self
    // in TB: inputs are reg, outputs are wires
    // in module: inputs are wires, outputs are reg
    wire [3:0] out;
    reg clk, rst, load, enable;
    reg [3:0] D;

    counter_4bit c4b(
        .out(out), 
        .D(D), 
        .clk(clk), 
        .rst(rst),
        .load(load), 
        .enable(enable));

    // clk
    initial clk=1'b1;
    always #10 clk=~clk;

    // D - input data for loading
    initial D = 4'b1101;

    // reset
    initial begin
        #0 rst = 1'b0;
        #20 rst = 1'b1;
        #15 rst = 1'b0;
    end

    // enable
    initial begin
        #0 enable = 1'b1;
        #50 enable = 1'b0; // set enable pin after reset, helps checking active low-enabled counting
    end

    // load
    initial begin
        #0 load = 1'b0;
        #360 load = 1'b1;
        #20 load = 1'b0;
    end

    // log details in text format
	initial begin
        $display ("time\t clk\t reset\t enable\t load \t dataIn \t out\t");
        $monitor ("%g\t %b\t %b\t %b\t %b\t %b\t %b\t", $time, clk, rst, enable, load, D, out);
        #450 $finish;
    end

    // Log *vcd file for vieweing in gtkWave
    initial begin
        $dumpfile("counter_4bit_vcd.vcd");
        $dumpvars(0, counter_4bit_tb);
    end

endmodule

hw3/p2/counter_4bit_vcd.vcd
$date
	Mon Sep 19 23:47:14 2022
$end
$version
	Icarus Verilog
$end
$timescale
	1s
$end
$scope module counter_4bit_tb $end
$var wire 4 ! out [3:0] $end
$var reg 4 " D [3:0] $end
$var reg 1 # clk $end
$var reg 1 $ enable $end
$var reg 1 % load $end
$var reg 1 & rst $end
$scope module c4b $end
$var wire 4 ' D [3:0] $end
$var wire 1 # clk $end
$var wire 1 $ enable $end
$var wire 1 % load $end
$var wire 1 & rst $end
$var reg 4 ( out [3:0] $end
$upscope $end
$upscope $end
$enddefinitions $end
$comment Show the parameter values. $end
$dumpall
$end
#0
$dumpvars
bx (
b1101 '
0&
0%
1$
1#
b1101 "
bx !
$end
#10
0#
#20
1#
1&
#30
b0 !
b0 (
0#
#35
0&
#40
1#
#50
b1 !
b1 (
0#
0$
#60
1#
#70
b10 !
b10 (
0#
#80
1#
#90
b11 !
b11 (
0#
#100
1#
#110
b100 !
b100 (
0#
#120
1#
#130
b101 !
b101 (
0#
#140
1#
#150
b110 !
b110 (
0#
#160
1#
#170
b111 !
b111 (
0#
#180
1#
#190
b1000 !
b1000 (
0#
#200
1#
#210
b1001 !
b1001 (
0#
#220
1#
#230
b1010 !
b1010 (
0#
#240
1#
#250
b1011 !
b1011 (
0#
#260
1#
#270
b1100 !
b1100 (
0#
#280
1#
#290
b1101 !
b1101 (
0#
#300
1#
#310
b1110 !
b1110 (
0#
#320
1#
#330
b1111 !
b1111 (
0#
#340
1#
#350
b0 !
b0 (
0#
#360
1#
1%
#370
b1101 !
b1101 (
0#
#380
1#
0%
#390
b1110 !
b1110 (
0#
#400
1#
#410
b1111 !
b1111 (
0#
#420
1#
#430
b0 !
b0 (
0#
#440
1#
#450
b1 !
b1 (
0#
