hw3/p2/counter_4bit_rco.v
/* 
A 4bit up_counter with:

- negative edge-triggered synchronization
- parallel load of data
- active-low enabled counting
- asynchronous load + reset (just for simplicity)
- rco output - ripple carry output, indicating 

On top, the rco output is asserted when the output is at its max value i.e., 1111 (F in hex)

*/

module counter_4bit_rco (
    output reg[3:0] out,
    output reg rco,
    input clk, rst, load, enable,
    input wire[3:0] D
);


always @ (negedge clk or posedge rst or posedge load) begin

    if (rst) out <= 4'b0000; // if reset, output 0

    else if (~enable & ~load) out <= out + 1; // low-enabled, load is 0, up-count

    // low-enabled, with data to load
    else if (~enable & load)  out <= D; // parallel-load of data

    // rco - carry output indication if out = 4'b1111
    if (out == 4'b1111) rco <= 1'b1;
    else rco <= 1'b0;

end
endmodule

hw3/p2/counter_8bit.v
/* 
A 8 bit up_counter, made up of two cascaded 4 bit counters with rco:

- negative edge-triggered synchronization
- synchronous load and reset
- parallel load of data
- active-low enabled counting.

*/

module counter_8bit (
    output [7:0] out,
    input clk, rst, load, enable,
    input [7:0] dataIn
);

    wire rco;
    wire [3:0] out1, out2;

    counter_4bit_rco counter1(
        .out(out1),
        .D(dataIn[3:0]), 
        .rco(rco),
        .clk(clk), 
        .rst(rst),
        .load(load), 
        .enable(enable));

    counter_4bit_rco counter2(
        .out(out2),
        .D(dataIn[7:4]), 
        .rco(),
        .clk(~rco),
        .rst(rst),
        .load(load), 
        .enable(enable));

    assign out = {out2, out1};

endmodule

hw3/p2/counter_8bit_tb.v
module counter_8bit_tb ();
    // note to self
    // in TB: inputs are reg, outputs are wires
    // in module: inputs are wires, outputs are reg
    wire [7:0] out;
    reg clk, rst, load, enable;
    reg [7:0] D;

    counter_8bit c4b(
        .out(out), 
        .dataIn(D), 
        .clk(clk), 
        .rst(rst),
        .load(load), 
        .enable(enable));

    // clk
    initial clk=1'b1;
    always #10 clk=~clk;

    // D - input data for loading
    initial D = 8'b11010101;

    // reset
    initial begin
        #0 rst = 1'b0;
        #20 rst = 1'b1;
        #15 rst = 1'b0;
        #5180 rst = 1'b1;
        #15 rst = 1'b0;
    end

    // enable
    initial begin
        #0 enable = 1'b1;
        #50 enable = 1'b0; // set enable pin after reset, helps checking active low-enabled counting
    end

    // load
    initial begin
        #0 load = 1'b0;
        #5160 load = 1'b1;
        #20 load = 1'b0;
    end

    // log details in text format
	initial begin
        $display ("time\t clk\t reset\t enable\t load \t dataIn \t out\t");
        $monitor ("%g\t %b\t %b\t %b\t %b\t %b\t %b\t", $time, clk, rst, enable, load, D, out);
        #6000 $finish;
    end

    // Log *vcd file for vieweing in gtkWave
    initial begin
        $dumpfile("counter_8bit_vcd.vcd");
        $dumpvars(0, counter_8bit_tb);
    end

endmodule

hw3/p2/counter_8bit_vcd.vcd
$date
	Tue Sep 20 13:54:29 2022
$end
$version
	Icarus Verilog
$end
$timescale
	1s
$end
$scope module counter_8bit_tb $end
$var wire 8 ! out [7:0] $end
$var reg 8 " D [7:0] $end
$var reg 1 # clk $end
$var reg 1 $ enable $end
$var reg 1 % load $end
$var reg 1 & rst $end
$scope module c4b $end
$var wire 1 # clk $end
$var wire 8 ' dataIn [7:0] $end
$var wire 1 $ enable $end
$var wire 1 % load $end
$var wire 1 & rst $end
$var wire 1 ( rco $end
$var wire 4 ) out2 [3:0] $end
$var wire 4 * out1 [3:0] $end
$var wire 8 + out [7:0] $end
$scope module counter1 $end
$var wire 4 , D [3:0] $end
$var wire 1 # clk $end
$var wire 1 $ enable $end
$var wire 1 % load $end
$var wire 1 & rst $end
$var reg 4 - out [3:0] $end
$var reg 1 ( rco $end
$upscope $end
$scope module counter2 $end
$var wire 4 . D [3:0] $end
$var wire 1 / clk $end
$var wire 1 $ enable $end
$var wire 1 % load $end
$var wire 1 & rst $end
$var reg 4 0 out [3:0] $end
$var reg 1 1 rco $end
$upscope $end
$upscope $end
$upscope $end
$enddefinitions $end
$comment Show the parameter values. $end
$dumpall
$end
#0
$dumpvars
x1
bx 0
x/
b1101 .
bx -
b101 ,
bx +
bx *
bx )
x(
b11010101 '
0&
0%
1$
1#
b11010101 "
bx !
$end
#10
1/
0(
0#
#20
b0 *
b0 -
01
b0 !
b0 +
b0 )
b0 0
1#
1&
#30
0#
#35
0&
#40
1#
#50
b1 !
b1 +
b1 *
b1 -
0#
0$
#60
1#
#70
b10 !
b10 +
b10 *
b10 -
0#
#80
1#
#90
b11 !
b11 +
b11 *
b11 -
0#
#100
1#
#110
b100 !
b100 +
b100 *
b100 -
0#
#120
1#
#130
b101 !
b101 +
b101 *
b101 -
0#
#140
1#
#150
b110 !
b110 +
b110 *
b110 -
0#
#160
1#
#170
b111 !
b111 +
b111 *
b111 -
0#
#180
1#
#190
b1000 !
b1000 +
b1000 *
b1000 -
0#
#200
1#
#210
b1001 !
b1001 +
b1001 *
b1001 -
0#
#220
1#
#230
b1010 !
b1010 +
b1010 *
b1010 -
0#
#240
1#
#250
b1011 !
b1011 +
b1011 *
b1011 -
0#
#260
1#
#270
b1100 !
b1100 +
b1100 *
b1100 -
0#
#280
1#
#290
b1101 !
b1101 +
b1101 *
b1101 -
0#
#300
1#
#310
b1110 !
b1110 +
b1110 *
b1110 -
0#
#320
1#
#330
b1111 !
b1111 +
b1111 *
b1111 -
0#
#340
1#
#350
b1 )
b1 0
0/
1(
b10000 !
b10000 +
b0 *
b0 -
0#
#360
1#
#370
1/
0(
b10001 !
b10001 +
b1 *
b1 -
0#
#380
1#
#390
b10010 !
b10010 +
b10 *
b10 -
0#
#400
1#
#410
b10011 !
b10011 +
b11 *
b11 -
0#
#420
1#
#430
b10100 !
b10100 +
b100 *
b100 -
0#
#440
1#
#450
b10101 !
b10101 +
b101 *
b101 -
0#
#460
1#
#470
b10110 !
b10110 +
b110 *
b110 -
0#
#480
1#
#490
b10111 !
b10111 +
b111 *
b111 -
0#
#500
1#
#510
b11000 !
b11000 +
b1000 *
b1000 -
0#
#520
1#
#530
b11001 !
b11001 +
b1001 *
b1001 -
0#
#540
1#
#550
b11010 !
b11010 +
b1010 *
b1010 -
0#
#560
1#
#570
b11011 !
b11011 +
b1011 *
b1011 -
0#
#580
1#
#590
b11100 !
b11100 +
b1100 *
b1100 -
0#
#600
1#
#610
b11101 !
b11101 +
b1101 *
b1101 -
0#
#620
1#
#630
b11110 !
b11110 +
b1110 *
b1110 -
0#
#640
1#
#650
b11111 !
b11111 +
b1111 *
b1111 -
0#
#660
1#
#670
b10 )
b10 0
0/
1(
b100000 !
b100000 +
b0 *
b0 -
0#
#680
1#
#690
1/
0(
b100001 !
b100001 +
b1 *
b1 -
0#
#700
1#
#710
b100010 !
b100010 +
b10 *
b10 -
0#
#720
1#
#730
b100011 !
b100011 +
b11 *
b11 -
0#
#740
1#
#750
b100100 !
b100100 +
b100 *
b100 -
0#
#760
1#
#770
b100101 !
b100101 +
b101 *
b101 -
0#
#780
1#
#790
b100110 !
b100110 +
b110 *
b110 -
0#
#800
1#
#810
b100111 !
b100111 +
b111 *
b111 -
0#
#820
1#
#830
b101000 !
b101000 +
b1000 *
b1000 -
0#
#840
1#
#850
b101001 !
b101001 +
b1001 *
b1001 -
0#
#860
1#
#870
b101010 !
b101010 +
b1010 *
b1010 -
0#
#880
1#
#890
b101011 !
b101011 +
b1011 *
b1011 -
0#
#900
1#
#910
b101100 !
b101100 +
b1100 *
b1100 -
0#
#920
1#
#930
b101101 !
b101101 +
b1101 *
b1101 -
0#
#940
1#
#950
b101110 !
b101110 +
b1110 *
b1110 -
0#
#960
1#
#970
b101111 !
b101111 +
b1111 *
b1111 -
0#
#980
1#
#990
b11 )
b11 0
0/
1(
b110000 !
b110000 +
b0 *
b0 -
0#
#1000
1#
#1010
1/
0(
b110001 !
b110001 +
b1 *
b1 -
0#
#1020
1#
#1030
b110010 !
b110010 +
b10 *
b10 -
0#
#1040
1#
#1050
b110011 !
b110011 +
b11 *
b11 -
0#
#1060
1#
#1070
b110100 !
b110100 +
b100 *
b100 -
0#
#1080
1#
#1090
b110101 !
b110101 +
b101 *
b101 -
0#
#1100
1#
#1110
b110110 !
b110110 +
b110 *
b110 -
0#
#1120
1#
#1130
b110111 !
b110111 +
b111 *
b111 -
0#
#1140
1#
#1150
b111000 !
b111000 +
b1000 *
b1000 -
0#
#1160
1#
#1170
b111001 !
b111001 +
b1001 *
b1001 -
0#
#1180
1#
#1190
b111010 !
b111010 +
b1010 *
b1010 -
0#
#1200
1#
#1210
b111011 !
b111011 +
b1011 *
b1011 -
0#
#1220
1#
#1230
b111100 !
b111100 +
b1100 *
b1100 -
0#
#1240
1#
#1250
b111101 !
b111101 +
b1101 *
b1101 -
0#
#1260
1#
#1270
b111110 !
b111110 +
b1110 *
b1110 -
0#
#1280
1#
#1290
b111111 !
b111111 +
b1111 *
b1111 -
0#
#1300
1#
#1310
b100 )
b100 0
0/
1(
b1000000 !
b1000000 +
b0 *
b0 -
0#
#1320
1#
#1330
1/
0(
b1000001 !
b1000001 +
b1 *
b1 -
0#
#1340
1#
#1350
b1000010 !
b1000010 +
b10 *
b10 -
0#
#1360
1#
#1370
b1000011 !
b1000011 +
b11 *
b11 -
0#
#1380
1#
#1390
b1000100 !
b1000100 +
b100 *
b100 -
0#
#1400
1#
#1410
b1000101 !
b1000101 +
b101 *
b101 -
0#
#1420
1#
#1430
b1000110 !
b1000110 +
b110 *
b110 -
0#
#1440
1#
#1450
b1000111 !
b1000111 +
b111 *
b111 -
0#
#1460
1#
#1470
b1001000 !
b1001000 +
b1000 *
b1000 -
0#
#1480
1#
#1490
b1001001 !
b1001001 +
b1001 *
b1001 -
0#
#1500
1#
#1510
b1001010 !
b1001010 +
b1010 *
b1010 -
0#
#1520
1#
#1530
b1001011 !
b1001011 +
b1011 *
b1011 -
0#
#1540
1#
#1550
b1001100 !
b1001100 +
b1100 *
b1100 -
0#
#1560
1#
#1570
b1001101 !
b1001101 +
b1101 *
b1101 -
0#
#1580
1#
#1590
b1001110 !
b1001110 +
b1110 *
b1110 -
0#
#1600
1#
#1610
b1001111 !
b1001111 +
b1111 *
b1111 -
0#
#1620
1#
#1630
b101 )
b101 0
0/
1(
b1010000 !
b1010000 +
b0 *
b0 -
0#
#1640
1#
#1650
1/
0(
b1010001 !
b1010001 +
b1 *
b1 -
0#
#1660
1#
#1670
b1010010 !
b1010010 +
b10 *
b10 -
0#
#1680
1#
#1690
b1010011 !
b1010011 +
b11 *
b11 -
0#
#1700
1#
#1710
b1010100 !
b1010100 +
b100 *
b100 -
0#
#1720
1#
#1730
b1010101 !
b1010101 +
b101 *
b101 -
0#
#1740
1#
#1750
b1010110 !
b1010110 +
b110 *
b110 -
0#
#1760
1#
#1770
b1010111 !
b1010111 +
b111 *
b111 -
0#
#1780
1#
#1790
b1011000 !
b1011000 +
b1000 *
b1000 -
0#
#1800
1#
#1810
b1011001 !
b1011001 +
b1001 *
b1001 -
0#
#1820
1#
#1830
b1011010 !
b1011010 +
b1010 *
b1010 -
0#
#1840
1#
#1850
b1011011 !
b1011011 +
b1011 *
b1011 -
0#
#1860
1#
#1870
b1011100 !
b1011100 +
b1100 *
b1100 -
0#
#1880
1#
#1890
b1011101 !
b1011101 +
b1101 *
b1101 -
0#
#1900
1#
#1910
b1011110 !
b1011110 +
b1110 *
b1110 -
0#
#1920
1#
#1930
b1011111 !
b1011111 +
b1111 *
b1111 -
0#
#1940
1#
#1950
b110 )
b110 0
0/
1(
b1100000 !
b1100000 +
b0 *
b0 -
0#
#1960
1#
#1970
1/
0(
b1100001 !
b1100001 +
b1 *
b1 -
0#
#1980
1#
#1990
b1100010 !
b1100010 +
b10 *
b10 -
0#
#2000
1#
#2010
b1100011 !
b1100011 +
b11 *
b11 -
0#
#2020
1#
#2030
b1100100 !
b1100100 +
b100 *
b100 -
0#
#2040
1#
#2050
b1100101 !
b1100101 +
b101 *
b101 -
0#
#2060
1#
#2070
b1100110 !
b1100110 +
b110 *
b110 -
0#
#2080
1#
#2090
b1100111 !
b1100111 +
b111 *
b111 -
0#
#2100
1#
#2110
b1101000 !
b1101000 +
b1000 *
b1000 -
0#
#2120
1#
#2130
b1101001 !
b1101001 +
b1001 *
b1001 -
0#
#2140
1#
#2150
b1101010 !
b1101010 +
b1010 *
b1010 -
0#
#2160
1#
#2170
b1101011 !
b1101011 +
b1011 *
b1011 -
0#
#2180
1#
#2190
b1101100 !
b1101100 +
b1100 *
b1100 -
0#
#2200
1#
#2210
b1101101 !
b1101101 +
b1101 *
b1101 -
0#
#2220
1#
#2230
b1101110 !
b1101110 +
b1110 *
b1110 -
0#
#2240
1#
#2250
b1101111 !
b1101111 +
b1111 *
b1111 -
0#
#2260
1#
#2270
b111 )
b111 0
0/
1(
b1110000 !
b1110000 +
b0 *
b0 -
0#
#2280
1#
#2290
1/
0(
b1110001 !
b1110001 +
b1 *
b1 -
0#
#2300
1#
#2310
b1110010 !
b1110010 +
b10 *
b10 -
0#
#2320
1#
#2330
b1110011 !
b1110011 +
b11 *
b11 -
0#
#2340
1#
#2350
b1110100 !
b1110100 +
b100 *
b100 -
0#
#2360
1#
#2370
b1110101 !
b1110101 +
b101 *
b101 -
0#
#2380
1#
#2390
b1110110 !
b1110110 +
b110 *
b110 -
0#
#2400
1#
#2410
b1110111 !
b1110111 +
b111 *
b111 -
0#
#2420
1#
#2430
b1111000 !
b1111000 +
b1000 *
b1000 -
0#
#2440
1#
#2450
b1111001 !
b1111001 +
b1001 *
b1001 -
0#
#2460
1#
#2470
b1111010 !
b1111010 +
b1010 *
b1010 -
0#
#2480
1#
#2490
b1111011 !
b1111011 +
b1011 *
b1011 -
0#
#2500
1#
#2510
b1111100 !
b1111100 +
b1100 *
b1100 -
0#
#2520
1#
#2530
b1111101 !
b1111101 +
b1101 *
b1101 -
0#
#2540
1#
#2550
b1111110 !
b1111110 +
b1110 *
b1110 -
0#
#2560
1#
#2570
b1111111 !
b1111111 +
b1111 *
b1111 -
0#
#2580
1#
#2590
b1000 )
b1000 0
0/
1(
b10000000 !
b10000000 +
b0 *
b0 -
0#
#2600
1#
#2610
1/
0(
b10000001 !
b10000001 +
b1 *
b1 -
0#
#2620
1#
#2630
b10000010 !
b10000010 +
b10 *
b10 -
0#
#2640
1#
#2650
b10000011 !
b10000011 +
b11 *
b11 -
0#
#2660
1#
#2670
b10000100 !
b10000100 +
b100 *
b100 -
0#
#2680
1#
#2690
b10000101 !
b10000101 +
b101 *
b101 -
0#
#2700
1#
#2710
b10000110 !
b10000110 +
b110 *
b110 -
0#
#2720
1#
#2730
b10000111 !
b10000111 +
b111 *
b111 -
0#
#2740
1#
#2750
b10001000 !
b10001000 +
b1000 *
b1000 -
0#
#2760
1#
#2770
b10001001 !
b10001001 +
b1001 *
b1001 -
0#
#2780
1#
#2790
b10001010 !
b10001010 +
b1010 *
b1010 -
0#
#2800
1#
#2810
b10001011 !
b10001011 +
b1011 *
b1011 -
0#
#2820
1#
#2830
b10001100 !
b10001100 +
b1100 *
b1100 -
0#
#2840
1#
#2850
b10001101 !
b10001101 +
b1101 *
b1101 -
0#
#2860
1#
#2870
b10001110 !
b10001110 +
b1110 *
b1110 -
0#
#2880
1#
#2890
b10001111 !
b10001111 +
b1111 *
b1111 -
0#
#2900
1#
#2910
b1001 )
b1001 0
0/
1(
b10010000 !
b10010000 +
b0 *
b0 -
0#
#2920
1#
#2930
1/
0(
b10010001 !
b10010001 +
b1 *
b1 -
0#
#2940
1#
#2950
b10010010 !
b10010010 +
b10 *
b10 -
0#
#2960
1#
#2970
b10010011 !
b10010011 +
b11 *
b11 -
0#
#2980
1#
#2990
b10010100 !
b10010100 +
b100 *
b100 -
0#
#3000
1#
#3010
b10010101 !
b10010101 +
b101 *
b101 -
0#
#3020
1#
#3030
b10010110 !
b10010110 +
b110 *
b110 -
0#
#3040
1#
#3050
b10010111 !
b10010111 +
b111 *
b111 -
0#
#3060
1#
#3070
b10011000 !
b10011000 +
b1000 *
b1000 -
0#
#3080
1#
#3090
b10011001 !
b10011001 +
b1001 *
b1001 -
0#
#3100
1#
#3110
b10011010 !
b10011010 +
b1010 *
b1010 -
0#
#3120
1#
#3130
b10011011 !
b10011011 +
b1011 *
b1011 -
0#
#3140
1#
#3150
b10011100 !
b10011100 +
b1100 *
b1100 -
0#
#3160
1#
#3170
b10011101 !
b10011101 +
b1101 *
b1101 -
0#
#3180
1#
#3190
b10011110 !
b10011110 +
b1110 *
b1110 -
0#
#3200
1#
#3210
b10011111 !
b10011111 +
b1111 *
b1111 -
0#
#3220
1#
#3230
b1010 )
b1010 0
0/
1(
b10100000 !
b10100000 +
b0 *
b0 -
0#
#3240
1#
#3250
1/
0(
b10100001 !
b10100001 +
b1 *
b1 -
0#
#3260
1#
#3270
b10100010 !
b10100010 +
b10 *
b10 -
0#
#3280
1#
#3290
b10100011 !
b10100011 +
b11 *
b11 -
0#
#3300
1#
#3310
b10100100 !
b10100100 +
b100 *
b100 -
0#
#3320
1#
#3330
b10100101 !
b10100101 +
b101 *
b101 -
0#
#3340
1#
#3350
b10100110 !
b10100110 +
b110 *
b110 -
0#
#3360
1#
#3370
b10100111 !
b10100111 +
b111 *
b111 -
0#
#3380
1#
#3390
b10101000 !
b10101000 +
b1000 *
b1000 -
0#
#3400
1#
#3410
b10101001 !
b10101001 +
b1001 *
b1001 -
0#
#3420
1#
#3430
b10101010 !
b10101010 +
b1010 *
b1010 -
0#
#3440
1#
#3450
b10101011 !
b10101011 +
b1011 *
b1011 -
0#
#3460
1#
#3470
b10101100 !
b10101100 +
b1100 *
b1100 -
0#
#3480
1#
#3490
b10101101 !
b10101101 +
b1101 *
b1101 -
0#
#3500
1#
#3510
b10101110 !
b10101110 +
b1110 *
b1110 -
0#
#3520
1#
#3530
b10101111 !
b10101111 +
b1111 *
b1111 -
0#
#3540
1#
#3550
b1011 )
b1011 0
0/
1(
b10110000 !
b10110000 +
b0 *
b0 -
0#
#3560
1#
#3570
1/
0(
b10110001 !
b10110001 +
b1 *
b1 -
0#
#3580
1#
#3590
b10110010 !
b10110010 +
b10 *
b10 -
0#
#3600
1#
#3610
b10110011 !
b10110011 +
b11 *
b11 -
0#
#3620
1#
#3630
b10110100 !
b10110100 +
b100 *
b100 -
0#
#3640
1#
#3650
b10110101 !
b10110101 +
b101 *
b101 -
0#
#3660
1#
#3670
b10110110 !
b10110110 +
b110 *
b110 -
0#
#3680
1#
#3690
b10110111 !
b10110111 +
b111 *
b111 -
0#
#3700
1#
#3710
b10111000 !
b10111000 +
b1000 *
b1000 -
0#
#3720
1#
#3730
b10111001 !
b10111001 +
b1001 *
b1001 -
0#
#3740
1#
#3750
b10111010 !
b10111010 +
b1010 *
b1010 -
0#
#3760
1#
#3770
b10111011 !
b10111011 +
b1011 *
b1011 -
0#
#3780
1#
#3790
b10111100 !
b10111100 +
b1100 *
b1100 -
0#
#3800
1#
#3810
b10111101 !
b10111101 +
b1101 *
b1101 -
0#
#3820
1#
#3830
b10111110 !
b10111110 +
b1110 *
b1110 -
0#
#3840
1#
#3850
b10111111 !
b10111111 +
b1111 *
b1111 -
0#
#3860
1#
#3870
b1100 )
b1100 0
0/
1(
b11000000 !
b11000000 +
b0 *
b0 -
0#
#3880
1#
#3890
1/
0(
b11000001 !
b11000001 +
b1 *
b1 -
0#
#3900
1#
#3910
b11000010 !
b11000010 +
b10 *
b10 -
0#
#3920
1#
#3930
b11000011 !
b11000011 +
b11 *
b11 -
0#
#3940
1#
#3950
b11000100 !
b11000100 +
b100 *
b100 -
0#
#3960
1#
#3970
b11000101 !
b11000101 +
b101 *
b101 -
0#
#3980
1#
#3990
b11000110 !
b11000110 +
b110 *
b110 -
0#
#4000
1#
#4010
b11000111 !
b11000111 +
b111 *
b111 -
0#
#4020
1#
#4030
b11001000 !
b11001000 +
b1000 *
b1000 -
0#
#4040
1#
#4050
b11001001 !
b11001001 +
b1001 *
b1001 -
0#
#4060
1#
#4070
b11001010 !
b11001010 +
b1010 *
b1010 -
0#
#4080
1#
#4090
b11001011 !
b11001011 +
b1011 *
b1011 -
0#
#4100
1#
#4110
b11001100 !
b11001100 +
b1100 *
b1100 -
0#
#4120
1#
#4130
b11001101 !
b11001101 +
b1101 *
b1101 -
0#
#4140
1#
#4150
b11001110 !
b11001110 +
b1110 *
b1110 -
0#
#4160
1#
#4170
b11001111 !
b11001111 +
b1111 *
b1111 -
0#
#4180
1#
#4190
b1101 )
b1101 0
0/
1(
b11010000 !
b11010000 +
b0 *
b0 -
0#
#4200
1#
#4210
1/
0(
b11010001 !
b11010001 +
b1 *
b1 -
0#
#4220
1#
#4230
b11010010 !
b11010010 +
b10 *
b10 -
0#
#4240
1#
#4250
b11010011 !
b11010011 +
b11 *
b11 -
0#
#4260
1#
#4270
b11010100 !
b11010100 +
b100 *
b100 -
0#
#4280
1#
#4290
b11010101 !
b11010101 +
b101 *
b101 -
0#
#4300
1#
#4310
b11010110 !
b11010110 +
b110 *
b110 -
0#
#4320
1#
#4330
b11010111 !
b11010111 +
b111 *
b111 -
0#
#4340
1#
#4350
b11011000 !
b11011000 +
b1000 *
b1000 -
0#
#4360
1#
#4370
b11011001 !
b11011001 +
b1001 *
b1001 -
0#
#4380
1#
#4390
b11011010 !
b11011010 +
b1010 *
b1010 -
0#
#4400
1#
#4410
b11011011 !
b11011011 +
b1011 *
b1011 -
0#
#4420
1#
#4430
b11011100 !
b11011100 +
b1100 *
b1100 -
0#
#4440
1#
#4450
b11011101 !
b11011101 +
b1101 *
b1101 -
0#
#4460
1#
#4470
b11011110 !
b11011110 +
b1110 *
b1110 -
0#
#4480
1#
#4490
b11011111 !
b11011111 +
b1111 *
b1111 -
0#
#4500
1#
#4510
b1110 )
b1110 0
0/
1(
b11100000 !
b11100000 +
b0 *
b0 -
0#
#4520
1#
#4530
1/
0(
b11100001 !
b11100001 +
b1 *
b1 -
0#
#4540
1#
#4550
b11100010 !
b11100010 +
b10 *
b10 -
0#
#4560
1#
#4570
b11100011 !
b11100011 +
b11 *
b11 -
0#
#4580
1#
#4590
b11100100 !
b11100100 +
b100 *
b100 -
0#
#4600
1#
#4610
b11100101 !
b11100101 +
b101 *
b101 -
0#
#4620
1#
#4630
b11100110 !
b11100110 +
b110 *
b110 -
0#
#4640
1#
#4650
b11100111 !
b11100111 +
b111 *
b111 -
0#
#4660
1#
#4670
b11101000 !
b11101000 +
b1000 *
b1000 -
0#
#4680
1#
#4690
b11101001 !
b11101001 +
b1001 *
b1001 -
0#
#4700
1#
#4710
b11101010 !
b11101010 +
b1010 *
b1010 -
0#
#4720
1#
#4730
b11101011 !
b11101011 +
b1011 *
b1011 -
0#
#4740
1#
#4750
b11101100 !
b11101100 +
b1100 *
b1100 -
0#
#4760
1#
#4770
b11101101 !
b11101101 +
b1101 *
b1101 -
0#
#4780
1#
#4790
b11101110 !
b11101110 +
b1110 *
b1110 -
0#
#4800
1#
#4810
b11101111 !
b11101111 +
b1111 *
b1111 -
0#
#4820
1#
#4830
b1111 )
b1111 0
0/
1(
b11110000 !
b11110000 +
b0 *
b0 -
0#
#4840
1#
#4850
1/
0(
b11110001 !
b11110001 +
b1 *
b1 -
0#
#4860
1#
#4870
b11110010 !
b11110010 +
b10 *
b10 -
0#
#4880
1#
#4890
b11110011 !
b11110011 +
b11 *
b11 -
0#
#4900
1#
#4910
b11110100 !
b11110100 +
b100 *
b100 -
0#
#4920
1#
#4930
b11110101 !
b11110101 +
b101 *
b101 -
0#
#4940
1#
#4950
b11110110 !
b11110110 +
b110 *
b110 -
0#
#4960
1#
#4970
b11110111 !
b11110111 +
b111 *
b111 -
0#
#4980
1#
#4990
b11111000 !
b11111000 +
b1000 *
b1000 -
0#
#5000
1#
#5010
b11111001 !
b11111001 +
b1001 *
b1001 -
0#
#5020
1#
#5030
b11111010 !
b11111010 +
b1010 *
b1010 -
0#
#5040
1#
#5050
b11111011 !
b11111011 +
b1011 *
b1011 -
0#
#5060
1#
#5070
b11111100 !
b11111100 +
b1100 *
b1100 -
0#
#5080
1#
#5090
b11111101 !
b11111101 +
b1101 *
b1101 -
0#
#5100
1#
#5110
b11111110 !
b11111110 +
b1110 *
b1110 -
0#
#5120
1#
#5130
b11111111 !
b11111111 +
b1111 *
b1111 -
0#
#5140
1#
#5150
11
b0 )
b0 0
0/
1(
b0 !
b0 +
b0 *
b0 -
0#
#5160
1/
0(
b101 *
b101 -
01
b11010101 !
b11010101 +
b1101 )
b1101 0
1#
1%
#5170
0#
#5180
1#
0%
#5190
b11010110 !
b11010110 +
b110 *
b110 -
0#
#5200
1#
#5210
b11010111 !
b11010111 +
b111 *
b111 -
0#
#5215
b0 *
b0 -
b0 !
b0 +
b0 )
b0 0
1&
#5220
1#
#5230
b1 !
b1 +
b1 *
b1 -
0#
0&
#5240
1#
#5250
b10 !
b10 +
b10 *
b10 -
0#
#5260
1#
#5270
b11 !
b11 +
b11 *
b11 -
0#
#5280
1#
#5290
b100 !
b100 +
b100 *
b100 -
0#
#5300
1#
#5310
b101 !
b101 +
b101 *
b101 -
0#
#5320
1#
#5330
b110 !
b110 +
b110 *
b110 -
0#
#5340
1#
#5350
b111 !
b111 +
b111 *
b111 -
0#
#5360
1#
#5370
b1000 !
b1000 +
b1000 *
b1000 -
0#
#5380
1#
#5390
b1001 !
b1001 +
b1001 *
b1001 -
0#
#5400
1#
#5410
b1010 !
b1010 +
b1010 *
b1010 -
0#
#5420
1#
#5430
b1011 !
b1011 +
b1011 *
b1011 -
0#
#5440
1#
#5450
b1100 !
b1100 +
b1100 *
b1100 -
0#
#5460
1#
#5470
b1101 !
b1101 +
b1101 *
b1101 -
0#
#5480
1#
#5490
b1110 !
b1110 +
b1110 *
b1110 -
0#
#5500
1#
#5510
b1111 !
b1111 +
b1111 *
b1111 -
0#
#5520
1#
#5530
b1 )
b1 0
0/
1(
b10000 !
b10000 +
b0 *
b0 -
0#
#5540
1#
#5550
1/
0(
b10001 !
b10001 +
b1 *
b1 -
0#
#5560
1#
#5570
b10010 !
b10010 +
b10 *
b10 -
0#
#5580
1#
#5590
b10011 !
b10011 +
b11 *
b11 -
0#
#5600
1#
#5610
b10100 !
b10100 +
b100 *
b100 -
0#
#5620
1#
#5630
b10101 !
b10101 +
b101 *
b101 -
0#
#5640
1#
#5650
b10110 !
b10110 +
b110 *
b110 -
0#
#5660
1#
#5670
b10111 !
b10111 +
b111 *
b111 -
0#
#5680
1#
#5690
b11000 !
b11000 +
b1000 *
b1000 -
0#
#5700
1#
#5710
b11001 !
b11001 +
b1001 *
b1001 -
0#
#5720
1#
#5730
b11010 !
b11010 +
b1010 *
b1010 -
0#
#5740
1#
#5750
b11011 !
b11011 +
b1011 *
b1011 -
0#
#5760
1#
#5770
b11100 !
b11100 +
b1100 *
b1100 -
0#
#5780
1#
#5790
b11101 !
b11101 +
b1101 *
b1101 -
0#
#5800
1#
#5810
b11110 !
b11110 +
b1110 *
b1110 -
0#
#5820
1#
#5830
b11111 !
b11111 +
b1111 *
b1111 -
0#
#5840
1#
#5850
b10 )
b10 0
0/
1(
b100000 !
b100000 +
b0 *
b0 -
0#
#5860
1#
#5870
1/
0(
b100001 !
b100001 +
b1 *
b1 -
0#
#5880
1#
#5890
b100010 !
b100010 +
b10 *
b10 -
0#
#5900
1#
#5910
b100011 !
b100011 +
b11 *
b11 -
0#
#5920
1#
#5930
b100100 !
b100100 +
b100 *
b100 -
0#
#5940
1#
#5950
b100101 !
b100101 +
b101 *
b101 -
0#
#5960
1#
#5970
b100110 !
b100110 +
b110 *
b110 -
0#
#5980
1#
#5990
b100111 !
b100111 +
b111 *
b111 -
0#
