hw5/fsm/moore.v
module moore
    // state encodings
    #(parameter white_state = 2'b00,
      parameter red_state = 2'b01,
      parameter green_state = 2'b10,
      parameter blue_state = 2'b11)
     (input clk, 
      input reset, // asynchronous reset port
      input red, green, blue, // 3-bit input
      output reg moore_out // moore output: 1 when a state change corresponds to a color change
     );

     reg [1:0] current_state, next_state; // 4 possible states, so we require at least 2 bits
    
    // moore FSM - output is a function of only current state

    // next state combinational logic + output logic (combined)
    always @ (red or green or blue or current_state) begin
        case (current_state)
            red_state: begin
                moore_out = 1;
                if (red) next_state = red_state;
                else next_state = white_state;
            end

            green_state: begin
                moore_out = 1;
                if (green) next_state = green_state;
                else next_state = white_state;
            end

            blue_state: begin
                moore_out = 1;
                if (blue) next_state = blue_state;
                else next_state = white_state;
            end

            white_state: begin
                moore_out = 0;
                if (red) next_state = red_state;
                else if (green) next_state = green_state;
                else if (blue) next_state = blue_state;
                else next_state = white_state;
            end
            
            default: next_state = white_state;

        endcase
    end

    // state registers, sequential logic
    always @ (posedge clk or posedge reset) begin
        if (reset) current_state = white_state; // asynchronous reset
        else current_state = next_state; // take the moore output
    end

endmodule

hw5/fsm/moore_tb.v
`timescale 1us/1fs

module moore_tb
    // state encodings
    #(parameter white_state = 2'b00,
      parameter red_state = 2'b01,
      parameter green_state = 2'b10,
      parameter blue_state = 2'b11)
    ();

    // TB values
    integer tb_cycle_number = 1;
    integer total_errors = 0;  // tracking total errors in assertions
    integer error_count = 0;

    real delay = 0.1;

    // Input registers to drive wires
    reg clk, reset;
    reg red, green, blue;

    // Output wires for registered FSM ports
    wire moore_out; // main output, dubbed moore_out/moore_out inside the FSM modules
    wire [1:0] current_state, next_state;

    // Events
    // Increment TB cycle number
    event tb_cycle_update;
    initial begin 
        forever @(tb_cycle_update) begin
            tb_cycle_number <= tb_cycle_number + 1;
        end
    end

    task error_print_task();
    begin
        begin
            if (error_count == 0) $display("Case Passed:", error_count, " error(s)");
            else $display("Case Failed:", error_count, " error(s)");
            total_errors = total_errors + error_count;
        end
    end
    endtask

    // Watchdog - used for exiting and reports error monitor
    event watchdog;
    initial begin
        forever @(watchdog) begin
            #(delay * 2);
            $display("\nTotal Error Count: ", total_errors);
            $finish;
        end
    end

    event reset_fsm;
    initial begin
        forever @(reset_fsm) begin
            red <= 1'b0;
            green <= 1'b0;
            blue <= 1'b0;
            reset <= 1'b1;
            #(delay) reset <= 1'b0;
            -> tb_cycle_update;
        end
    end

    // Create the FSM
    moore fsm(  
                .clk(clk),
                .reset(reset),
                .red(red), .green(green), .blue(blue),
                .moore_out(moore_out),
                .current_state(current_state), .next_state(next_state)
            );

    initial begin
        clk <= 1'b0;
        forever #delay clk <= ~clk; // 8 MHz clock
    end
    
    event state_loop;
    initial begin 
        forever @(state_loop) begin

            // Transitions for:
            // WHITE TO RED STATE - RED BACK TO WHITE STATE
            $display("\nTesting Transition: 1XX (WhiteState)");
            error_count = 0;
            if (moore_out != 0) error_count = error_count + 1; // ensures that we start at steady state
            red <= 1;
            #(delay * 0.5);
            // before transition
            if (current_state != white_state) error_count = error_count + 1;
            if (next_state != red_state) error_count = error_count + 1; // testing for current & next states
            if (moore_out == 1'b1) error_count = error_count + 1; // FSM output will NOT instantly be 1 (moore)

            error_print_task;

            // after transition
            $display("\nTesting Transition: 1XX (RedState)");
            error_count = 0;
            #(delay * 2);

            if (current_state != red_state) error_count = error_count + 1;
            if (next_state != red_state) error_count = error_count + 1; // testing for current & next states
            if (moore_out != 1'b1) error_count = error_count + 1; // FSM output will NOT instantly be 1 (moore)

            error_print_task;


            $display("\nTesting Transition: 0XX (RedState)");
            error_count = 0;
            red <= 0;
            #(delay * 0.5);
            // before transition
            if (current_state != red_state) error_count = error_count + 1;
            if (next_state != white_state) error_count = error_count + 1; // testing for current & next states
            if (moore_out == 1'b0) error_count = error_count + 1; // FSM output will NOT instantly be 1 (moore)

            error_print_task;

            // after transition
            $display("\nTesting Transition: 000 (WhiteState)");
            error_count = 0;
            #(delay * 2);

            if (current_state != white_state) error_count = error_count + 1;
            if (next_state != white_state) error_count = error_count + 1; // testing for current & next states
            if (moore_out == 1'b1) error_count = error_count + 1; // FSM output will NOT instantly be 1 (moore)

            error_print_task;

            // Transitions for:
            // WHITE TO GREEN STATE - GREEN BACK TO WHITE STATE
            $display("\nTesting Transition: 01X (WhiteState)");
            error_count = 0;
            if (moore_out != 0) error_count = error_count + 1; // ensures that we start at steady state
            green <= 1;
            #(delay * 0.5);
            // before transition
            if (current_state != white_state) error_count = error_count + 1;
            if (next_state != green_state) error_count = error_count + 1; // testing for current & next states
            if (moore_out == 1'b1) error_count = error_count + 1; // FSM output will NOT instantly be 1 (moore)

            error_print_task;

            // after transition
            $display("\nTesting Transition: X1X (GreenState)");
            error_count = 0;
            #(delay * 2);

            if (current_state != green_state) error_count = error_count + 1;
            if (next_state != green_state) error_count = error_count + 1; // testing for current & next states
            if (moore_out != 1'b1) error_count = error_count + 1; // FSM output will NOT instantly be 1 (moore)

            error_print_task;

            $display("\nTesting Transition: X0X (GreenState)");
            error_count = 0;
            green <= 0;
            #(delay * 0.5);
            // before transition
            if (current_state != green_state) error_count = error_count + 1;
            if (next_state != white_state) error_count = error_count + 1; // testing for current & next states
            if (moore_out == 1'b0) error_count = error_count + 1; // FSM output will NOT instantly be 1 (moore)

            error_print_task;

            // after transition
            $display("\nTesting Transition: 000 (WhiteState)");
            error_count = 0;
            #(delay * 2);

            if (current_state != white_state) error_count = error_count + 1;
            if (next_state != white_state) error_count = error_count + 1; // testing for current & next states
            if (moore_out == 1'b1) error_count = error_count + 1; // FSM output will NOT instantly be 1 (moore)

            error_print_task;

            // Transitions for:
            // WHITE TO BLUE STATE - BLUE BACK TO WHITE STATE
            $display("\nTesting Transition: 001 (WhiteState)");
            error_count = 0;
            if (moore_out == 1'b1) error_count = error_count + 1; // ensures that we start at steady state
            #(delay * 0.5);
            blue <= 1;
            #(delay * 0.5);
            // before transition
            if (current_state != white_state) error_count = error_count + 1;
            if (next_state != blue_state) error_count = error_count + 1; // testing for current & next states
            if (moore_out == 1'b1) error_count = error_count + 1; // FSM output will NOT instantly be 1 (moore)

            error_print_task;

            // after transition
            $display("\nTesting Transition: XX1 (BlueState)");
            error_count = 0;
            #(delay * 2);

            if (current_state != blue_state) error_count = error_count + 1;
            if (next_state != blue_state) error_count = error_count + 1; // testing for current & next states
            if (moore_out != 1'b1) error_count = error_count + 1; // FSM output will NOT instantly be 1 (moore)

            error_print_task;

            $display("\nTesting Transition: XX0 (BlueState)");
            error_count = 0;
            blue <= 0;
            #(delay * 0.5);
            // before transition
            if (current_state != blue_state) error_count = error_count + 1;
            if (next_state != white_state) error_count = error_count + 1; // testing for current & next states
            if (moore_out == 1'b0) error_count = error_count + 1; // FSM output will NOT instantly be 1 (moore)

            error_print_task;

            // after transition
            $display("\nTesting Transition: 000 (WhiteState)");
            error_count = 0;
            #(delay * 2);

            if (current_state != white_state) error_count = error_count + 1;
            if (next_state != white_state) error_count = error_count + 1; // testing for current & next states
            if (moore_out == 1'b1) error_count = error_count + 1; // FSM output will NOT instantly be 1 (moore)

            error_print_task;

            -> tb_cycle_update;
        end
    end

    // Test Case Loop
    always @ (*) begin
        case(tb_cycle_number)
            1: -> reset_fsm;
            2: -> state_loop;
            default: -> watchdog;
        endcase
    end

    // Log *vcd file for vieweing in gtkWave
    initial begin
        $dumpfile("moore.vcd");
        $dumpvars(0, moore_tb);
    end
endmodule

hw5/fsm/moore.vcd
$date
	Thu Oct 13 20:20:11 2022
$end
$version
	Icarus Verilog
$end
$timescale
	1fs
$end
$scope module moore_tb $end
$var event 1 ! watchdog $end
$var event 1 " tb_cycle_update $end
$var event 1 # state_loop $end
$var event 1 $ reset_fsm $end
$var wire 2 % next_state [1:0] $end
$var wire 1 & moore_out $end
$var wire 2 ' current_state [1:0] $end
$var parameter 2 ( blue_state $end
$var parameter 2 ) green_state $end
$var parameter 2 * red_state $end
$var parameter 2 + white_state $end
$var reg 1 , blue $end
$var reg 1 - clk $end
$var reg 1 . green $end
$var reg 1 / red $end
$var reg 1 0 reset $end
$var real 1 1 delay $end
$var integer 32 2 error_count [31:0] $end
$var integer 32 3 tb_cycle_number [31:0] $end
$var integer 32 4 total_errors [31:0] $end
$scope module fsm $end
$var wire 1 , blue $end
$var wire 1 - clk $end
$var wire 1 . green $end
$var wire 1 / red $end
$var wire 1 0 reset $end
$var parameter 2 5 blue_state $end
$var parameter 2 6 green_state $end
$var parameter 2 7 red_state $end
$var parameter 2 8 white_state $end
$var reg 2 9 current_state [1:0] $end
$var reg 1 & moore_out $end
$var reg 2 : next_state [1:0] $end
$upscope $end
$scope task error_print_task $end
$upscope $end
$upscope $end
$enddefinitions $end
$comment Show the parameter values. $end
$dumpall
b0 8
b1 7
b10 6
b11 5
b0 +
b1 *
b10 )
b11 (
$end
#0
$dumpvars
b0 :
b0 9
b0 4
b1 3
b0 2
r0.1 1
10
0/
0.
0-
0,
b0 '
0&
b0 %
1$
1#
1"
1!
$end
#100000000
b1 %
b1 :
1/
1#
b10 3
00
1-
1"
#200000000
0-
#300000000
1&
b1 '
b1 9
1-
#350000000
b0 %
b0 :
0/
#400000000
0-
#500000000
0&
b0 '
b0 9
1-
#600000000
b10 %
b10 :
0-
1.
#700000000
1&
b10 '
b10 9
1-
#800000000
0-
#850000000
b0 %
b0 :
0.
#900000000
0&
b0 '
b0 9
1-
#1000000000
0-
#1100000000
1-
#1150000000
b11 %
b11 :
1,
#1200000000
0-
#1300000000
1&
b11 '
b11 9
1-
#1400000000
b0 %
b0 :
0-
0,
#1500000000
0&
b0 '
b0 9
1-
#1600000000
0-
#1650000000
1!
b11 3
1"
