hw4/p2/fifo.v
`timescale 1ns/1ps
// depth is the total size of the FIFO memory, i.e. the total number of elements
// that can be stored inside the memory

// ptr_size is simply the number of bits required to index all elements of the array
// 2**ptr_size = depth

// width_in = width of the data that is read from/written into the FIFO array

module fifo
    #(parameter depth = 96,
      parameter ptr_size = $clog2(depth), // # of bits to completely address all depth entries of the FIFO array
      parameter width_in = 8,
      parameter width_out = 1 * width_in) // TODO

    // inputs
    (input clk_read,
            clk_write, 
            rst,
            enable_read, 
            enable_write,
    input [width_in-1:0] data_in,

    // outputs
    output reg [width_out-1:0] data_out,
    output reg  empty, 
                full, 
                half_full, 
    output reg [ptr_size:0] counter); // counts the number of elements inside the FIFO array

    reg[ptr_size-1:0] ptr_read, ptr_write;           // pointer to read and write addresses  
    reg [width_in-1:0] fifo_mem[depth-1:0];     // actual 2D memory array  

    // loop counter
    integer i;
    // logic for full, empty, and half-full
    // directly use the counter information to determine this
    always @ (counter) begin
        empty = (counter == 0);
        full = (counter == depth);
        half_full = (counter == (depth >> 1)); // 96 in binary is 1100000, half of 96 = 48 is 110000, equivalent to a shift right operation
    end

    // asynchronous reset of the memory
    always @ (posedge rst) begin
        counter <= 0;
        ptr_write <= 0;
        ptr_read <= 0;
        data_out <= 0;
        empty <= 1'b1; // on reset, memory gets emptied
        full <= 1'b0;
        half_full <= 1'b0;
        for (i=0; i < depth; i=i+1) begin
            fifo_mem[i] <= {width_in{1'b0}}; // write 0's to all memory when resetting
        end
    end

    // read logic
    always @ (posedge clk_read) begin
        if (enable_read && !empty) begin
            // read data from fifo, increment read pointer and decrement counter
            // TODO: Make this generic based on multiple read ports
            data_out <= fifo_mem[ptr_read];
            ptr_read <= ptr_read + 1;
            counter <= counter - 1;
        end
        else begin
            // do nothing, latch onto previous values
            data_out <= data_out;
            ptr_read <= ptr_read;
            counter <= counter;
        end
    end

    // write logic
    always @ (posedge clk_write) begin
        if (enable_write && !full) begin
            // write data from fifo, increment write pointer and counter
            fifo_mem[ptr_write] <= data_in;
            ptr_write <= ptr_write + 1;
            counter <= counter + 1;
        end
        else begin
            // do nothing, latch onto previous values
            fifo_mem[ptr_write] <= fifo_mem[ptr_write];
            ptr_write <= ptr_write;
            counter <= counter;
        end
    end



endmodule

hw4/p2/fifo_tb.v
`timescale 1ns/1ps
module fifo_tb
    // Todo: make sure it's consistent with the dvt
    #(parameter depth = 96,
      parameter ptr_size = $clog2(depth), // # of bits to completely address all depth entries of the FIFO array
      parameter width_in = 8,
      parameter width_out = 1 * width_in);

    // FIFO inputs
    reg clk_read,
        clk_write, 
        rst,
        enable_read, 
        enable_write;

    reg [width_in-1:0] data_in;

    // FIFO outputs
    wire [width_out-1:0] data_out;
    wire empty, full, half_full;
    wire [ptr_size:0] counter;

    reg [width_out-1:0] temp_data; // temporary data being read/dequeued from the FIFO mem array

    integer tb_cycle_number = 1;
    integer total_errors = 0;  // tracking total errors in assertions
    integer i; // loop variable

    //////////// EVENTS //////////////

    // Increment TB cycle number
    event tb_cycle_update;
    initial begin 
        forever @(tb_cycle_update) begin
            tb_cycle_number = tb_cycle_number + 1;
        end
    end

    // Increment error variable for error monitor
    event error;
    initial begin 
        forever @(error) begin
            total_errors = total_errors + 1;
        end
    end

    // Error Monitor
    initial  begin
        $display("\t\tTB Cycle Number,\terror count"); 
        $monitor("\t%d,\t%d", tb_cycle_number, total_errors); 
    end 

    // Asynchronous reset
    event rst_low;
    event rst_high;
    initial begin
        forever @(rst_low) rst = 1'b0;
    end

    initial begin
        forever @(rst_high) rst = 1'b1;
    end

    // Handled in task for enqueue/dequeue
    // Enable/Disable events
    // event enable_reader;
    // event enable_writer;
    // event disable_reader;
    // event disable_writer;
    // initial begin
    //     forever @(enable_reader) enable_read = 1'b1;
    // end
    // initial begin
    //     forever @(enable_writer) enable_write = 1'b1;
    // end
    // initial begin
    //     forever @(disable_reader) enable_read = 1'b0;
    // end
    // initial begin
    //     forever @(disable_writer) enable_write = 1'b0;
    // end

    // Create the FIFO queue
    fifo queue(
            // Inputs
            .clk_read(clk_read),
            .clk_write(clk_write), 
            .rst(rst),
            .enable_read(enable_read), 
            .enable_write(enable_write),
            .data_in(data_in),
            // Outputs
            .data_out(data_out),
            .empty(empty), 
            .full(full), 
            .half_full(half_full), 
            .counter(counter));

    // Tasks
    task enqueue(input [width_in-1:0] data);
    begin
        // $display("enqueue called");
        if (full) $display("Warning: Cannot enqueue: FIFO is full.");
        else
            begin
            // $display("Pushed ", data, empty);
            data_in = data;
            enable_write = 1'b1;
            @(posedge clk_write);
                #1 enable_write = 1'b0;
            end
    end
    endtask

    task dequeue(output [width_out-1:0] data);
    begin
        // $display("enqueue called");
        if (empty) $display("Warning: Cannot dequeue: FIFO is empty.");
        else
            begin
            // $display("Pushed ", data, empty);
            data = data_out;
            enable_read = 1'b1;
            @(posedge clk_read);
                #1 enable_read = 1'b0;
            end
    end
    endtask


    // set clock frequencies, reader is independent of writer
    initial begin
        clk_read = 1'b0;
        forever #2 clk_read = ~clk_read;
    end

    initial begin
        clk_write = 1'b0;
        forever #1.5 clk_write = ~clk_write;
    end

    // Test 1: Reset FIFO
    event tb_reset;
    initial begin
        forever @(tb_reset) begin
            #3 -> rst_high;
            #3 -> rst_low;
            if (empty != 1'b1) -> error;  // memory should be empty if it has been reset
            if (full != 1'b0) -> error;
            if (half_full != 1'b0) -> error;
            if (data_out != 0) -> error;  // reader read data when fifo is reset
            if (counter != 0) -> error;
            // update tb cycle, next test case is called manually (reset is used multiple times)
            -> tb_cycle_update;
        end
    end

    // Test 2: Write Until Full
    event tb_write_until_full;
    initial begin
        forever @(tb_write_until_full) begin
            // starting from empty, append elements until queue is full
            for (i=0; i < depth; i=i+1) begin
                if (full != 1'b0) -> error; // queue should not be full since it will have at most depth - 1 elements here in the loop
                enqueue(i);
                if (empty != 1'b0) -> error; // stuff is getting pushed, can't be empty
            end
            // queue is now full, if we push now, full boolean should be true, otherwise error
            enqueue(i);
            if (full != 1'b1) -> error;
            if (empty == 1'b1) -> error;

            // update tb cycle, jump to next test case
            -> tb_cycle_update;
            #5 -> tb_read_until_empty; 
        end
    end
    
    // Test 3: Read Until Empty
    event tb_read_until_empty;
    initial begin
        forever @(tb_read_until_empty) begin
            // starting from full, read elements until queue is empty
            if (empty == 1'b1) -> error;
            if (full == 1'b0) -> error;
            for (i=0; i < depth; i=i+1) begin
                dequeue(temp_data);
                if (full == 1'b1) -> error;
            end
            dequeue(temp_data);
            if (empty != 1'b1) -> error;
            if (full != 1'b0) -> error;
            -> tb_cycle_update;
        end
    end

    initial begin
        #0 -> tb_reset;
        #6 -> tb_write_until_full;
        //#1000 -> tb_read_until_empty;
    end

    initial begin
        // TODO: Make Watchdog event and Stop based on that
        //TODO: add cases for halffull/half empty, read and write at same time, etc.
        #5000 $display("Total Error Count: ", total_errors);
        $finish;
    end

    // Log *vcd file for vieweing in gtkWave
    initial begin
        $dumpfile("fifo.vcd");
        $dumpvars(0, fifo_tb);
    end

endmodule

hw4/p2/fifo.vcd
$date
	Fri Sep 30 01:00:42 2022
$end
$version
	Icarus Verilog
$end
$timescale
	1ps
$end
$scope module fifo_tb $end
$var event 1 ! tb_write_until_full $end
$var event 1 " tb_reset $end
$var event 1 # tb_read_until_empty $end
$var event 1 $ tb_cycle_update $end
$var event 1 % rst_low $end
$var event 1 & rst_high $end
$var event 1 ' error $end
$var wire 1 ( half_full $end
$var wire 1 ) full $end
$var wire 1 * empty $end
$var wire 8 + data_out [7:0] $end
$var wire 8 , counter [7:0] $end
$var parameter 32 - depth $end
$var parameter 32 . ptr_size $end
$var parameter 32 / width_in $end
$var parameter 64 0 width_out $end
$var reg 1 1 clk_read $end
$var reg 1 2 clk_write $end
$var reg 8 3 data_in [7:0] $end
$var reg 1 4 enable_read $end
$var reg 1 5 enable_write $end
$var reg 1 6 rst $end
$var reg 8 7 temp_data [7:0] $end
$var integer 32 8 i [31:0] $end
$var integer 32 9 tb_cycle_number [31:0] $end
$var integer 32 : total_errors [31:0] $end
$scope module queue $end
$var wire 1 1 clk_read $end
$var wire 1 2 clk_write $end
$var wire 8 ; data_in [7:0] $end
$var wire 1 4 enable_read $end
$var wire 1 5 enable_write $end
$var wire 1 6 rst $end
$var parameter 32 < depth $end
$var parameter 32 = ptr_size $end
$var parameter 32 > width_in $end
$var parameter 64 ? width_out $end
$var reg 8 @ counter [7:0] $end
$var reg 8 A data_out [7:0] $end
$var reg 1 * empty $end
$var reg 1 ) full $end
$var reg 1 ( half_full $end
$var reg 7 B ptr_read [6:0] $end
$var reg 7 C ptr_write [6:0] $end
$var integer 32 D i [31:0] $end
$upscope $end
$scope task dequeue $end
$var reg 8 E data [7:0] $end
$upscope $end
$scope task enqueue $end
$var reg 8 F data [7:0] $end
$upscope $end
$upscope $end
$enddefinitions $end
$comment Show the parameter values. $end
$dumpall
b1000 ?
b1000 >
b111 =
b1100000 <
b1000 0
b1000 /
b111 .
b1100000 -
$end
#0
$dumpvars
bx F
bx E
bx D
bx C
bx B
bx A
bx @
bx ;
b0 :
b1 9
bx 8
bx 7
x6
x5
x4
bx 3
02
01
bx ,
bx +
x*
x)
x(
1'
1&
1%
1$
1#
1"
1!
$end
#1500
12
#2000
11
#3000
0(
0)
1*
b0 +
b0 A
b0 B
b0 C
b0 ,
b0 @
b1100000 D
16
02
1&
#4000
01
#4500
12
#6000
b10 9
06
15
b0 3
b0 ;
b0 F
b0 8
02
11
1$
1%
1!
#7500
0*
b1 ,
b1 @
b1 C
12
#8000
01
#8500
b1 3
b1 ;
b1 F
b1 8
15
#9000
02
#10000
11
#10500
b10 ,
b10 @
b10 C
12
#11500
b10 3
b10 ;
b10 F
b10 8
15
#12000
02
01
#13500
b11 ,
b11 @
b11 C
12
#14000
11
#14500
b11 3
b11 ;
b11 F
b11 8
15
#15000
02
#16000
01
#16500
b100 ,
b100 @
b100 C
12
#17500
b100 3
b100 ;
b100 F
b100 8
15
#18000
02
11
#19500
b101 ,
b101 @
b101 C
12
#20000
01
#20500
b101 3
b101 ;
b101 F
b101 8
15
#21000
02
#22000
11
#22500
b110 ,
b110 @
b110 C
12
#23500
b110 3
b110 ;
b110 F
b110 8
15
#24000
02
01
#25500
b111 ,
b111 @
b111 C
12
#26000
11
#26500
b111 3
b111 ;
b111 F
b111 8
15
#27000
02
#28000
01
#28500
b1000 ,
b1000 @
b1000 C
12
#29500
b1000 3
b1000 ;
b1000 F
b1000 8
15
#30000
02
11
#31500
b1001 ,
b1001 @
b1001 C
12
#32000
01
#32500
b1001 3
b1001 ;
b1001 F
b1001 8
15
#33000
02
#34000
11
#34500
b1010 ,
b1010 @
b1010 C
12
#35500
b1010 3
b1010 ;
b1010 F
b1010 8
15
#36000
02
01
#37500
b1011 ,
b1011 @
b1011 C
12
#38000
11
#38500
b1011 3
b1011 ;
b1011 F
b1011 8
15
#39000
02
#40000
01
#40500
b1100 ,
b1100 @
b1100 C
12
#41500
b1100 3
b1100 ;
b1100 F
b1100 8
15
#42000
02
11
#43500
b1101 ,
b1101 @
b1101 C
12
#44000
01
#44500
b1101 3
b1101 ;
b1101 F
b1101 8
15
#45000
02
#46000
11
#46500
b1110 ,
b1110 @
b1110 C
12
#47500
b1110 3
b1110 ;
b1110 F
b1110 8
15
#48000
02
01
#49500
b1111 ,
b1111 @
b1111 C
12
#50000
11
#50500
b1111 3
b1111 ;
b1111 F
b1111 8
15
#51000
02
#52000
01
#52500
b10000 ,
b10000 @
b10000 C
12
#53500
b10000 3
b10000 ;
b10000 F
b10000 8
15
#54000
02
11
#55500
b10001 ,
b10001 @
b10001 C
12
#56000
01
#56500
b10001 3
b10001 ;
b10001 F
b10001 8
15
#57000
02
#58000
11
#58500
b10010 ,
b10010 @
b10010 C
12
#59500
b10010 3
b10010 ;
b10010 F
b10010 8
15
#60000
02
01
#61500
b10011 ,
b10011 @
b10011 C
12
#62000
11
#62500
b10011 3
b10011 ;
b10011 F
b10011 8
15
#63000
02
#64000
01
#64500
b10100 ,
b10100 @
b10100 C
12
#65500
b10100 3
b10100 ;
b10100 F
b10100 8
15
#66000
02
11
#67500
b10101 ,
b10101 @
b10101 C
12
#68000
01
#68500
b10101 3
b10101 ;
b10101 F
b10101 8
15
#69000
02
#70000
11
#70500
b10110 ,
b10110 @
b10110 C
12
#71500
b10110 3
b10110 ;
b10110 F
b10110 8
15
#72000
02
01
#73500
b10111 ,
b10111 @
b10111 C
12
#74000
11
#74500
b10111 3
b10111 ;
b10111 F
b10111 8
15
#75000
02
#76000
01
#76500
b11000 ,
b11000 @
b11000 C
12
#77500
b11000 3
b11000 ;
b11000 F
b11000 8
15
#78000
02
11
#79500
b11001 ,
b11001 @
b11001 C
12
#80000
01
#80500
b11001 3
b11001 ;
b11001 F
b11001 8
15
#81000
02
#82000
11
#82500
b11010 ,
b11010 @
b11010 C
12
#83500
b11010 3
b11010 ;
b11010 F
b11010 8
15
#84000
02
01
#85500
b11011 ,
b11011 @
b11011 C
12
#86000
11
#86500
b11011 3
b11011 ;
b11011 F
b11011 8
15
#87000
02
#88000
01
#88500
b11100 ,
b11100 @
b11100 C
12
#89500
b11100 3
b11100 ;
b11100 F
b11100 8
15
#90000
02
11
#91500
b11101 ,
b11101 @
b11101 C
12
#92000
01
#92500
b11101 3
b11101 ;
b11101 F
b11101 8
15
#93000
02
#94000
11
#94500
b11110 ,
b11110 @
b11110 C
12
#95500
b11110 3
b11110 ;
b11110 F
b11110 8
15
#96000
02
01
#97500
b11111 ,
b11111 @
b11111 C
12
#98000
11
#98500
b11111 3
b11111 ;
b11111 F
b11111 8
15
#99000
02
#100000
01
#100500
b100000 ,
b100000 @
b100000 C
12
#101500
b100000 3
b100000 ;
b100000 F
b100000 8
15
#102000
02
11
#103500
b100001 ,
b100001 @
b100001 C
12
#104000
01
#104500
b100001 3
b100001 ;
b100001 F
b100001 8
15
#105000
02
#106000
11
#106500
b100010 ,
b100010 @
b100010 C
12
#107500
b100010 3
b100010 ;
b100010 F
b100010 8
15
#108000
02
01
#109500
b100011 ,
b100011 @
b100011 C
12
#110000
11
#110500
b100011 3
b100011 ;
b100011 F
b100011 8
15
#111000
02
#112000
01
#112500
b100100 ,
b100100 @
b100100 C
12
#113500
b100100 3
b100100 ;
b100100 F
b100100 8
15
#114000
02
11
#115500
b100101 ,
b100101 @
b100101 C
12
#116000
01
#116500
b100101 3
b100101 ;
b100101 F
b100101 8
15
#117000
02
#118000
11
#118500
b100110 ,
b100110 @
b100110 C
12
#119500
b100110 3
b100110 ;
b100110 F
b100110 8
15
#120000
02
01
#121500
b100111 ,
b100111 @
b100111 C
12
#122000
11
#122500
b100111 3
b100111 ;
b100111 F
b100111 8
15
#123000
02
#124000
01
#124500
b101000 ,
b101000 @
b101000 C
12
#125500
b101000 3
b101000 ;
b101000 F
b101000 8
15
#126000
02
11
#127500
b101001 ,
b101001 @
b101001 C
12
#128000
01
#128500
b101001 3
b101001 ;
b101001 F
b101001 8
15
#129000
02
#130000
11
#130500
b101010 ,
b101010 @
b101010 C
12
#131500
b101010 3
b101010 ;
b101010 F
b101010 8
15
#132000
02
01
#133500
b101011 ,
b101011 @
b101011 C
12
#134000
11
#134500
b101011 3
b101011 ;
b101011 F
b101011 8
15
#135000
02
#136000
01
#136500
b101100 ,
b101100 @
b101100 C
12
#137500
b101100 3
b101100 ;
b101100 F
b101100 8
15
#138000
02
11
#139500
b101101 ,
b101101 @
b101101 C
12
#140000
01
#140500
b101101 3
b101101 ;
b101101 F
b101101 8
15
#141000
02
#142000
11
#142500
b101110 ,
b101110 @
b101110 C
12
#143500
b101110 3
b101110 ;
b101110 F
b101110 8
15
#144000
02
01
#145500
b101111 ,
b101111 @
b101111 C
12
#146000
11
#146500
b101111 3
b101111 ;
b101111 F
b101111 8
15
#147000
02
#148000
01
#148500
1(
b110000 ,
b110000 @
b110000 C
12
#149500
b110000 3
b110000 ;
b110000 F
b110000 8
15
#150000
02
11
#151500
0(
b110001 ,
b110001 @
b110001 C
12
#152000
01
#152500
b110001 3
b110001 ;
b110001 F
b110001 8
15
#153000
02
#154000
11
#154500
b110010 ,
b110010 @
b110010 C
12
#155500
b110010 3
b110010 ;
b110010 F
b110010 8
15
#156000
02
01
#157500
b110011 ,
b110011 @
b110011 C
12
#158000
11
#158500
b110011 3
b110011 ;
b110011 F
b110011 8
15
#159000
02
#160000
01
#160500
b110100 ,
b110100 @
b110100 C
12
#161500
b110100 3
b110100 ;
b110100 F
b110100 8
15
#162000
02
11
#163500
b110101 ,
b110101 @
b110101 C
12
#164000
01
#164500
b110101 3
b110101 ;
b110101 F
b110101 8
15
#165000
02
#166000
11
#166500
b110110 ,
b110110 @
b110110 C
12
#167500
b110110 3
b110110 ;
b110110 F
b110110 8
15
#168000
02
01
#169500
b110111 ,
b110111 @
b110111 C
12
#170000
11
#170500
b110111 3
b110111 ;
b110111 F
b110111 8
15
#171000
02
#172000
01
#172500
b111000 ,
b111000 @
b111000 C
12
#173500
b111000 3
b111000 ;
b111000 F
b111000 8
15
#174000
02
11
#175500
b111001 ,
b111001 @
b111001 C
12
#176000
01
#176500
b111001 3
b111001 ;
b111001 F
b111001 8
15
#177000
02
#178000
11
#178500
b111010 ,
b111010 @
b111010 C
12
#179500
b111010 3
b111010 ;
b111010 F
b111010 8
15
#180000
02
01
#181500
b111011 ,
b111011 @
b111011 C
12
#182000
11
#182500
b111011 3
b111011 ;
b111011 F
b111011 8
15
#183000
02
#184000
01
#184500
b111100 ,
b111100 @
b111100 C
12
#185500
b111100 3
b111100 ;
b111100 F
b111100 8
15
#186000
02
11
#187500
b111101 ,
b111101 @
b111101 C
12
#188000
01
#188500
b111101 3
b111101 ;
b111101 F
b111101 8
15
#189000
02
#190000
11
#190500
b111110 ,
b111110 @
b111110 C
12
#191500
b111110 3
b111110 ;
b111110 F
b111110 8
15
#192000
02
01
#193500
b111111 ,
b111111 @
b111111 C
12
#194000
11
#194500
b111111 3
b111111 ;
b111111 F
b111111 8
15
#195000
02
#196000
01
#196500
b1000000 ,
b1000000 @
b1000000 C
12
#197500
b1000000 3
b1000000 ;
b1000000 F
b1000000 8
15
#198000
02
11
#199500
b1000001 ,
b1000001 @
b1000001 C
12
#200000
01
#200500
b1000001 3
b1000001 ;
b1000001 F
b1000001 8
15
#201000
02
#202000
11
#202500
b1000010 ,
b1000010 @
b1000010 C
12
#203500
b1000010 3
b1000010 ;
b1000010 F
b1000010 8
15
#204000
02
01
#205500
b1000011 ,
b1000011 @
b1000011 C
12
#206000
11
#206500
b1000011 3
b1000011 ;
b1000011 F
b1000011 8
15
#207000
02
#208000
01
#208500
b1000100 ,
b1000100 @
b1000100 C
12
#209500
b1000100 3
b1000100 ;
b1000100 F
b1000100 8
15
#210000
02
11
#211500
b1000101 ,
b1000101 @
b1000101 C
12
#212000
01
#212500
b1000101 3
b1000101 ;
b1000101 F
b1000101 8
15
#213000
02
#214000
11
#214500
b1000110 ,
b1000110 @
b1000110 C
12
#215500
b1000110 3
b1000110 ;
b1000110 F
b1000110 8
15
#216000
02
01
#217500
b1000111 ,
b1000111 @
b1000111 C
12
#218000
11
#218500
b1000111 3
b1000111 ;
b1000111 F
b1000111 8
15
#219000
02
#220000
01
#220500
b1001000 ,
b1001000 @
b1001000 C
12
#221500
b1001000 3
b1001000 ;
b1001000 F
b1001000 8
15
#222000
02
11
#223500
b1001001 ,
b1001001 @
b1001001 C
12
#224000
01
#224500
b1001001 3
b1001001 ;
b1001001 F
b1001001 8
15
#225000
02
#226000
11
#226500
b1001010 ,
b1001010 @
b1001010 C
12
#227500
b1001010 3
b1001010 ;
b1001010 F
b1001010 8
15
#228000
02
01
#229500
b1001011 ,
b1001011 @
b1001011 C
12
#230000
11
#230500
b1001011 3
b1001011 ;
b1001011 F
b1001011 8
15
#231000
02
#232000
01
#232500
b1001100 ,
b1001100 @
b1001100 C
12
#233500
b1001100 3
b1001100 ;
b1001100 F
b1001100 8
15
#234000
02
11
#235500
b1001101 ,
b1001101 @
b1001101 C
12
#236000
01
#236500
b1001101 3
b1001101 ;
b1001101 F
b1001101 8
15
#237000
02
#238000
11
#238500
b1001110 ,
b1001110 @
b1001110 C
12
#239500
b1001110 3
b1001110 ;
b1001110 F
b1001110 8
15
#240000
02
01
#241500
b1001111 ,
b1001111 @
b1001111 C
12
#242000
11
#242500
b1001111 3
b1001111 ;
b1001111 F
b1001111 8
15
#243000
02
#244000
01
#244500
b1010000 ,
b1010000 @
b1010000 C
12
#245500
b1010000 3
b1010000 ;
b1010000 F
b1010000 8
15
#246000
02
11
#247500
b1010001 ,
b1010001 @
b1010001 C
12
#248000
01
#248500
b1010001 3
b1010001 ;
b1010001 F
b1010001 8
15
#249000
02
#250000
11
#250500
b1010010 ,
b1010010 @
b1010010 C
12
#251500
b1010010 3
b1010010 ;
b1010010 F
b1010010 8
15
#252000
02
01
#253500
b1010011 ,
b1010011 @
b1010011 C
12
#254000
11
#254500
b1010011 3
b1010011 ;
b1010011 F
b1010011 8
15
#255000
02
#256000
01
#256500
b1010100 ,
b1010100 @
b1010100 C
12
#257500
b1010100 3
b1010100 ;
b1010100 F
b1010100 8
15
#258000
02
11
#259500
b1010101 ,
b1010101 @
b1010101 C
12
#260000
01
#260500
b1010101 3
b1010101 ;
b1010101 F
b1010101 8
15
#261000
02
#262000
11
#262500
b1010110 ,
b1010110 @
b1010110 C
12
#263500
b1010110 3
b1010110 ;
b1010110 F
b1010110 8
15
#264000
02
01
#265500
b1010111 ,
b1010111 @
b1010111 C
12
#266000
11
#266500
b1010111 3
b1010111 ;
b1010111 F
b1010111 8
15
#267000
02
#268000
01
#268500
b1011000 ,
b1011000 @
b1011000 C
12
#269500
b1011000 3
b1011000 ;
b1011000 F
b1011000 8
15
#270000
02
11
#271500
b1011001 ,
b1011001 @
b1011001 C
12
#272000
01
#272500
b1011001 3
b1011001 ;
b1011001 F
b1011001 8
15
#273000
02
#274000
11
#274500
b1011010 ,
b1011010 @
b1011010 C
12
#275500
b1011010 3
b1011010 ;
b1011010 F
b1011010 8
15
#276000
02
01
#277500
b1011011 ,
b1011011 @
b1011011 C
12
#278000
11
#278500
b1011011 3
b1011011 ;
b1011011 F
b1011011 8
15
#279000
02
#280000
01
#280500
b1011100 ,
b1011100 @
b1011100 C
12
#281500
b1011100 3
b1011100 ;
b1011100 F
b1011100 8
15
#282000
02
11
#283500
b1011101 ,
b1011101 @
b1011101 C
12
#284000
01
#284500
b1011101 3
b1011101 ;
b1011101 F
b1011101 8
15
#285000
02
#286000
11
#286500
b1011110 ,
b1011110 @
b1011110 C
12
#287500
b1011110 3
b1011110 ;
b1011110 F
b1011110 8
15
#288000
02
01
#289500
b1011111 ,
b1011111 @
b1011111 C
12
#290000
11
#290500
b1011111 3
b1011111 ;
b1011111 F
b1011111 8
15
#291000
02
#292000
01
#292500
1)
b1100000 ,
b1100000 @
b1100000 C
12
#293500
b11 9
1$
b1100000 F
b1100000 8
05
#294000
02
11
#295500
12
#296000
01
#297000
02
#298000
11
#298500
14
b0 E
b0 8
12
1#
#300000
02
01
#301500
12
#302000
0)
b1011111 ,
b1011111 @
b1 B
11
#303000
b1 8
b0 7
14
02
#304000
01
#304500
12
#306000
b1011110 ,
b1011110 @
b10 B
b1 +
b1 A
02
11
#307000
b1 E
b10 8
14
#307500
12
#308000
01
#309000
02
#310000
b1011101 ,
b1011101 @
b11 B
b10 +
b10 A
11
#310500
12
#311000
b10 E
b11 8
b1 7
14
#312000
02
01
#313500
12
#314000
b1011100 ,
b1011100 @
b100 B
b11 +
b11 A
11
#315000
b11 E
b100 8
b10 7
14
02
#316000
01
#316500
12
#318000
b1011011 ,
b1011011 @
b101 B
b100 +
b100 A
02
11
#319000
b100 E
b101 8
b11 7
14
#319500
12
#320000
01
#321000
02
#322000
b1011010 ,
b1011010 @
b110 B
b101 +
b101 A
11
#322500
12
#323000
b101 E
b110 8
b100 7
14
#324000
02
01
#325500
12
#326000
b1011001 ,
b1011001 @
b111 B
b110 +
b110 A
11
#327000
b110 E
b111 8
b101 7
14
02
#328000
01
#328500
12
#330000
b1011000 ,
b1011000 @
b1000 B
b111 +
b111 A
02
11
#331000
b111 E
b1000 8
b110 7
14
#331500
12
#332000
01
#333000
02
#334000
b1010111 ,
b1010111 @
b1001 B
b1000 +
b1000 A
11
#334500
12
#335000
b1000 E
b1001 8
b111 7
14
#336000
02
01
#337500
12
#338000
b1010110 ,
b1010110 @
b1010 B
b1001 +
b1001 A
11
#339000
b1001 E
b1010 8
b1000 7
14
02
#340000
01
#340500
12
#342000
b1010101 ,
b1010101 @
b1011 B
b1010 +
b1010 A
02
11
#343000
b1010 E
b1011 8
b1001 7
14
#343500
12
#344000
01
#345000
02
#346000
b1010100 ,
b1010100 @
b1100 B
b1011 +
b1011 A
11
#346500
12
#347000
b1011 E
b1100 8
b1010 7
14
#348000
02
01
#349500
12
#350000
b1010011 ,
b1010011 @
b1101 B
b1100 +
b1100 A
11
#351000
b1100 E
b1101 8
b1011 7
14
02
#352000
01
#352500
12
#354000
b1010010 ,
b1010010 @
b1110 B
b1101 +
b1101 A
02
11
#355000
b1101 E
b1110 8
b1100 7
14
#355500
12
#356000
01
#357000
02
#358000
b1010001 ,
b1010001 @
b1111 B
b1110 +
b1110 A
11
#358500
12
#359000
b1110 E
b1111 8
b1101 7
14
#360000
02
01
#361500
12
#362000
b1010000 ,
b1010000 @
b10000 B
b1111 +
b1111 A
11
#363000
b1111 E
b10000 8
b1110 7
14
02
#364000
01
#364500
12
#366000
b1001111 ,
b1001111 @
b10001 B
b10000 +
b10000 A
02
11
#367000
b10000 E
b10001 8
b1111 7
14
#367500
12
#368000
01
#369000
02
#370000
b1001110 ,
b1001110 @
b10010 B
b10001 +
b10001 A
11
#370500
12
#371000
b10001 E
b10010 8
b10000 7
14
#372000
02
01
#373500
12
#374000
b1001101 ,
b1001101 @
b10011 B
b10010 +
b10010 A
11
#375000
b10010 E
b10011 8
b10001 7
14
02
#376000
01
#376500
12
#378000
b1001100 ,
b1001100 @
b10100 B
b10011 +
b10011 A
02
11
#379000
b10011 E
b10100 8
b10010 7
14
#379500
12
#380000
01
#381000
02
#382000
b1001011 ,
b1001011 @
b10101 B
b10100 +
b10100 A
11
#382500
12
#383000
b10100 E
b10101 8
b10011 7
14
#384000
02
01
#385500
12
#386000
b1001010 ,
b1001010 @
b10110 B
b10101 +
b10101 A
11
#387000
b10101 E
b10110 8
b10100 7
14
02
#388000
01
#388500
12
#390000
b1001001 ,
b1001001 @
b10111 B
b10110 +
b10110 A
02
11
#391000
b10110 E
b10111 8
b10101 7
14
#391500
12
#392000
01
#393000
02
#394000
b1001000 ,
b1001000 @
b11000 B
b10111 +
b10111 A
11
#394500
12
#395000
b10111 E
b11000 8
b10110 7
14
#396000
02
01
#397500
12
#398000
b1000111 ,
b1000111 @
b11001 B
b11000 +
b11000 A
11
#399000
b11000 E
b11001 8
b10111 7
14
02
#400000
01
#400500
12
#402000
b1000110 ,
b1000110 @
b11010 B
b11001 +
b11001 A
02
11
#403000
b11001 E
b11010 8
b11000 7
14
#403500
12
#404000
01
#405000
02
#406000
b1000101 ,
b1000101 @
b11011 B
b11010 +
b11010 A
11
#406500
12
#407000
b11010 E
b11011 8
b11001 7
14
#408000
02
01
#409500
12
#410000
b1000100 ,
b1000100 @
b11100 B
b11011 +
b11011 A
11
#411000
b11011 E
b11100 8
b11010 7
14
02
#412000
01
#412500
12
#414000
b1000011 ,
b1000011 @
b11101 B
b11100 +
b11100 A
02
11
#415000
b11100 E
b11101 8
b11011 7
14
#415500
12
#416000
01
#417000
02
#418000
b1000010 ,
b1000010 @
b11110 B
b11101 +
b11101 A
11
#418500
12
#419000
b11101 E
b11110 8
b11100 7
14
#420000
02
01
#421500
12
#422000
b1000001 ,
b1000001 @
b11111 B
b11110 +
b11110 A
11
#423000
b11110 E
b11111 8
b11101 7
14
02
#424000
01
#424500
12
#426000
b1000000 ,
b1000000 @
b100000 B
b11111 +
b11111 A
02
11
#427000
b11111 E
b100000 8
b11110 7
14
#427500
12
#428000
01
#429000
02
#430000
b111111 ,
b111111 @
b100001 B
b100000 +
b100000 A
11
#430500
12
#431000
b100000 E
b100001 8
b11111 7
14
#432000
02
01
#433500
12
#434000
b111110 ,
b111110 @
b100010 B
b100001 +
b100001 A
11
#435000
b100001 E
b100010 8
b100000 7
14
02
#436000
01
#436500
12
#438000
b111101 ,
b111101 @
b100011 B
b100010 +
b100010 A
02
11
#439000
b100010 E
b100011 8
b100001 7
14
#439500
12
#440000
01
#441000
02
#442000
b111100 ,
b111100 @
b100100 B
b100011 +
b100011 A
11
#442500
12
#443000
b100011 E
b100100 8
b100010 7
14
#444000
02
01
#445500
12
#446000
b111011 ,
b111011 @
b100101 B
b100100 +
b100100 A
11
#447000
b100100 E
b100101 8
b100011 7
14
02
#448000
01
#448500
12
#450000
b111010 ,
b111010 @
b100110 B
b100101 +
b100101 A
02
11
#451000
b100101 E
b100110 8
b100100 7
14
#451500
12
#452000
01
#453000
02
#454000
b111001 ,
b111001 @
b100111 B
b100110 +
b100110 A
11
#454500
12
#455000
b100110 E
b100111 8
b100101 7
14
#456000
02
01
#457500
12
#458000
b111000 ,
b111000 @
b101000 B
b100111 +
b100111 A
11
#459000
b100111 E
b101000 8
b100110 7
14
02
#460000
01
#460500
12
#462000
b110111 ,
b110111 @
b101001 B
b101000 +
b101000 A
02
11
#463000
b101000 E
b101001 8
b100111 7
14
#463500
12
#464000
01
#465000
02
#466000
b110110 ,
b110110 @
b101010 B
b101001 +
b101001 A
11
#466500
12
#467000
b101001 E
b101010 8
b101000 7
14
#468000
02
01
#469500
12
