hw4/p2/fifo.v
`timescale 1ns/1ps
// depth is the total size of the FIFO memory, i.e. the total number of elements
// that can be stored inside the memory

// ptr_size is simply the number of bits required to index all elements of the array
// 2**ptr_size = depth

// width_in = width of the data that is read from/written into the FIFO array

module fifo
    #(parameter depth = 96,
      parameter ptr_size = $clog2(depth), // # of bits to completely address all depth entries of the FIFO array
      parameter width_in = 8,
      parameter width_out = 1 * width_in) // TODO

    // inputs
    (input clk_read,
            clk_write, 
            rst,
            enable_read, 
            enable_write,
    input [width_in-1:0] data_in,

    // outputs
    output reg [width_out-1:0] data_out,
    output reg  empty, 
                full, 
                half_full, 
    output reg [ptr_size:0] counter); // counts the number of elements inside the FIFO array

    reg[ptr_size-1:0] ptr_read, ptr_write;           // pointer to read and write addresses  
    reg [width_in-1:0] fifo_mem[depth-1:0];     // actual 2D memory array  

    // loop counter
    integer i;
    // logic for full, empty, and half-full
    // directly use the counter information to determine this
    always @ (counter) begin
        empty = (counter == 0);
        full = (counter == depth);
        half_full = (counter == (depth >> 1)); // 96 in binary is 1100000, half of 96 = 48 is 110000, equivalent to a shift right operation
    end

    // asynchronous reset of the memory
    always @ (posedge rst) begin
        counter <= 0;
        ptr_write <= 0;
        ptr_read <= 0;
        data_out <= 0;
        empty <= 1'b1; // on reset, memory gets emptied
        full <= 1'b0;
        half_full <= 1'b0;
        for (i=0; i < depth; i=i+1) begin
            fifo_mem[i] <= {width_in{1'b0}}; // write 0's to all memory when resetting
        end
    end

    // read logic
    always @ (posedge clk_read) begin
        if (enable_read && !empty) begin
            // read data from fifo, increment read pointer and decrement counter
            // TODO: Make this generic based on multiple read ports
            data_out <= fifo_mem[ptr_read];
            ptr_read <= ptr_read + 1;
            counter <= counter - 1;
        end
        else begin
            // do nothing, latch onto previous values
            data_out <= data_out;
            ptr_read <= ptr_read;
            counter <= counter;
        end
    end

    // write logic
    always @ (posedge clk_write) begin
        if (enable_write && !full) begin
            // write data from fifo, increment write pointer and counter
            fifo_mem[ptr_write] <= data_in;
            ptr_write <= ptr_write + 1;
            counter <= counter + 1;
        end
        else begin
            // do nothing, latch onto previous values
            fifo_mem[ptr_write] <= fifo_mem[ptr_write];
            ptr_write <= ptr_write;
            counter <= counter;
        end
    end

endmodule

hw4/p2/fifo_tb.v
`timescale 1ns/1ps
module fifo_tb
    // Todo: make sure it's consistent with the dvt
    #(parameter depth = 96,
      parameter ptr_size = $clog2(depth), // # of bits to completely address all depth entries of the FIFO array
      parameter width_in = 8,
      parameter width_out = 1 * width_in);

    // FIFO inputs
    reg clk_read,
        clk_write, 
        rst,
        enable_read, 
        enable_write;

    reg [width_in-1:0] data_in;

    // FIFO outputs
    wire [width_out-1:0] data_out;
    wire empty, full, half_full;
    wire [ptr_size:0] counter;

    integer tb_cycle_number = 1;
    integer total_errors = 0;  // tracking total errors in assertions
    integer temp = 9;          // temporary value, used in test cases
    integer i; // loop variable

    //////////// EVENTS //////////////

    // Increment TB cycle number
    event tb_cycle_update;
    initial begin 
        forever @(tb_cycle_update) begin
            tb_cycle_number = tb_cycle_number + 1;
        end
    end

    // Increment error variable for error monitor
    event error;
    initial begin 
        forever @(error) begin
            total_errors = total_errors + 1;
        end
    end

    // Error Monitor
    initial  begin
        $display("\t\tTime, TB Cycle Number,\terror count"); 
        $monitor("\t%d,\t%d", $time, tb_cycle_number, total_errors); 
    end 

    // Watchdog - used for exiting and reports error monitor
    event watchdog;
    initial begin
        forever @(watchdog) begin
            $display("Total Error Count: ", total_errors);
            $finish;
        end
    end

    // Asynchronous reset
    event rst_low;
    event rst_high;
    initial begin
        forever @(rst_low) rst = 1'b0;
    end

    initial begin
        forever @(rst_high) rst = 1'b1;
    end

    // Create the FIFO queue
    fifo queue(
            // Inputs
            .clk_read(clk_read),
            .clk_write(clk_write), 
            .rst(rst),
            .enable_read(enable_read), 
            .enable_write(enable_write),
            .data_in(data_in),
            // Outputs
            .data_out(data_out),
            .empty(empty), 
            .full(full), 
            .half_full(half_full), 
            .counter(counter));

    // Tasks
    task enqueue(input [width_in-1:0] data);
    begin
        // $display("enqueue called");
        if (full) $display("Warning: Cannot enqueue: FIFO is full.");
        else
            begin
            // $display("Pushed ", data, empty);
            data_in = data;
            enable_write = 1'b1;
            @(posedge clk_write);
                #1 enable_write = 1'b0;
            end
    end
    endtask

    task dequeue();
    begin
        // $display("enqueue called");
        if (empty) $display("Warning: Cannot dequeue: FIFO is empty.");
        else
            begin
            // $display("Pushed ", data, empty);
            enable_read = 1'b1;
            @(posedge clk_read) 
                #1 enable_read = 1'b0;
            end
    end
    endtask


    // set clock frequencies, reader is independent of writer
    initial begin
        clk_read = 1'b0;
        forever #2 clk_read = ~clk_read;
    end

    initial begin
        clk_write = 1'b0;
        forever #1.5 clk_write = ~clk_write;
    end

    // Test 1: Reset FIFO
    event tb_reset;
    initial begin
        forever @(tb_reset) begin
            #3 -> rst_high;
            #3 -> rst_low;
            if (empty != 1'b1) -> error;  // memory should be empty if it has been reset
            if (full != 1'b0) -> error;
            if (half_full != 1'b0) -> error;
            if (data_out != 0) -> error;  // reader read data when fifo is reset
            if (counter != 0) -> error;
            // update tb cycle, next test case is called manually (reset is used multiple times)
            -> tb_cycle_update;
        end
    end

    // Test 2: Write Until Full
    event tb_write_until_full;
    initial begin
        forever @(tb_write_until_full) begin
            // starting from empty, write elements until queue is full
            if (empty == 1'b0) -> error;
            if (full == 1'b1) -> error;
            // starting from empty, append elements until queue is full
            for (i=0; i < depth; i=i+1) begin
                if (full != 1'b0) -> error; // queue should not be full since it will have at most depth - 1 elements here in the loop
                enqueue(i);
                if (empty != 1'b0) -> error; // stuff is getting pushed, can't be empty
            end
            // queue is now full, if we push now, full boolean should be true, otherwise error
            enqueue(i);
            if (full != 1'b1) -> error;
            if (empty == 1'b1) -> error;

            // update tb cycle, jump to next test case
            -> tb_cycle_update;
            #5 -> tb_read_until_empty; 
        end
    end
    
    // Test 3: Read Until Empty
    event tb_read_until_empty;
    initial begin
        forever @(tb_read_until_empty) begin
            // starting from full, read elements until queue is empty
            if (empty == 1'b1) -> error;
            if (full == 1'b0) -> error;
            for (i=0; i < depth; i=i+1) begin
                dequeue();
                if (full == 1'b1) -> error;
            end
            dequeue();
            if (empty != 1'b1) -> error;
            if (full != 1'b0) -> error;
            // update tb cycle, jump to next test case
            -> tb_cycle_update;
            #5 -> tb_half_full_half_empty; 
        end
    end

    // Test 4: Half Full/Half Empty
    event tb_half_full_half_empty;
    initial begin
        forever @(tb_half_full_half_empty) begin
            // starting from empty, write elements until queue is half-full
            if (empty == 1'b0) -> error;
            if (full == 1'b1) -> error;
            if (half_full == 1'b1) -> error;
            // starting from empty, append elements until queue is full
            for (i=0; i < depth / 2; i=i+1) begin
                if (full != 1'b0) -> error; // queue should not be full since it will have at most depth - 1 elements here in the loop
                enqueue(i);
                if (empty != 1'b0) -> error; // stuff is getting pushed, can't be empty
            end
            // queue is now full, if we push now, full boolean should be true, otherwise error
            if (full == 1'b1) -> error;
            if (empty == 1'b1) -> error;
            if (half_full == 1'b0) -> error; // queue should be half full/half-empty, otherwise raise error
            // update tb cycle, jump to next test case
            -> tb_cycle_update;
            -> tb_reset;
            #10 -> tb_read_write_instantaneous;
        end
    end

    // Test 5: Half Full/Half Empty
    event tb_read_write_instantaneous;
    initial begin
        forever @(tb_read_write_instantaneous) begin
            // starting from empty, write and read at the same time
            if (empty == 1'b0) -> error;
            enqueue(temp);
            dequeue();
            if (temp != data_out) -> error;
            // simultaneous writing and reading, should read previously written value first, and second value second
            fork
                enqueue(temp+1);
                dequeue();
            join
            if (data_out != temp) -> error;
            dequeue();
            if (data_out != temp+1) -> error;
            // update tb cycle, trigger watchdog
            -> tb_cycle_update;
            #10 -> watchdog;
        end
    end

    initial begin
        // Start the test suite
        #0 -> tb_reset;
        #6 -> tb_write_until_full;
    end

    // Log *vcd file for vieweing in gtkWave
    initial begin
        $dumpfile("fifo.vcd");
        $dumpvars(0, fifo_tb);
    end

endmodule

hw4/p2/fifo.vcd
$date
	Fri Sep 30 20:14:25 2022
$end
$version
	Icarus Verilog
$end
$timescale
	1ps
$end
$scope module fifo_tb $end
$var event 1 ! watchdog $end
$var event 1 " tb_write_until_full $end
$var event 1 # tb_reset $end
$var event 1 $ tb_read_write_instantaneous $end
$var event 1 % tb_read_until_empty $end
$var event 1 & tb_half_full_half_empty $end
$var event 1 ' tb_cycle_update $end
$var event 1 ( rst_low $end
$var event 1 ) rst_high $end
$var event 1 * error $end
$var wire 1 + half_full $end
$var wire 1 , full $end
$var wire 1 - empty $end
$var wire 8 . data_out [7:0] $end
$var wire 8 / counter [7:0] $end
$var parameter 32 0 depth $end
$var parameter 32 1 ptr_size $end
$var parameter 32 2 width_in $end
$var parameter 64 3 width_out $end
$var reg 1 4 clk_read $end
$var reg 1 5 clk_write $end
$var reg 8 6 data_in [7:0] $end
$var reg 1 7 enable_read $end
$var reg 1 8 enable_write $end
$var reg 1 9 rst $end
$var integer 32 : i [31:0] $end
$var integer 32 ; tb_cycle_number [31:0] $end
$var integer 32 < temp [31:0] $end
$var integer 32 = total_errors [31:0] $end
$scope module queue $end
$var wire 1 4 clk_read $end
$var wire 1 5 clk_write $end
$var wire 8 > data_in [7:0] $end
$var wire 1 7 enable_read $end
$var wire 1 8 enable_write $end
$var wire 1 9 rst $end
$var parameter 32 ? depth $end
$var parameter 32 @ ptr_size $end
$var parameter 32 A width_in $end
$var parameter 64 B width_out $end
$var reg 8 C counter [7:0] $end
$var reg 8 D data_out [7:0] $end
$var reg 1 - empty $end
$var reg 1 , full $end
$var reg 1 + half_full $end
$var reg 7 E ptr_read [6:0] $end
$var reg 7 F ptr_write [6:0] $end
$var integer 32 G i [31:0] $end
$upscope $end
$scope task dequeue $end
$upscope $end
$scope task enqueue $end
$var reg 8 H data [7:0] $end
$upscope $end
$upscope $end
$enddefinitions $end
$comment Show the parameter values. $end
$dumpall
b1000 B
b1000 A
b111 @
b1100000 ?
b1000 3
b1000 2
b111 1
b1100000 0
$end
#0
$dumpvars
bx H
bx G
bx F
bx E
bx D
bx C
bx >
b0 =
b1001 <
b1 ;
bx :
x9
x8
x7
bx 6
05
04
bx /
bx .
x-
x,
x+
1*
1)
1(
1'
1&
1%
1$
1#
1"
1!
$end
#1500
15
#2000
14
#3000
0+
0,
1-
b0 .
b0 D
b0 E
b0 F
b0 /
b0 C
b1100000 G
19
05
1)
#4000
04
#4500
15
#6000
b10 ;
09
18
b0 6
b0 >
b0 H
b0 :
05
14
1'
1(
1"
#7500
0-
b1 /
b1 C
b1 F
15
#8000
04
#8500
b1 6
b1 >
b1 H
b1 :
18
#9000
05
#10000
14
#10500
b10 /
b10 C
b10 F
15
#11500
b10 6
b10 >
b10 H
b10 :
18
#12000
05
04
#13500
b11 /
b11 C
b11 F
15
#14000
14
#14500
b11 6
b11 >
b11 H
b11 :
18
#15000
05
#16000
04
#16500
b100 /
b100 C
b100 F
15
#17500
b100 6
b100 >
b100 H
b100 :
18
#18000
05
14
#19500
b101 /
b101 C
b101 F
15
#20000
04
#20500
b101 6
b101 >
b101 H
b101 :
18
#21000
05
#22000
14
#22500
b110 /
b110 C
b110 F
15
#23500
b110 6
b110 >
b110 H
b110 :
18
#24000
05
04
#25500
b111 /
b111 C
b111 F
15
#26000
14
#26500
b111 6
b111 >
b111 H
b111 :
18
#27000
05
#28000
04
#28500
b1000 /
b1000 C
b1000 F
15
#29500
b1000 6
b1000 >
b1000 H
b1000 :
18
#30000
05
14
#31500
b1001 /
b1001 C
b1001 F
15
#32000
04
#32500
b1001 6
b1001 >
b1001 H
b1001 :
18
#33000
05
#34000
14
#34500
b1010 /
b1010 C
b1010 F
15
#35500
b1010 6
b1010 >
b1010 H
b1010 :
18
#36000
05
04
#37500
b1011 /
b1011 C
b1011 F
15
#38000
14
#38500
b1011 6
b1011 >
b1011 H
b1011 :
18
#39000
05
#40000
04
#40500
b1100 /
b1100 C
b1100 F
15
#41500
b1100 6
b1100 >
b1100 H
b1100 :
18
#42000
05
14
#43500
b1101 /
b1101 C
b1101 F
15
#44000
04
#44500
b1101 6
b1101 >
b1101 H
b1101 :
18
#45000
05
#46000
14
#46500
b1110 /
b1110 C
b1110 F
15
#47500
b1110 6
b1110 >
b1110 H
b1110 :
18
#48000
05
04
#49500
b1111 /
b1111 C
b1111 F
15
#50000
14
#50500
b1111 6
b1111 >
b1111 H
b1111 :
18
#51000
05
#52000
04
#52500
b10000 /
b10000 C
b10000 F
15
#53500
b10000 6
b10000 >
b10000 H
b10000 :
18
#54000
05
14
#55500
b10001 /
b10001 C
b10001 F
15
#56000
04
#56500
b10001 6
b10001 >
b10001 H
b10001 :
18
#57000
05
#58000
14
#58500
b10010 /
b10010 C
b10010 F
15
#59500
b10010 6
b10010 >
b10010 H
b10010 :
18
#60000
05
04
#61500
b10011 /
b10011 C
b10011 F
15
#62000
14
#62500
b10011 6
b10011 >
b10011 H
b10011 :
18
#63000
05
#64000
04
#64500
b10100 /
b10100 C
b10100 F
15
#65500
b10100 6
b10100 >
b10100 H
b10100 :
18
#66000
05
14
#67500
b10101 /
b10101 C
b10101 F
15
#68000
04
#68500
b10101 6
b10101 >
b10101 H
b10101 :
18
#69000
05
#70000
14
#70500
b10110 /
b10110 C
b10110 F
15
#71500
b10110 6
b10110 >
b10110 H
b10110 :
18
#72000
05
04
#73500
b10111 /
b10111 C
b10111 F
15
#74000
14
#74500
b10111 6
b10111 >
b10111 H
b10111 :
18
#75000
05
#76000
04
#76500
b11000 /
b11000 C
b11000 F
15
#77500
b11000 6
b11000 >
b11000 H
b11000 :
18
#78000
05
14
#79500
b11001 /
b11001 C
b11001 F
15
#80000
04
#80500
b11001 6
b11001 >
b11001 H
b11001 :
18
#81000
05
#82000
14
#82500
b11010 /
b11010 C
b11010 F
15
#83500
b11010 6
b11010 >
b11010 H
b11010 :
18
#84000
05
04
#85500
b11011 /
b11011 C
b11011 F
15
#86000
14
#86500
b11011 6
b11011 >
b11011 H
b11011 :
18
#87000
05
#88000
04
#88500
b11100 /
b11100 C
b11100 F
15
#89500
b11100 6
b11100 >
b11100 H
b11100 :
18
#90000
05
14
#91500
b11101 /
b11101 C
b11101 F
15
#92000
04
#92500
b11101 6
b11101 >
b11101 H
b11101 :
18
#93000
05
#94000
14
#94500
b11110 /
b11110 C
b11110 F
15
#95500
b11110 6
b11110 >
b11110 H
b11110 :
18
#96000
05
04
#97500
b11111 /
b11111 C
b11111 F
15
#98000
14
#98500
b11111 6
b11111 >
b11111 H
b11111 :
18
#99000
05
#100000
04
#100500
b100000 /
b100000 C
b100000 F
15
#101500
b100000 6
b100000 >
b100000 H
b100000 :
18
#102000
05
14
#103500
b100001 /
b100001 C
b100001 F
15
#104000
04
#104500
b100001 6
b100001 >
b100001 H
b100001 :
18
#105000
05
#106000
14
#106500
b100010 /
b100010 C
b100010 F
15
#107500
b100010 6
b100010 >
b100010 H
b100010 :
18
#108000
05
04
#109500
b100011 /
b100011 C
b100011 F
15
#110000
14
#110500
b100011 6
b100011 >
b100011 H
b100011 :
18
#111000
05
#112000
04
#112500
b100100 /
b100100 C
b100100 F
15
#113500
b100100 6
b100100 >
b100100 H
b100100 :
18
#114000
05
14
#115500
b100101 /
b100101 C
b100101 F
15
#116000
04
#116500
b100101 6
b100101 >
b100101 H
b100101 :
18
#117000
05
#118000
14
#118500
b100110 /
b100110 C
b100110 F
15
#119500
b100110 6
b100110 >
b100110 H
b100110 :
18
#120000
05
04
#121500
b100111 /
b100111 C
b100111 F
15
#122000
14
#122500
b100111 6
b100111 >
b100111 H
b100111 :
18
#123000
05
#124000
04
#124500
b101000 /
b101000 C
b101000 F
15
#125500
b101000 6
b101000 >
b101000 H
b101000 :
18
#126000
05
14
#127500
b101001 /
b101001 C
b101001 F
15
#128000
04
#128500
b101001 6
b101001 >
b101001 H
b101001 :
18
#129000
05
#130000
14
#130500
b101010 /
b101010 C
b101010 F
15
#131500
b101010 6
b101010 >
b101010 H
b101010 :
18
#132000
05
04
#133500
b101011 /
b101011 C
b101011 F
15
#134000
14
#134500
b101011 6
b101011 >
b101011 H
b101011 :
18
#135000
05
#136000
04
#136500
b101100 /
b101100 C
b101100 F
15
#137500
b101100 6
b101100 >
b101100 H
b101100 :
18
#138000
05
14
#139500
b101101 /
b101101 C
b101101 F
15
#140000
04
#140500
b101101 6
b101101 >
b101101 H
b101101 :
18
#141000
05
#142000
14
#142500
b101110 /
b101110 C
b101110 F
15
#143500
b101110 6
b101110 >
b101110 H
b101110 :
18
#144000
05
04
#145500
b101111 /
b101111 C
b101111 F
15
#146000
14
#146500
b101111 6
b101111 >
b101111 H
b101111 :
18
#147000
05
#148000
04
#148500
1+
b110000 /
b110000 C
b110000 F
15
#149500
b110000 6
b110000 >
b110000 H
b110000 :
18
#150000
05
14
#151500
0+
b110001 /
b110001 C
b110001 F
15
#152000
04
#152500
b110001 6
b110001 >
b110001 H
b110001 :
18
#153000
05
#154000
14
#154500
b110010 /
b110010 C
b110010 F
15
#155500
b110010 6
b110010 >
b110010 H
b110010 :
18
#156000
05
04
#157500
b110011 /
b110011 C
b110011 F
15
#158000
14
#158500
b110011 6
b110011 >
b110011 H
b110011 :
18
#159000
05
#160000
04
#160500
b110100 /
b110100 C
b110100 F
15
#161500
b110100 6
b110100 >
b110100 H
b110100 :
18
#162000
05
14
#163500
b110101 /
b110101 C
b110101 F
15
#164000
04
#164500
b110101 6
b110101 >
b110101 H
b110101 :
18
#165000
05
#166000
14
#166500
b110110 /
b110110 C
b110110 F
15
#167500
b110110 6
b110110 >
b110110 H
b110110 :
18
#168000
05
04
#169500
b110111 /
b110111 C
b110111 F
15
#170000
14
#170500
b110111 6
b110111 >
b110111 H
b110111 :
18
#171000
05
#172000
04
#172500
b111000 /
b111000 C
b111000 F
15
#173500
b111000 6
b111000 >
b111000 H
b111000 :
18
#174000
05
14
#175500
b111001 /
b111001 C
b111001 F
15
#176000
04
#176500
b111001 6
b111001 >
b111001 H
b111001 :
18
#177000
05
#178000
14
#178500
b111010 /
b111010 C
b111010 F
15
#179500
b111010 6
b111010 >
b111010 H
b111010 :
18
#180000
05
04
#181500
b111011 /
b111011 C
b111011 F
15
#182000
14
#182500
b111011 6
b111011 >
b111011 H
b111011 :
18
#183000
05
#184000
04
#184500
b111100 /
b111100 C
b111100 F
15
#185500
b111100 6
b111100 >
b111100 H
b111100 :
18
#186000
05
14
#187500
b111101 /
b111101 C
b111101 F
15
#188000
04
#188500
b111101 6
b111101 >
b111101 H
b111101 :
18
#189000
05
#190000
14
#190500
b111110 /
b111110 C
b111110 F
15
#191500
b111110 6
b111110 >
b111110 H
b111110 :
18
#192000
05
04
#193500
b111111 /
b111111 C
b111111 F
15
#194000
14
#194500
b111111 6
b111111 >
b111111 H
b111111 :
18
#195000
05
#196000
04
#196500
b1000000 /
b1000000 C
b1000000 F
15
#197500
b1000000 6
b1000000 >
b1000000 H
b1000000 :
18
#198000
05
14
#199500
b1000001 /
b1000001 C
b1000001 F
15
#200000
04
#200500
b1000001 6
b1000001 >
b1000001 H
b1000001 :
18
#201000
05
#202000
14
#202500
b1000010 /
b1000010 C
b1000010 F
15
#203500
b1000010 6
b1000010 >
b1000010 H
b1000010 :
18
#204000
05
04
#205500
b1000011 /
b1000011 C
b1000011 F
15
#206000
14
#206500
b1000011 6
b1000011 >
b1000011 H
b1000011 :
18
#207000
05
#208000
04
#208500
b1000100 /
b1000100 C
b1000100 F
15
#209500
b1000100 6
b1000100 >
b1000100 H
b1000100 :
18
#210000
05
14
#211500
b1000101 /
b1000101 C
b1000101 F
15
#212000
04
#212500
b1000101 6
b1000101 >
b1000101 H
b1000101 :
18
#213000
05
#214000
14
#214500
b1000110 /
b1000110 C
b1000110 F
15
#215500
b1000110 6
b1000110 >
b1000110 H
b1000110 :
18
#216000
05
04
#217500
b1000111 /
b1000111 C
b1000111 F
15
#218000
14
#218500
b1000111 6
b1000111 >
b1000111 H
b1000111 :
18
#219000
05
#220000
04
#220500
b1001000 /
b1001000 C
b1001000 F
15
#221500
b1001000 6
b1001000 >
b1001000 H
b1001000 :
18
#222000
05
14
#223500
b1001001 /
b1001001 C
b1001001 F
15
#224000
04
#224500
b1001001 6
b1001001 >
b1001001 H
b1001001 :
18
#225000
05
#226000
14
#226500
b1001010 /
b1001010 C
b1001010 F
15
#227500
b1001010 6
b1001010 >
b1001010 H
b1001010 :
18
#228000
05
04
#229500
b1001011 /
b1001011 C
b1001011 F
15
#230000
14
#230500
b1001011 6
b1001011 >
b1001011 H
b1001011 :
18
#231000
05
#232000
04
#232500
b1001100 /
b1001100 C
b1001100 F
15
#233500
b1001100 6
b1001100 >
b1001100 H
b1001100 :
18
#234000
05
14
#235500
b1001101 /
b1001101 C
b1001101 F
15
#236000
04
#236500
b1001101 6
b1001101 >
b1001101 H
b1001101 :
18
#237000
05
#238000
14
#238500
b1001110 /
b1001110 C
b1001110 F
15
#239500
b1001110 6
b1001110 >
b1001110 H
b1001110 :
18
#240000
05
04
#241500
b1001111 /
b1001111 C
b1001111 F
15
#242000
14
#242500
b1001111 6
b1001111 >
b1001111 H
b1001111 :
18
#243000
05
#244000
04
#244500
b1010000 /
b1010000 C
b1010000 F
15
#245500
b1010000 6
b1010000 >
b1010000 H
b1010000 :
18
#246000
05
14
#247500
b1010001 /
b1010001 C
b1010001 F
15
#248000
04
#248500
b1010001 6
b1010001 >
b1010001 H
b1010001 :
18
#249000
05
#250000
14
#250500
b1010010 /
b1010010 C
b1010010 F
15
#251500
b1010010 6
b1010010 >
b1010010 H
b1010010 :
18
#252000
05
04
#253500
b1010011 /
b1010011 C
b1010011 F
15
#254000
14
#254500
b1010011 6
b1010011 >
b1010011 H
b1010011 :
18
#255000
05
#256000
04
#256500
b1010100 /
b1010100 C
b1010100 F
15
#257500
b1010100 6
b1010100 >
b1010100 H
b1010100 :
18
#258000
05
14
#259500
b1010101 /
b1010101 C
b1010101 F
15
#260000
04
#260500
b1010101 6
b1010101 >
b1010101 H
b1010101 :
18
#261000
05
#262000
14
#262500
b1010110 /
b1010110 C
b1010110 F
15
#263500
b1010110 6
b1010110 >
b1010110 H
b1010110 :
18
#264000
05
04
#265500
b1010111 /
b1010111 C
b1010111 F
15
#266000
14
#266500
b1010111 6
b1010111 >
b1010111 H
b1010111 :
18
#267000
05
#268000
04
#268500
b1011000 /
b1011000 C
b1011000 F
15
#269500
b1011000 6
b1011000 >
b1011000 H
b1011000 :
18
#270000
05
14
#271500
b1011001 /
b1011001 C
b1011001 F
15
#272000
04
#272500
b1011001 6
b1011001 >
b1011001 H
b1011001 :
18
#273000
05
#274000
14
#274500
b1011010 /
b1011010 C
b1011010 F
15
#275500
b1011010 6
b1011010 >
b1011010 H
b1011010 :
18
#276000
05
04
#277500
b1011011 /
b1011011 C
b1011011 F
15
#278000
14
#278500
b1011011 6
b1011011 >
b1011011 H
b1011011 :
18
#279000
05
#280000
04
#280500
b1011100 /
b1011100 C
b1011100 F
15
#281500
b1011100 6
b1011100 >
b1011100 H
b1011100 :
18
#282000
05
14
#283500
b1011101 /
b1011101 C
b1011101 F
15
#284000
04
#284500
b1011101 6
b1011101 >
b1011101 H
b1011101 :
18
#285000
05
#286000
14
#286500
b1011110 /
b1011110 C
b1011110 F
15
#287500
b1011110 6
b1011110 >
b1011110 H
b1011110 :
18
#288000
05
04
#289500
b1011111 /
b1011111 C
b1011111 F
15
#290000
14
#290500
b1011111 6
b1011111 >
b1011111 H
b1011111 :
18
#291000
05
#292000
04
#292500
1,
b1100000 /
b1100000 C
b1100000 F
15
#293500
b11 ;
1'
b1100000 H
b1100000 :
08
#294000
05
14
#295500
15
#296000
04
#297000
05
#298000
14
#298500
17
b0 :
15
1%
#300000
05
04
#301500
15
#302000
0,
b1011111 /
b1011111 C
b1 E
14
#303000
b1 :
17
05
#304000
04
#304500
15
#306000
b1011110 /
b1011110 C
b10 E
b1 .
b1 D
05
14
#307000
b10 :
17
#307500
15
#308000
04
#309000
05
#310000
b1011101 /
b1011101 C
b11 E
b10 .
b10 D
14
#310500
15
#311000
b11 :
17
#312000
05
04
#313500
15
#314000
b1011100 /
b1011100 C
b100 E
b11 .
b11 D
14
#315000
b100 :
17
05
#316000
04
#316500
15
#318000
b1011011 /
b1011011 C
b101 E
b100 .
b100 D
05
14
#319000
b101 :
17
#319500
15
#320000
04
#321000
05
#322000
b1011010 /
b1011010 C
b110 E
b101 .
b101 D
14
#322500
15
#323000
b110 :
17
#324000
05
04
#325500
15
#326000
b1011001 /
b1011001 C
b111 E
b110 .
b110 D
14
#327000
b111 :
17
05
#328000
04
#328500
15
#330000
b1011000 /
b1011000 C
b1000 E
b111 .
b111 D
05
14
#331000
b1000 :
17
#331500
15
#332000
04
#333000
05
#334000
b1010111 /
b1010111 C
b1001 E
b1000 .
b1000 D
14
#334500
15
#335000
b1001 :
17
#336000
05
04
#337500
15
#338000
b1010110 /
b1010110 C
b1010 E
b1001 .
b1001 D
14
#339000
b1010 :
17
05
#340000
04
#340500
15
#342000
b1010101 /
b1010101 C
b1011 E
b1010 .
b1010 D
05
14
#343000
b1011 :
17
#343500
15
#344000
04
#345000
05
#346000
b1010100 /
b1010100 C
b1100 E
b1011 .
b1011 D
14
#346500
15
#347000
b1100 :
17
#348000
05
04
#349500
15
#350000
b1010011 /
b1010011 C
b1101 E
b1100 .
b1100 D
14
#351000
b1101 :
17
05
#352000
04
#352500
15
#354000
b1010010 /
b1010010 C
b1110 E
b1101 .
b1101 D
05
14
#355000
b1110 :
17
#355500
15
#356000
04
#357000
05
#358000
b1010001 /
b1010001 C
b1111 E
b1110 .
b1110 D
14
#358500
15
#359000
b1111 :
17
#360000
05
04
#361500
15
#362000
b1010000 /
b1010000 C
b10000 E
b1111 .
b1111 D
14
#363000
b10000 :
17
05
#364000
04
#364500
15
#366000
b1001111 /
b1001111 C
b10001 E
b10000 .
b10000 D
05
14
#367000
b10001 :
17
#367500
15
#368000
04
#369000
05
#370000
b1001110 /
b1001110 C
b10010 E
b10001 .
b10001 D
14
#370500
15
#371000
b10010 :
17
#372000
05
04
#373500
15
#374000
b1001101 /
b1001101 C
b10011 E
b10010 .
b10010 D
14
#375000
b10011 :
17
05
#376000
04
#376500
15
#378000
b1001100 /
b1001100 C
b10100 E
b10011 .
b10011 D
05
14
#379000
b10100 :
17
#379500
15
#380000
04
#381000
05
#382000
b1001011 /
b1001011 C
b10101 E
b10100 .
b10100 D
14
#382500
15
#383000
b10101 :
17
#384000
05
04
#385500
15
#386000
b1001010 /
b1001010 C
b10110 E
b10101 .
b10101 D
14
#387000
b10110 :
17
05
#388000
04
#388500
15
#390000
b1001001 /
b1001001 C
b10111 E
b10110 .
b10110 D
05
14
#391000
b10111 :
17
#391500
15
#392000
04
#393000
05
#394000
b1001000 /
b1001000 C
b11000 E
b10111 .
b10111 D
14
#394500
15
#395000
b11000 :
17
#396000
05
04
#397500
15
#398000
b1000111 /
b1000111 C
b11001 E
b11000 .
b11000 D
14
#399000
b11001 :
17
05
#400000
04
#400500
15
#402000
b1000110 /
b1000110 C
b11010 E
b11001 .
b11001 D
05
14
#403000
b11010 :
17
#403500
15
#404000
04
#405000
05
#406000
b1000101 /
b1000101 C
b11011 E
b11010 .
b11010 D
14
#406500
15
#407000
b11011 :
17
#408000
05
04
#409500
15
#410000
b1000100 /
b1000100 C
b11100 E
b11011 .
b11011 D
14
#411000
b11100 :
17
05
#412000
04
#412500
15
#414000
b1000011 /
b1000011 C
b11101 E
b11100 .
b11100 D
05
14
#415000
b11101 :
17
#415500
15
#416000
04
#417000
05
#418000
b1000010 /
b1000010 C
b11110 E
b11101 .
b11101 D
14
#418500
15
#419000
b11110 :
17
#420000
05
04
#421500
15
#422000
b1000001 /
b1000001 C
b11111 E
b11110 .
b11110 D
14
#423000
b11111 :
17
05
#424000
04
#424500
15
#426000
b1000000 /
b1000000 C
b100000 E
b11111 .
b11111 D
05
14
#427000
b100000 :
17
#427500
15
#428000
04
#429000
05
#430000
b111111 /
b111111 C
b100001 E
b100000 .
b100000 D
14
#430500
15
#431000
b100001 :
17
#432000
05
04
#433500
15
#434000
b111110 /
b111110 C
b100010 E
b100001 .
b100001 D
14
#435000
b100010 :
17
05
#436000
04
#436500
15
#438000
b111101 /
b111101 C
b100011 E
b100010 .
b100010 D
05
14
#439000
b100011 :
17
#439500
15
#440000
04
#441000
05
#442000
b111100 /
b111100 C
b100100 E
b100011 .
b100011 D
14
#442500
15
#443000
b100100 :
17
#444000
05
04
#445500
15
#446000
b111011 /
b111011 C
b100101 E
b100100 .
b100100 D
14
#447000
b100101 :
17
05
#448000
04
#448500
15
#450000
b111010 /
b111010 C
b100110 E
b100101 .
b100101 D
05
14
#451000
b100110 :
17
#451500
15
#452000
04
#453000
05
#454000
b111001 /
b111001 C
b100111 E
b100110 .
b100110 D
14
#454500
15
#455000
b100111 :
17
#456000
05
04
#457500
15
#458000
b111000 /
b111000 C
b101000 E
b100111 .
b100111 D
14
#459000
b101000 :
17
05
#460000
04
#460500
15
#462000
b110111 /
b110111 C
b101001 E
b101000 .
b101000 D
05
14
#463000
b101001 :
17
#463500
15
#464000
04
#465000
05
#466000
b110110 /
b110110 C
b101010 E
b101001 .
b101001 D
14
#466500
15
#467000
b101010 :
17
#468000
05
04
#469500
15
#470000
b110101 /
b110101 C
b101011 E
b101010 .
b101010 D
14
#471000
b101011 :
17
05
#472000
04
#472500
15
#474000
b110100 /
b110100 C
b101100 E
b101011 .
b101011 D
05
14
#475000
b101100 :
17
#475500
15
#476000
04
#477000
05
#478000
b110011 /
b110011 C
b101101 E
b101100 .
b101100 D
14
#478500
15
#479000
b101101 :
17
#480000
05
04
#481500
15
