hw3/p1/d_flipflop.v
/* 
A rising edge D flip flop with synchronous reset
*/

module d_flipflop (
    output reg Q,
    input D, clk, rst  
);

    always @(posedge clk) begin
        if (rst == 1'b1) Q <= 0;
        else begin
            Q <= D; 
        end 
    end
endmodule

hw3/p1/p5-15.v
/* 

From book - Figure P5-15

This module instantiates a rising-edge synchronous reset D flipflop from d_flipflop.v 
*/

module p5_15 (
    output wire P_odd,
    input D_in, clk, rst       
);

    wire D;
    assign D = D_in ^ P_odd; // xor operator

    d_flipflop dff(
        .D(D),
        .Q(P_odd),
        .clk(clk), 
        .rst(rst));

endmodule

hw3/p1/p5-15_tb.v
/* 

From book - example 5.46

I have assumed a word size of 4 bits, because I was running into compilation errors

*/

module p5_15_tb ();

    reg  D_in, clk, rst;
    output P_odd;

    p5_15 dvt(
        .P_odd(P_odd), 
        .D_in(D_in), 
        .clk(clk), 
        .rst(rst));

    initial clk=1'b0;
    always #10 clk=~clk;

    initial rst=1'b1;
    initial begin
        #20 rst = 1'b0;
        #400 rst = 1'b1;
        #20 rst = 1'b0;
    end

    initial D_in=1'b0;

    initial begin
        // alternate between 1 and 0, with a bigger gap in between
        #25 D_in=1'b1;
        #25 D_in=1'b0;
        #25 D_in=1'b1;
        #25 D_in=1'b0;
        #300 D_in=1'b1;
        #25 D_in=1'b0;
        #25 D_in=1'b1;
        #25 D_in=1'b0;
        #25 D_in=1'b1;
        #25 D_in=1'b0;
        #300 D_in=1'b1;
    end

    initial begin
        #1000 $finish;
    end

    // Log *vcd file for vieweing in gtkWave
    initial begin
        $dumpfile("p5_15_vcd.vcd");
        $dumpvars(0, p5_15_tb);
    end

endmodule

hw3/p1/p5_15_vcd.vcd
$date
	Sun Sep 18 20:59:20 2022
$end
$version
	Icarus Verilog
$end
$timescale
	1s
$end
$scope module p5_15_tb $end
$var wire 1 ! P_odd $end
$var reg 1 " D_in $end
$var reg 1 # clk $end
$var reg 1 $ rst $end
$scope module dvt $end
$var wire 1 % D $end
$var wire 1 " D_in $end
$var wire 1 # clk $end
$var wire 1 $ rst $end
$var wire 1 ! P_odd $end
$scope module dff $end
$var wire 1 % D $end
$var wire 1 # clk $end
$var wire 1 $ rst $end
$var reg 1 ! Q $end
$upscope $end
$upscope $end
$upscope $end
$enddefinitions $end
$comment Show the parameter values. $end
$dumpall
$end
#0
$dumpvars
x%
1$
0#
0"
x!
$end
#10
0%
0!
1#
#20
0#
0$
#25
1%
1"
#30
0%
1!
1#
#40
0#
#50
1%
1#
0"
#60
0#
#70
1#
#75
0%
1"
#80
0#
#90
1%
0!
1#
#100
0%
0#
0"
#110
1#
#120
0#
#130
1#
#140
0#
#150
1#
#160
0#
#170
1#
#180
0#
#190
1#
#200
0#
#210
1#
#220
0#
#230
1#
#240
0#
#250
1#
#260
0#
#270
1#
#280
0#
#290
1#
#300
0#
#310
1#
#320
0#
#330
1#
#340
0#
#350
1#
#360
0#
#370
1#
#380
0#
#390
1#
#400
1%
0#
1"
#410
0%
1!
1#
#420
0#
1$
#425
1%
0"
#430
0%
0!
1#
#440
0#
0$
#450
1!
0%
1#
1"
#460
0#
#470
1%
0!
1#
#475
0%
0"
#480
0#
#490
1#
#500
1%
0#
1"
#510
0%
1!
1#
#520
0#
#525
1%
0"
#530
1#
#540
0#
#550
1#
#560
0#
#570
1#
#580
0#
#590
1#
#600
0#
#610
1#
#620
0#
#630
1#
#640
0#
#650
1#
#660
0#
#670
1#
#680
0#
#690
1#
#700
0#
#710
1#
#720
0#
#730
1#
#740
0#
#750
1#
#760
0#
#770
1#
#780
0#
#790
1#
#800
0#
#810
1#
#820
0#
#825
0%
1"
#830
1%
0!
1#
#840
0#
#850
0%
1!
1#
#860
0#
#870
1%
0!
1#
#880
0#
#890
0%
1!
1#
#900
0#
#910
1%
0!
1#
#920
0#
#930
0%
1!
1#
#940
0#
#950
1%
0!
1#
#960
0#
#970
0%
1!
1#
#980
0#
#990
1%
0!
1#
