hw3/p1/universal_shift_reg.v
/* 

From book - example 5.46

I have assumed a word size of 4 bits, because I was running into compilation errors

*/

module universal_shift_reg (
    output reg[3:0] data_out,
    output msb_out, lsb_out,
    input [3:0]  data_in,
    input msb_in, lsb_in,
    input s1, s0, clk, rst             
);

    assign msb_out = data_out[3];
    assign lsb_out = data_out[0];

    always @(posedge clk) begin
        if (rst == 1'b1) data_out <= 0;
        else case ({s1, s0})
            0: data_out <= data_out;                // hold
            1: data_out <= {msb_in, data_out[3:1]}; // serial shift from msb
            2: data_out <= {data_out[2:0], lsb_in}; // serial shift from lsb
            3: data_out <= data_in;                 // parallel load
        endcase
    end
endmodule

hw3/p1/universal_shift_reg_tb.v
/* 

From book - example 5.46

I have assumed a word size of 4 bits, because I was running into compilation errors

*/

module universal_shift_reg_tb ();
    wire [3:0] data_out;
    wire msb_out, lsb_out;
    reg  [3:0] data_in;
    reg msb_in, lsb_in;
    reg  s1, s0, clk, rst;

    universal_shift_reg usr(
        .data_out(data_out), 
        .msb_out(msb_out), 
        .lsb_out(lsb_out),
        .data_in(data_in), 
        .msb_in(msb_in), 
        .lsb_in(lsb_in),
        .s1(s1), 
        .s0(s0), 
        .clk(clk), 
        .rst(rst));

    // choosing inputs to match waveforms from the book
    // rst
    initial begin
        #0   rst=1'b1;
        #22  rst=1'b0;
        #121  rst=1'b1;
        #22  rst=1'b0;
        #99  rst=1'b1;
        #22  rst=1'b0;
        #330 rst=1'b1;
        #22  rst=1'b0;
        #220  $finish;
    end
    // clk
    initial clk=1'b0;
    always #11 clk=~clk;
    // s0
    initial begin
        #0    s0=1'b0;
        #44   s0=1'b1;
        #88   s0=1'b0;
        #121  s0=1'b1;
        #209  s0=1'b0;
    end
    // s1
    initial begin
        #0    s1=1'b0;
        #154  s1=1'b1;
        #88   s1=1'b0;
        #22   s1=1'b1;
        #198  s1=1'b0;
    end
    // lsb_in
    initial lsb_in=1'b1;
    // msb_in
    initial msb_in=1'b1;
    // data_in
    initial data_in=4'b1111;
    // Log *vcd file for vieweing in gtkWave
    initial begin
        $dumpfile("universal_shift_reg_vcd.vcd");
        $dumpvars(0, universal_shift_reg_tb);
    end

endmodule

hw3/p1/universal_shift_reg_vcd.vcd
$date
	Tue Sep 20 14:08:03 2022
$end
$version
	Icarus Verilog
$end
$timescale
	1s
$end
$scope module universal_shift_reg_tb $end
$var wire 1 ! msb_out $end
$var wire 1 " lsb_out $end
$var wire 4 # data_out [3:0] $end
$var reg 1 $ clk $end
$var reg 4 % data_in [3:0] $end
$var reg 1 & lsb_in $end
$var reg 1 ' msb_in $end
$var reg 1 ( rst $end
$var reg 1 ) s0 $end
$var reg 1 * s1 $end
$scope module usr $end
$var wire 1 $ clk $end
$var wire 4 + data_in [3:0] $end
$var wire 1 & lsb_in $end
$var wire 1 ' msb_in $end
$var wire 1 ( rst $end
$var wire 1 ) s0 $end
$var wire 1 * s1 $end
$var wire 1 ! msb_out $end
$var wire 1 " lsb_out $end
$var reg 4 , data_out [3:0] $end
$upscope $end
$upscope $end
$enddefinitions $end
$comment Show the parameter values. $end
$dumpall
$end
#0
$dumpvars
bx ,
b1111 +
0*
0)
1(
1'
1&
b1111 %
0$
bx #
x"
x!
$end
#11
0!
0"
b0 #
b0 ,
1$
#22
0$
0(
#33
1$
#44
0$
1)
#55
1!
b1000 #
b1000 ,
1$
#66
0$
#77
b1100 #
b1100 ,
1$
#88
0$
#99
b1110 #
b1110 ,
1$
#110
0$
#121
1"
b1111 #
b1111 ,
1$
#132
0$
0)
#143
0!
0"
b0 #
b0 ,
1$
1(
#154
0$
1*
#165
1"
b1 #
b1 ,
1$
0(
#176
0$
#187
b11 #
b11 ,
1$
#198
0$
#209
b111 #
b111 ,
1$
#220
0$
#231
1!
b1111 #
b1111 ,
1$
#242
0$
0*
#253
1$
1)
#264
0$
1*
1(
#275
0!
0"
b0 #
b0 ,
1$
#286
0$
0(
#297
1!
1"
b1111 #
b1111 ,
1$
#308
0$
#319
1$
#330
0$
#341
1$
#352
0$
#363
1$
#374
0$
#385
1$
#396
0$
#407
1$
#418
0$
#429
1$
#440
0$
#451
1$
#462
0$
0*
0)
#473
1$
#484
0$
#495
1$
#506
0$
#517
1$
#528
0$
#539
1$
#550
0$
#561
1$
#572
0$
#583
1$
#594
0$
#605
1$
#616
0$
1(
#627
0!
0"
b0 #
b0 ,
1$
#638
0$
0(
